Workbook

Sheet Qualified Leads
A1: company_name | B1: company_website | C1: recipients_name | D1: recipients_email_id | E1: mail_send_from | F1: mail_send_date | G1: mail_status | H1: lead_bucket | I1: email_domain | J1: Registration No. | K1: Registered Office Address | L1: Registered Office Telephone | M1: Registered Office Fax | N1: Registered Office City | O1: Registered Office State | P1: Registered Office Pincode | Q1: Correspondence Address | R1: Correspondence Email-Id | S1: Correspondence Telephone | T1: Correspondence Fax | U1: Correspondence City | V1: Correspondence State | W1: Correspondence Pincode | X1: Validity From | Y1: Validity To | Z1: Country | AA1: Lead Type | AB1: Multi-Registered | AC1: source_category | AE1: email_type | AF1: entity_type | AG1: data_completeness_score | AH1: lead_priority_score | AJ1: duplicate_group_key | AK1: exclusion_reason | AL1: review_reason | AM1: recommended_next_step
A2: UNIFI CAPITAL PRIVATE LIMITED | C2: Anu Kaimal | D2: compliance@unificap.com | E2: pragatichothe002 | F2: 46202 | G2: Sent | H2: A - Contact First | I2: unificap.com | J2: INP000000613 | K2: NO 11, KAKANI TOWERS,, 15 KHADER NAWAZ KHAN RD, | L2: 9109633512464 | M2: 9109633512464 | N2: CHENNAI | O2: TAMIL NADU | P2: 600006 | Q2: No11 Kakani Towers 15 Khader Nawaz Khan Road Nungambakkam Chennai 600006 | U2: CHENNAI | V2: TAMIL NADU | W2: 600006 | X2: Mar 01, 2017 | Y2: Perpetual | AA2: Portfolio Manager | AB2: No | AC2: Portfolio Manager | AE2: corporate_domain | AF2: company_firm | AG2: 100 | AH2: 100 | AJ2: DOMAIN::unificap.com | AM2: Find/verify website, run accessibility scan, then outreach
A3: WAY2WEALTH BROKERS PRIVATE LTD. | C3: Sandhya Sandhya | D3: sandhya@way2wealth.com | E3: pragatichothe002 | F3: 46202 | G3: Sent | H3: A - Contact First | I3: way2wealth.com | J3: INP000000829 | K3: RUKMINI TOWERS, 3RD and 4TH FLOOR,, NO. 3 1, PLATFORM ROAD,SHESHADRIPURAM, | L3: 9108043676869 | M3: 9108043676869 | N3: BANGALORE | O3: KARNATAKA | P3: 560020 | Q3: 3rd Floor Rukmini Towers 3 bar 1 , Sheshadripuram Bengaluru 560 020 | U3: BANGALORE | V3: KARNATAKA | W3: 560020 | X3: Jun 16, 2015 | Y3: Perpetual | AA3: Portfolio Manager | AB3: No | AC3: Portfolio Manager | AE3: corporate_domain | AF3: company_firm | AG3: 100 | AH3: 100 | AJ3: DOMAIN::way2wealth.com | AM3: Find/verify website, run accessibility scan, then outreach
A4: TRUST INVESTMENT ADVISORS PVT. LTD. | C4: Aayushi Mulasi | D4: co.pms@trustgroup.in | E4: pragatichothe002 | F4: 46202 | G4: Sent | H4: A - Contact First | I4: trustgroup.in | J4: INP000001843 | K4: 109 by 110, FIRST FLOOR, BALARAMA PREMISES CO OP SOC LTD, VILLAGE PARIGKHARI, BANDRA KURLA COMPLEX, BANDRA E | L4: 9102242245053 | M4: 9102242245053 | N4: MUMBAI | O4: MAHARASHTRA | P4: 400051 | Q4: CORPORATE OFFICE NAMAN CENTRE 1101 1102, 11TH FLOOR G BLOCK C 31 BANDRA KURLA COMPLEX BANDRA EAST | U4: MUMBAI | V4: MAHARASHTRA | W4: 400051 | X4: Oct 01, 2015 | Y4: Perpetual | AA4: Portfolio Manager | AB4: No | AC4: Portfolio Manager | AE4: corporate_domain | AF4: company_firm | AG4: 100 | AH4: 100 | AJ4: DOMAIN::trustgroup.in | AM4: Find/verify website, run accessibility scan, then outreach
A5: GLOBE CAPITAL MARKET LTD. | C5: Gautam Gupta | D5: gautamgupta@globecapital.com | E5: pragatichothe002 | F5: 46202 | G5: Sent | H5: A - Contact First | I5: globecapital.com | J5: INP000002361 | K5: 609, Ansal Bhawan, 16 K.G. Marg, Connaught Place | L5: 913041230412345 | M5: 913041230412345 | N5: NEW DELHI | O5: NATIONAL CAPITAL TERRITORY OF DELHI | P5: 110001 | Q5: 609, Ansal Bhawan, 16 K.G. Marg, Connaught Place | U5: NEW DELHI | V5: NATIONAL CAPITAL TERRITORY OF DELHI | W5: 110001 | X5: Oct 21, 2016 | Y5: Perpetual | AA5: Portfolio Manager | AB5: No | AC5: Portfolio Manager | AE5: corporate_domain | AF5: company_firm | AG5: 100 | AH5: 100 | AJ5: DOMAIN::globecapital.com | AM5: Find/verify website, run accessibility scan, then outreach
A6: ALFACCURATE ADVISORS PVT. LTD. | C6: Bhushan Koli | D6: bhushankoli@alfaccurate.com | E6: pragatichothe002 | F6: 46202 | G6: Sent | H6: A - Contact First | I6: alfaccurate.com | J6: INP000003419 | K6: 503, 5th Floor, B Wing Naman Midtown, Senapati Bapat Marg, Elphinstone Road | L6: 9122042360300 | M6: 9122042360333 | N6: MUMBAI | O6: MAHARASHTRA | P6: 400013 | Q6: 503, 5th Floor, B Wing Naman Midtown, Senapati Bapat Marg, Elphinstone Road | U6: MUMBAI | V6: MAHARASHTRA | W6: 400013 | X6: Sep 22, 2015 | Y6: Perpetual | AA6: Portfolio Manager | AB6: No | AC6: Portfolio Manager | AE6: corporate_domain | AF6: company_firm | AG6: 100 | AH6: 100 | AJ6: DOMAIN::alfaccurate.com | AM6: Find/verify website, run accessibility scan, then outreach
A7: RIGHT HORIZONS PORTFOLIO MANAGEMENT PRIVATE LIMITED | C7: Sandeep Goyal | D7: skg@righthorizons.com | G7: Sent | H7: A - Contact First | I7: righthorizons.com | J7: INP000004359 | K7: No 6 2nd Main Road Aerekere, Bannerghatta Road | L7: 910808050593005 | M7: 910808050593005 | N7: BANGALORE | O7: KARNATAKA | P7: 560076 | Q7: No 6 2nd Main Road Arekere, Bannerghatta Road | U7: BANGALORE | V7: KARNATAKA | W7: 560076 | X7: Aug 06, 2015 | Y7: Perpetual | AA7: Portfolio Manager | AB7: No | AC7: Portfolio Manager | AE7: corporate_domain | AF7: company_firm | AG7: 100 | AH7: 100 | AJ7: DOMAIN::righthorizons.com | AM7: Find/verify website, run accessibility scan, then outreach
A8: EMKAY INVESTMENT MANAGERS LIMITED | C8: Arvind Tankkar | D8: compliance@emkayglobal.com | E8: pragatichothe002 | F8: 46202 | G8: Sent | H8: A - Contact First | I8: emkayglobal.com | J8: INP000004458 | K8: The Ruby, 7th Floor,, Senapati Bapat Marg, Dadar W, | L8: 9102266299299 | M8: 9102266299299 | N8: MUMBAI | O8: MAHARASHTRA | P8: 400028 | Q8: C 6, Ground Floor, Paragon Center, P.B. Marg, Opp. Century Mills, Worli, | U8: MUMBAI | V8: MAHARASHTRA | W8: 400013 | X8: Mar 16, 2015 | Y8: Perpetual | AA8: Portfolio Manager | AB8: No | AC8: Portfolio Manager | AE8: corporate_domain | AF8: company_firm | AG8: 100 | AH8: 100 | AJ8: DOMAIN::emkayglobal.com | AM8: Find/verify website, run accessibility scan, then outreach
A9: 360 ONE Asset Management Limited | C9: Chinmayi Wagle | D9: pmscompliance@360.one | E9: pragatichothe002 | F9: 46202 | G9: Sent | H9: A - Contact First | I9: 360.one | J9: INP000004565 | K9: 6th Floor, IIFL Centre, Kamala City,, Senapati Bapat Marg, Lower Parel, | L9: 9102248765496 | M9: 9102248765496 | N9: MUMBAI | O9: MAHARASHTRA | P9: 400013 | Q9: IIFL Centre, Kamala City, Senapati Bapat Marg, Lower Parel, | U9: MUMBAI | V9: MAHARASHTRA | W9: 400013 | X9: Sep 25, 2014 | Y9: Perpetual | AA9: Portfolio Manager | AB9: No | AC9: Portfolio Manager | AE9: corporate_domain | AF9: company_firm | AG9: 100 | AH9: 100 | AJ9: DOMAIN::360.one | AM9: Find/verify website, run accessibility scan, then outreach
A10: MO Alternate Investment Advisors Private Limited | C10: Naveen Gupta | D10: compliance.moalts@motilaloswal.com | E10: pragatichothe002 | F10: 46202 | G10: Sent | H10: A - Contact First | I10: motilaloswal.com | J10: INP000004920 | K10: Motilal Oswal Tower, Rahimtullah Sayani Road, Opposite Parel ST Depot, Prabhadevi, Mumbai | L10: 91227199757083948 | M10: 91227199757083948 | N10: MUMBAI | O10: MAHARASHTRA | P10: 400025 | Q10: 10th Floor Motilal Oswal Tower Jn. of Gokhale Road, and Sayani Road Prabhadevi | U10: MUMBAI | V10: MAHARASHTRA | W10: 400025 | X10: Nov 17, 2015 | Y10: Perpetual | AA10: Portfolio Manager | AB10: No | AC10: Portfolio Manager | AE10: corporate_domain | AF10: company_firm | AG10: 100 | AH10: 100 | AJ10: DOMAIN::motilaloswal.com | AM10: Find/verify website, run accessibility scan, then outreach
A11: Buglerock Capital Private Limited | C11: Bharat Sharda | D11: compliance@buglerock.asia | E11: pragatichothe002 | F11: 46202 | G11: Sent | H11: A - Contact First | I11: buglerock.asia | J11: INP000005430 | K11: Prestige Takt, 1st Floor No 23, Kasturba Road Cross, Mahatma Gandhi Road Bangalore North Bangalore | L11: 9102269251000 | N11: BANGALORE | O11: KARNATAKA | P11: 560001 | Q11: One World Center, Tower 2, Office No 802, 8th Floor, Senapati Bapat Marg, Elphinstone Road West | U11: MUMBAI | V11: MAHARASHTRA | W11: 400013 | X11: Oct 09, 2024 | Y11: Perpetual | AA11: Portfolio Manager | AB11: No | AC11: Portfolio Manager | AE11: corporate_domain | AF11: company_firm | AG11: 100 | AH11: 100 | AJ11: DOMAIN::buglerock.asia | AM11: Find/verify website, run accessibility scan, then outreach
A12: RENAISSANCE INVESTMENT MANAGERS PRIVATE LIMITED | C12: Meghana Kashte | D12: compliance@renaissanceinvest.in | E12: pragatichothe002 | F12: 46202 | G12: Sent | H12: A - Contact First | I12: renaissanceinvest.in | J12: INP000005455 | K12: Office No. 710, 7th Floor, C Wing, Mittal Commercia Premises CHS Ltd, Off. M.V. Road. Near Mittal Estate, Marol, Andheri East | L12: 9102249711561 | N12: MUMBAI | O12: MAHARASHTRA | P12: 400059 | Q12: C 710,7th Floor, Mittal Commercia Premises CHS Ltd , Off. M.V. Road, Near Mittal Estate, Andheri | U12: MUMBAI | V12: MAHARASHTRA | W12: 400059 | X12: May 30, 2017 | Y12: Perpetual | AA12: Portfolio Manager | AB12: No | AC12: Portfolio Manager | AE12: corporate_domain | AF12: company_firm | AG12: 100 | AH12: 100 | AJ12: DOMAIN::renaissanceinvest.in | AM12: Find/verify website, run accessibility scan, then outreach
A13: EUREKA PORTFOLIO MANAGEMENT SERVICES PVT LTD | C13: VIVEK KHATOR | D13: PMS@EUREKASEC.COM | E13: pragatichothe002 | F13: 46202 | G13: Sent | H13: A - Contact First | I13: eurekasec.com | J13: INP000005740 | K13: DN 51 Merlin Infinite 11th Floor, Salt Lake Sector V | L13: 9103366280000 | M13: 9103322105184 | N13: KOLKATA | O13: WEST BENGAL | P13: 700091 | Q13: DN 51 Merlin Infinite 11th Floor, Salt Lake Sector V | U13: KOLKATA | V13: WEST BENGAL | W13: 700091 | X13: Jul 19, 2017 | Y13: Perpetual | AA13: Portfolio Manager | AB13: No | AC13: Portfolio Manager | AE13: corporate_domain | AF13: company_firm | AG13: 100 | AH13: 100 | AJ13: DOMAIN::eurekasec.com | AM13: Find/verify website, run accessibility scan, then outreach
A14: SYKES & RAY EQUITIES INDIA LIMITED | C14: Sidhant Prabhu | D14: sidhant@sre.co.in | E14: pragatichothe002 | F14: 46202 | G14: Sent | H14: A - Contact First | I14: sre.co.in | J14: INP000005795 | K14: 3rd Floor, CAMA Building, , Dalal Street, Fort | L14: 9102261937408 | M14: 9102261937408 | N14: MUMBAI | O14: MAHARASHTRA | P14: 400001 | X14: Aug 11, 2017 | Y14: Perpetual | AA14: Portfolio Manager | AB14: No | AC14: Portfolio Manager | AE14: corporate_domain | AF14: company_firm | AG14: 100 | AH14: 100 | AJ14: DOMAIN::sre.co.in | AM14: Find/verify website, run accessibility scan, then outreach
A15: Asit C Mehta Investment Interrmediates Limited | C15: Jaideep Vaidya | D15: complianceofficer@acm.co.in | E15: pragatichothe002 | F15: 46202 | G15: Sent | H15: A - Contact First | I15: acm.co.in | J15: INP000005801 | K15: PANTOMATH NUCLEUS HOUSE, SAKI VIHAR ROAD ANDHERI E | L15: 02202228583333 | N15: MUMBAI | O15: MAHARASHTRA | P15: 400072 | Q15: PANTOMATH NUCLEUS HOUSE, SAKI VIHAR ROAD ANDHERI E | U15: MUMBAI | V15: MAHARASHTRA | W15: 400072 | X15: May 29, 2024 | Y15: Perpetual | AA15: Portfolio Manager | AB15: Yes | AC15: Portfolio Manager | AE15: corporate_domain | AF15: company_firm | AG15: 100 | AH15: 100 | AJ15: DOMAIN::acm.co.in | AM15: Find/verify website, run accessibility scan, then outreach
A16: 360 ONE PORTFOLIO MANAGERS LIMITED | C16: Purva Joshi | D16: regcompliance@iiflw.com | E16: pragatichothe002 | F16: 46202 | G16: Sent | H16: A - Contact First | I16: iiflw.com | J16: INP000005874 | K16: IIFL Centre, Kamala City, Senapati Bapat Marg, Lower Parel West | L16: 9102248765496 | M16: 9102248765496 | N16: MUMBAI | O16: MAHARASHTRA | P16: 400013 | Q16: IIFL Centre, Kamala City, Senapati Bapat Marg, Lower Parel, | U16: MUMBAI | V16: MAHARASHTRA | W16: 400013 | X16: Nov 28, 2017 | Y16: Perpetual | AA16: Portfolio Manager | AB16: No | AC16: Portfolio Manager | AE16: corporate_domain | AF16: company_firm | AG16: 100 | AH16: 100 | AJ16: DOMAIN::iiflw.com | AM16: Find/verify website, run accessibility scan, then outreach
A17: GREEN PORTFOLIO PRIVATE LIMITED | C17: Tamana Mahnot | D17: cs@greenportfolio.co | E17: pragatichothe002 | F17: 46202 | G17: Sent | H17: A - Contact First | I17: greenportfolio.co | J17: INP000006022 | K17: Unit No. 207, 2nd Floor, JMD Empire Square, Mehrauli Gurgaon Road, A Block, DLF Phase - I, Sector 28, Sikanderpur Ghosi | L17: 0919782027569 | M17: 0919782027569 | N17: GURUGRAM | O17: HARYANA | P17: 122002 | Q17: Farm No. 5, 1645, Kanawani Village, Indirapuram, Ghaziabad | U17: GHAZIABAD | V17: UTTAR PRADESH | W17: 201014 | X17: Jun 11, 2018 | Y17: Perpetual | AA17: Portfolio Manager | AB17: Yes | AC17: Portfolio Manager | AE17: corporate_domain | AF17: company_firm | AG17: 100 | AH17: 100 | AJ17: DOMAIN::greenportfolio.co | AM17: Find/verify website, run accessibility scan, then outreach
A18: Fort Capital Investment Advisory Private Limited | C18: NIDHI KAJI | D18: compliance@fortcapital.in | E18: pragatichothe002 | F18: 46202 | G18: Sent | H18: A - Contact First | I18: fortcapital.in | J18: INP000006031 | K18: 304, 3rd Floor, Hubtown Solaris,, N. S. Phadke Marg, Near Flyover Bridge, Andheri East, | L18: 9102269973600 | M18: 9102269973600 | N18: MUMBAI | O18: MAHARASHTRA | P18: 400069 | Q18: 304, 3rd Floor, Hubtown Solaris, N. S. Phadke Marg, Near Flyover Bridge, Andheri East, | U18: MUMBAI | V18: MAHARASHTRA | W18: 400069 | X18: Jun 13, 2018 | Y18: Perpetual | AA18: Portfolio Manager | AB18: No | AC18: Portfolio Manager | AE18: corporate_domain | AF18: company_firm | AG18: 100 | AH18: 100 | AJ18: DOMAIN::fortcapital.in | AM18: Find/verify website, run accessibility scan, then outreach
A19: Credent Asset Management Services Private Limited | C19: Preeti Sethi | D19: compliance@credentglobal.com | E19: pragatichothe002 | F19: 46202 | G19: Sent | H19: A - Contact First | I19: credentglobal.com | J19: INP000006101 | K19: 306, B2, Shubham Centre, Cardinal Gracious Road, Chakala, Andheri East | L19: 9102268452001 | M19: 9102268452001 | N19: MUMBAI | O19: MAHARASHTRA | P19: 400099 | Q19: Unit No. 609, 6th Floor, C Wing, One BKC, G Block, Bandra Kurla Complex, Bandra East | U19: MUMBAI | V19: MAHARASHTRA | W19: 400051 | X19: Dec 18, 2023 | Y19: Perpetual | AA19: Portfolio Manager | AB19: Yes | AC19: Portfolio Manager | AE19: corporate_domain | AF19: company_firm | AG19: 100 | AH19: 100 | AJ19: DOMAIN::credentglobal.com | AM19: Find/verify website, run accessibility scan, then outreach
A20: Spark Asia Impact Managers Private Limited | C20: Amrita Pillai | D20: eam.compliance@sparkcapital.in | E20: pragatichothe002 | F20: 46202 | G20: Sent | H20: A - Contact First | I20: sparkcapital.in | J20: INP000006235 | K20: No. 1, 3rd Floor, First Crescent Park Road, Gandhi Nagar, Adyar | L20: 9104469250000 | M20: 9104469250000 | N20: CHENNAI | O20: TAMIL NADU | P20: 600020 | Q20: No. 99, 2nd Floor, Senans Squaree, Santhome High Road, Santhome | U20: CHENNAI | V20: TAMIL NADU | W20: 600028 | X20: Nov 14, 2018 | Y20: Perpetual | AA20: Portfolio Manager | AB20: No | AC20: Portfolio Manager | AE20: corporate_domain | AF20: company_firm | AG20: 100 | AH20: 100 | AJ20: DOMAIN::sparkcapital.in | AM20: Find/verify website, run accessibility scan, then outreach
A21: Entrust Family Office Investment Advisors Private Limited | C21: Pradeep A N | D21: compliance@entrust.co.in | E21: pragatichothe002 | F21: 46202 | G21: Sent | H21: A - Contact First | I21: entrust.co.in | J21: INP000006314 | K21: No.24, 4th Floor, 1st Cross, Magrath Road, | L21: 9108041479777 | M21: 9108041479777 | N21: BANGALORE | O21: KARNATAKA | P21: 560025 | Q21: No.24,4th Floor, 1st Cross, Magrath Road | U21: BANGALORE | V21: KARNATAKA | W21: 560025 | X21: Dec 11, 2018 | Y21: Perpetual | AA21: Portfolio Manager | AB21: No | AC21: Portfolio Manager | AE21: corporate_domain | AF21: company_firm | AG21: 100 | AH21: 100 | AJ21: DOMAIN::entrust.co.in | AM21: Find/verify website, run accessibility scan, then outreach
A22: CONCEPT INVESTWELL PRIVATE LIMITED | C22: NIRAV DESAI | D22: compliance@conceptinvestwell.com | E22: pragatichothe002 | F22: 46202 | G22: Sent | H22: A - Contact First | I22: conceptinvestwell.com | J22: INP000006323 | K22: 10 A UNION HEIGHTS , MAHARANA PRATAP ROAD, RAHUL RAJ MALL LANE,DUMAS ROAD | L22: 9102612206026 | M22: 9102612206026 | N22: SURAT | O22: GUJARAT | P22: 395007 | Q22: 10 A UNION HEIGHTS, MAHARANA PRATAP ROAD, RAHUL RAJJ MALL, | U22: SURAT | V22: GUJARAT | W22: 395007 | X22: Dec 13, 2018 | Y22: Perpetual | AA22: Portfolio Manager | AB22: No | AC22: Portfolio Manager | AE22: corporate_domain | AF22: company_firm | AG22: 100 | AH22: 100 | AJ22: DOMAIN::conceptinvestwell.com | AM22: Find/verify website, run accessibility scan, then outreach
A23: WEALTH FIRST PORTFOLIO MANAGERS LIMITED | C23: NIKHIL JAIN | D23: nikhil@wealthfirst.biz | E23: pragatichothe002 | F23: 46202 | G23: Sent | H23: A - Contact First | I23: wealthfirst.biz | J23: INP000006332 | K23: CAPITOL HOUSE, 10 PARAS-II, NEAR CAMPUS CORNER,, PRAHALADNAGAR, ANANDNAGAR, ABD 380015 | L23: 07907940240000 | M23: 07907940240000 | N23: AHMEDABAD | O23: GUJARAT | P23: 380015 | Q23: CAPITOL HOUSE, 10 PARAS-II, NEAR CAMPUS CORNER, PRAHALADNAGAR, ANANDNAGAR, ABD 380015 | U23: AHMEDABAD | V23: GUJARAT | W23: 380015 | X23: Dec 21, 2018 | Y23: Perpetual | AA23: Portfolio Manager | AB23: No | AC23: Portfolio Manager | AE23: corporate_domain | AF23: company_firm | AG23: 100 | AH23: 100 | AJ23: DOMAIN::wealthfirst.biz | AM23: Find/verify website, run accessibility scan, then outreach
A24: M/S.ASTEYA INVESTMENT MANAGERS LLP, | C24: Poonam Rawal | D24: poonam.rawal@asteyaglobal.com | E24: pragatichothe002 | F24: 46202 | G24: Sent | H24: A - Contact First | I24: asteyaglobal.com | J24: INP000006536 | K24: Office no.110, 1st floor, Keshava Building, Plot No C-5,, E Block, Bandra Kurla Complex, Bandra East | L24: 9102226514252 | M24: 9102226514252 | N24: MUMBAI | O24: MAHARASHTRA | P24: 400051 | Q24: Office no.110, 1st floor, Keshava Building, Plot No C-5, E Block, Bandra Kurla Complex, Bandra East | U24: MUMBAI | V24: MAHARASHTRA | W24: 400051 | X24: Apr 01, 2019 | Y24: Perpetual | AA24: Portfolio Manager | AB24: No | AC24: Portfolio Manager | AE24: corporate_domain | AF24: company_firm | AG24: 100 | AH24: 100 | AJ24: DOMAIN::asteyaglobal.com | AM24: Find/verify website, run accessibility scan, then outreach
A25: COMPOUND EVERYDAY CAPITAL MANAGEMENT LLP | C25: Arpit Parmar | D25: arpit.parmar@cedcapital.in | E25: pragatichothe002 | F25: 46202 | G25: Sent | H25: A - Contact First | I25: cedcapital.in | J25: INP000006633 | K25: Sakar Bhawan, 2nd Floor, ATM Side, 21/4 Ratlam Kothi Main Road, Above Federal Bank | L25: 9107312510070 | M25: 9107312510070 | N25: INDORE | O25: MADHYA PRADESH | P25: 452001 | Q25: Sakar Bhawan, 2nd Floor, ATM Side, 21/4 Ratlam Kothi Main Road, Above Federal Bank | U25: INDORE | V25: MADHYA PRADESH | W25: 452001 | X25: Apr 11, 2019 | Y25: Perpetual | AA25: Portfolio Manager | AB25: No | AC25: Portfolio Manager | AE25: corporate_domain | AF25: company_firm | AG25: 100 | AH25: 100 | AJ25: DOMAIN::cedcapital.in | AM25: Find/verify website, run accessibility scan, then outreach
A26: First Global Finance Pvt Ltd | C26: Mahima Vyas | D26: compliance@firstglobal.in | E26: pragatichothe002 | F26: 46202 | G26: Sent | H26: A - Contact First | I26: firstglobal.in | J26: INP000006697 | K26: 1st Floor, Ratnam Square, Plot No. 38 39, Sector 19A, Sector 19A, Vashi, | L26: 91222261166525 | N26: NAVI MUMBAI | O26: MAHARASHTRA | P26: 110001 | Q26: Ratnam Square, Plot No. 38 39, Sector 19A, Vashi | U26: NAVI MUMBAI | V26: MAHARASHTRA | W26: 400703 | X26: Apr 23, 2019 | Y26: Perpetual | AA26: Portfolio Manager | AB26: No | AC26: Portfolio Manager | AE26: corporate_domain | AF26: company_firm | AG26: 100 | AH26: 100 | AJ26: DOMAIN::firstglobal.in | AM26: Find/verify website, run accessibility scan, then outreach
A27: SMC Global Securities Limited | C27: Vikas Sethi | D27: vikassethi@smcindiaonline.com | E27: pragatichothe002 | F27: 46202 | G27: Sent | H27: A - Contact First | I27: smcindiaonline.com | J27: INP000006703 | K27: 11/6B, Shanti Chambers Pusa Road, New Delhi | L27: 91111130111000 | M27: 91111130111000 | N27: NEW DELHI | O27: NATIONAL CAPITAL TERRITORY OF DELHI | P27: 110005 | Q27: 11/6B, Shanti Chambers Pusa Road, New Delhi | U27: NEW DELHI | V27: NATIONAL CAPITAL TERRITORY OF DELHI | W27: 110005 | X27: Apr 26, 2019 | Y27: Perpetual | AA27: Portfolio Manager | AB27: No | AC27: Portfolio Manager | AE27: corporate_domain | AF27: company_firm | AG27: 100 | AH27: 100 | AJ27: DOMAIN::smcindiaonline.com | AM27: Find/verify website, run accessibility scan, then outreach
A28: TURTLE WEALTH MANAGEMENT PVT. LTD. | C28: Vibhati Arya | D28: vibhati@turtlewealth.in | E28: pragatichothe002 | F28: 46202 | G28: Sent | H28: A - Contact First | I28: turtlewealth.in | J28: INP000006758 | K28: 1001 Rajhans Montessa, B/S Le Meridien Hotel , Dumas Road, Magdalla | L28: 91919925238849 | M28: 91919925238849 | N28: SURAT | O28: GUJARAT | P28: 395007 | Q28: 1001 Rajhans Montessa, B/S Le Meridien Hotel , Dumas Road, Magdalla | U28: SURAT | V28: GUJARAT | W28: 395007 | X28: May 08, 2019 | Y28: Perpetual | AA28: Portfolio Manager | AB28: No | AC28: Portfolio Manager | AE28: corporate_domain | AF28: company_firm | AG28: 100 | AH28: 100 | AJ28: DOMAIN::turtlewealth.in | AM28: Find/verify website, run accessibility scan, then outreach
A29: JAINAM BROKING LIMITED | C29: Vidhi Parikh | D29: vidhi.parikh@jainam.in | E29: pragatichothe002 | F29: 46202 | G29: Sent | H29: A - Contact First | I29: jainam.in | J29: INP000006785 | K29: JAINAM HOUSE, NEW PASSPORT OFFICE ROAD,, PIPLOD | L29: 09102616725556 | M29: 09102616725556 | N29: SURAT | O29: GUJARAT | P29: 395007 | Q29: JAINAM HOUSE, NEW PASSPORT OFFICE ROAD, PIPLOD | U29: SURAT | V29: GUJARAT | W29: 395007 | X29: Jun 27, 2019 | Y29: Perpetual | AA29: Portfolio Manager | AB29: Yes | AC29: Portfolio Manager | AE29: corporate_domain | AF29: company_firm | AG29: 100 | AH29: 100 | AJ29: DOMAIN::jainam.in | AM29: Find/verify website, run accessibility scan, then outreach
A30: Altlnvest Capital Advisors Private Limited | C30: Hashim Khan | D30: invest@propsharecapital.com | E30: pragatichothe002 | F30: 46202 | G30: Sent | H30: A - Contact First | I30: propsharecapital.com | J30: INP000006800 | K30: 10th Floor, SKAV Seethalakshmi, 21/22, Kasturba Road | L30: 9108041692999 | N30: BANGALORE | O30: KARNATAKA | P30: 560001 | Q30: 10th Floor, SKAV Seethalakshmi, 21/22, Kasturba Road | U30: BANGALORE | V30: KARNATAKA | W30: 560001 | X30: Jun 28, 2019 | Y30: Perpetual | AA30: Portfolio Manager | AB30: No | AC30: Portfolio Manager | AE30: corporate_domain | AF30: company_firm | AG30: 100 | AH30: 100 | AJ30: DOMAIN::propsharecapital.com | AM30: Find/verify website, run accessibility scan, then outreach
A31: Julius Baer Wealth Advisors India Private Limited | C31: Purva Joshi | D31: purva.joshi@juliusbaer.com | E31: pragatichothe002 | F31: 46202 | G31: Sent | H31: A - Contact First | I31: juliusbaer.com | J31: INP000007012 | K31: Altimus, 2501, 25th level,, Pandurang Budhkar Marg, Worli | L31: 9102261760184 | M31: 9102261760184 | N31: MUMBAI | O31: MAHARASHTRA | P31: 400018 | Q31: Altimus, 2501, 25th level, Pandurang Budhkar Marg, Worli | U31: MUMBAI | V31: MAHARASHTRA | W31: 400018 | X31: Jul 14, 2020 | Y31: Perpetual | AA31: Portfolio Manager | AB31: No | AC31: Portfolio Manager | AE31: corporate_domain | AF31: company_firm | AG31: 100 | AH31: 100 | AJ31: DOMAIN::juliusbaer.com | AM31: Find/verify website, run accessibility scan, then outreach
A32: Purnartha Investment Advisers Pvt.Ltd. | C32: AMOL DEO | D32: amol.d@purnartha.com | E32: pragatichothe002 | F32: 46202 | G32: Sent | H32: A - Contact First | I32: purnartha.com | J32: INP000007021 | K32: Rachna Bungalow Dr Kelkar Road, Off Karve Road Erandwane | L32: 9102049127100 | N32: PUNE | O32: MAHARASHTRA | P32: 411004 | Q32: Rachna Bungalow Dr Kelkar Road, Off Karve Road Erandwane | U32: PUNE | V32: MAHARASHTRA | W32: 411004 | X32: Jul 23, 2020 | Y32: Perpetual | AA32: Portfolio Manager | AB32: Yes | AC32: Portfolio Manager | AE32: corporate_domain | AF32: company_firm | AG32: 100 | AH32: 100 | AJ32: DOMAIN::purnartha.com | AM32: Find/verify website, run accessibility scan, then outreach
A33: EQUIRUS WEALTH PRIVATE LIMITED | C33: JINESHA MEHTA | D33: equirus_compliance@equirus.com | E33: pragatichothe002 | F33: 46202 | G33: Sent | H33: A - Contact First | I33: equirus.com | J33: INP000007076 | K33: A1303MarathonFuturexMafatlalMillsCompound , NMJOSHIMARGLOWERPAREL | L33: 9107961909586 | M33: 9107961909586 | N33: MUMBAI | O33: MAHARASHTRA | P33: 400013 | Q33: 3RD FLOOR HOUSE NO 9 MAGNET CORPORATE PARK, B/H INTAS SOLA BRIDGE S G HIGHWAY THALTEJ | U33: AHMEDABAD | V33: GUJARAT | W33: 380054 | X33: Oct 06, 2020 | Y33: Perpetual | AA33: Portfolio Manager | AB33: No | AC33: Portfolio Manager | AE33: corporate_domain | AF33: company_firm | AG33: 100 | AH33: 100 | AJ33: DOMAIN::equirus.com | AM33: Find/verify website, run accessibility scan, then outreach
A34: CKREDENCE WEALTH MANAGEMENT PRIVATE LIMITED | C34: PRAKASHKUMAR MAVANI | D34: PRAKASH.MAVANI@CKREDENCEWEALTH.COM | E34: pragatichothe002 | F34: 46202 | G34: Sent | H34: A - Contact First | I34: ckredencewealth.com | J34: INP000007164 | K34: 901,902,903, International Wealth Center, VIP Road, Vesu | L34: 9102614084406 | M34: 9102614084406 | N34: SURAT | O34: GUJARAT | P34: 395007 | X34: Feb 26, 2021 | Y34: Perpetual | AA34: Portfolio Manager | AB34: Yes | AC34: Portfolio Manager | AE34: corporate_domain | AF34: company_firm | AG34: 100 | AH34: 100 | AJ34: DOMAIN::ckredencewealth.com | AM34: Find/verify website, run accessibility scan, then outreach
A35: Arthya Wealth and Investments Pvt Ltd | C35: Nasreen Qureshi | D35: nasreen@arthyawealth.com | E35: pragatichothe002 | F35: 46202 | G35: Sent | H35: A - Contact First | I35: arthyawealth.com | J35: INP000007225 | K35: 712 THE SUMMIT BUSINESS BAY, 7th Floor, Near Western Express Highway, Off Andheri Kurla Road, Andheri East | L35: 910009819793096 | M35: 910009819793096 | N35: MUMBAI | O35: MAHARASHTRA | P35: 400069 | Q35: 712 THE SUMMIT BUSINESS BAY, 7th Floor, Near Western Express Highway, Off Andheri Kurla Road, Andheri East | U35: MUMBAI | V35: MAHARASHTRA | W35: 400069 | X35: Jun 09, 2021 | Y35: Perpetual | AA35: Portfolio Manager | AB35: No | AC35: Portfolio Manager | AE35: corporate_domain | AF35: company_firm | AG35: 100 | AH35: 100 | AJ35: DOMAIN::arthyawealth.com | AM35: Find/verify website, run accessibility scan, then outreach
A36: Pioneer Client Associates Private Limited | C36: Rakesh Khanna | D36: rakeshkhanna@clientassociates.com | E36: pragatichothe002 | F36: 46202 | G36: Sent | H36: A - Contact First | I36: clientassociates.com | J36: INP100007231 | K36: 2nd Floor, Block B, Vatika Towers, Golf Course Road,, Sector 54 | L36: 9112404995400 | N36: GURGAON | O36: HARYANA | P36: 122002 | Q36: 2nd Floor, Block B, Vatika Towers, Golf Course Road, Sector 54 | U36: GURGAON | V36: HARYANA | W36: 122002 | X36: Jun 29, 2021 | Y36: Perpetual | AA36: Portfolio Manager | AB36: No | AC36: Portfolio Manager | AE36: corporate_domain | AF36: company_firm | AG36: 100 | AH36: 100 | AJ36: DOMAIN::clientassociates.com | AM36: Find/verify website, run accessibility scan, then outreach
A37: DEZERV INVESTMENTS PRIVATE LIMITED | C37: Kavita Khatri | D37: kavita.khatri@dezerv.in | E37: pragatichothe001 | F37: 46202 | G37: Sent | H37: A - Contact First | I37: dezerv.in | J37: INP000007377 | K37: Unit No. 301, Trade Centre, Bandra East | L37: 910009167830754 | M37: 910009167830754 | N37: MUMBAI | O37: MAHARASHTRA | P37: 400051 | Q37: Unit No. 301, Trade Centre, Bandra East | U37: MUMBAI | V37: MAHARASHTRA | W37: 400051 | X37: Mar 24, 2022 | Y37: Perpetual | AA37: Portfolio Manager | AB37: No | AC37: Portfolio Manager | AE37: corporate_domain | AF37: company_firm | AG37: 100 | AH37: 100 | AJ37: DOMAIN::dezerv.in | AM37: Find/verify website, run accessibility scan, then outreach
A38: WhiteOak Capital Asset Management Limited | C38: Prannav Shah | D38: prannav.shah@whiteoakinvestors.com | E38: pragatichothe001 | F38: 46202 | G38: Sent | H38: A - Contact First | I38: whiteoakinvestors.com | J38: INP000007766 | K38: Unit No. B4, 6th Floor, Cnergy, Appasaheb Marathe Marg, Prabhadevi | L38: 00002269463518 | M38: 00002269463518 | N38: MUMBAI | O38: MAHARASHTRA | P38: 400025 | Q38: Unit No. B4, 6th Floor, Cnergy, Appasaheb Marathe Marg, Prabhadevi | U38: MUMBAI | V38: MAHARASHTRA | W38: 400025 | X38: Jan 13, 2023 | Y38: Perpetual | AA38: Portfolio Manager | AB38: No | AC38: Portfolio Manager | AE38: corporate_domain | AF38: company_firm | AG38: 100 | AH38: 100 | AJ38: DOMAIN::whiteoakinvestors.com | AM38: Find/verify website, run accessibility scan, then outreach
A39: SINCERE SYNDICATION AND CORPORATE SERVICES LLP | C39: Sudharshan S | D39: Sudarshan@sinceresyndication.com | E39: pragatichothe001 | F39: 46202 | G39: Sent | H39: A - Contact First | I39: sinceresyndication.com | J39: INP200007803 | K39: Adwave Towers, 3rd Floor, Block A,, No.9, South Boag Road, T. Nagar | L39: 004445546075 | M39: 004445546075 | N39: CHENNAI | O39: TAMIL NADU | P39: 600017 | Q39: Adwave Towers, 3rd Floor, Block A, No.9, South Boag Road, T. Nagar | U39: CHENNAI | V39: TAMIL NADU | W39: 600017 | X39: Jan 31, 2023 | Y39: Perpetual | AA39: Portfolio Manager | AB39: Yes | AC39: Portfolio Manager | AE39: corporate_domain | AF39: company_firm | AG39: 100 | AH39: 100 | AJ39: DOMAIN::sinceresyndication.com | AM39: Find/verify website, run accessibility scan, then outreach
A40: Waterfield Financial and Investment Advisors Private Limited | C40: Shilpa Dadhich | D40: shilpa.dadhich@waterfieldadvisors.com | E40: pragatichothe001 | F40: 46202 | G40: Sent | H40: A - Contact First | I40: waterfieldadvisors.com | J40: INP000007818 | K40: 142 Maker Chamber VI , 220 Jamnalal Bajaj Marg Nariman Point | L40: 000919987538394 | M40: 000919987538394 | N40: MUMBAI | O40: MAHARASHTRA | P40: 400021 | Q40: 142 Maker Chamber VI , 220 Jamnalal Bajaj Marg Nariman Point | U40: MUMBAI | V40: MAHARASHTRA | W40: 400021 | X40: Feb 14, 2023 | Y40: Perpetual | AA40: Portfolio Manager | AB40: No | AC40: Portfolio Manager | AE40: corporate_domain | AF40: company_firm | AG40: 100 | AH40: 100 | AJ40: DOMAIN::waterfieldadvisors.com | AM40: Find/verify website, run accessibility scan, then outreach
A41: ASK Wealth Advisors Private Limited | C41: Vinita Taparia | D41: vinita.taparia@askwealthadvisors.com | E41: pragatichothe001 | F41: 46202 | G41: Not delivered | H41: A - Contact First | I41: askwealthadvisors.com | J41: INP000007827 | K41: Birla Aurora, 16 Level, Office Floor 9 , Dr. Annie Besant Road, Worli | L41: 9102266132887 | M41: 9102266132887 | N41: MUMBAI | O41: MAHARASHTRA | P41: 400030 | Q41: One Lodha Place, Unit No. 2803, 2804, 2805, Senpati Bapat Marg, Lower Parel | U41: MUMBAI | V41: MAHARASHTRA | W41: 400013 | X41: Feb 14, 2023 | Y41: Perpetual | AA41: Portfolio Manager | AB41: Yes | AC41: Portfolio Manager | AE41: corporate_domain | AF41: company_firm | AG41: 100 | AH41: 100 | AJ41: DOMAIN::askwealthadvisors.com | AM41: Find/verify website, run accessibility scan, then outreach
A42: DRCHOKSEY FINSERV PRIVATE LIMITED | C42: NIRALI SHAH | D42: pmscompliance@devenchoksey.com | E42: pragatichothe001 | F42: 46202 | G42: Sent | H42: A - Contact First | I42: devenchoksey.com | J42: INP000007906 | K42: 5TH FLOOR ABHISHEK BUILDING BEHIND MONGINIS CAKE FACTORY , OFF NEW LINK ROAD ANDHERI WEST | L42: 0002266965555 | M42: 0002266965555 | N42: MUMBAI | O42: MAHARASHTRA | P42: 400053 | Q42: 5TH FLOOR ABHISHEK BUILDING BEHIND MONGINIS CAKE FACTORY , OFF NEW LINK ROAD ANDHERI WEST | U42: MUMBAI | V42: MAHARASHTRA | W42: 400053 | X42: Mar 13, 2023 | Y42: Perpetual | AA42: Portfolio Manager | AB42: Yes | AC42: Portfolio Manager | AE42: corporate_domain | AF42: company_firm | AG42: 100 | AH42: 100 | AJ42: DOMAIN::devenchoksey.com | AM42: Find/verify website, run accessibility scan, then outreach
A43: Tamohara Investment Managers Private Limited | C43: Rajesh Kodnaney | D43: rajesh@tamohara.net | E43: pragatichothe001 | F43: 46202 | G43: Sent | H43: A - Contact First | I43: tamohara.net | J43: INP000008020 | K43: 1402, Peninsula Park,Off Veera Desai Road, Andheri West | L43: 910229769644474 | M43: 910229769644474 | N43: MUMBAI | O43: MAHARASHTRA | P43: 400053 | Q43: 1402,Peninsula Park,Off Veera Desai Road,Andheri West | U43: MUMBAI | V43: MAHARASHTRA | W43: 400053 | X43: Apr 13, 2023 | Y43: Perpetual | AA43: Portfolio Manager | AB43: Yes | AC43: Portfolio Manager | AE43: corporate_domain | AF43: company_firm | AG43: 100 | AH43: 100 | AJ43: DOMAIN::tamohara.net | AM43: Find/verify website, run accessibility scan, then outreach
A44: Swastika Investmart Limited | C44: Dimple Soni | D44: compliance@swastika.co.in | E44: pragatichothe001 | F44: 46202 | G44: Sent | H44: A - Contact First | I44: swastika.co.in | J44: INP000008181 | K44: Office No. 104, 1st Floor, KESHAVA Commercial Building, Plot No. C5, E Block, Bandra Kurla Complex, Opp GST Bhavan, Bandra East | L44: 9107316644244 | M44: 9107316644244 | N44: MUMBAI | O44: MAHARASHTRA | P44: 400051 | Q44: 48 , Jaora Compound , M.Y. Hospital Road | U44: INDORE | V44: MADHYA PRADESH | W44: 452001 | X44: Jul 04, 2023 | Y44: Perpetual | AA44: Portfolio Manager | AB44: Yes | AC44: Portfolio Manager | AE44: corporate_domain | AF44: company_firm | AG44: 100 | AH44: 100 | AJ44: DOMAIN::swastika.co.in | AM44: Find/verify website, run accessibility scan, then outreach
A45: Citrus Advisors Private Limited | C45: Neel Visaria | D45: neel.visaria@citrusadvisors.com | E45: pragatichothe001 | F45: 46202 | G45: Sent | H45: A - Contact First | I45: citrusadvisors.com | J45: INP000008206 | K45: 2B/2, Neptune Apts Chs Ltd, Juhu Tara Road,Santacruz West | L45: 910227738604454 | M45: 910227738604454 | N45: MUMBAI | O45: MAHARASHTRA | P45: 400049 | Q45: Plot No.116, Sector 21,Kharghar,Near ISKCON Temple, Opp Bhagwati Gardens,Navi Mumbai | U45: MUMBAI | V45: MAHARASHTRA | W45: 410210 | X45: Jul 21, 2023 | Y45: Perpetual | AA45: Portfolio Manager | AB45: Yes | AC45: Portfolio Manager | AE45: corporate_domain | AF45: company_firm | AG45: 100 | AH45: 100 | AJ45: DOMAIN::citrusadvisors.com | AM45: Find/verify website, run accessibility scan, then outreach
A46: Aavishkaar Advisors Private Limited | C46: Shyamkant Joshi | D46: accountsavms@aavishkaar.in | E46: pragatichothe001 | F46: 46202 | G46: Sent | H46: A - Contact First | I46: aavishkaar.in | J46: INP000008224 | K46: Unit no 202, 203, 204, 2nd floor, Naman Centre, G Block, Bandra Kurla Complex, Bandra East | L46: 91222261248900 | M46: 91222261248900 | N46: MUMBAI | O46: MAHARASHTRA | P46: 400051 | Q46: Unit no 202, 203, 204, 2nd floor, Naman Centre, G Block, Bandra Kurla Complex, Bandra East | U46: MUMBAI | V46: MAHARASHTRA | W46: 400051 | X46: Aug 07, 2023 | Y46: Perpetual | AA46: Portfolio Manager | AB46: No | AC46: Portfolio Manager | AE46: corporate_domain | AF46: company_firm | AG46: 100 | AH46: 100 | AJ46: DOMAIN::aavishkaar.in | AM46: Find/verify website, run accessibility scan, then outreach
A47: Caspian Impact Investment Adviser Private Limited | C47: Ruchi Mehta | D47: caspiancompliance@caspian.in | E47: pragatichothe001 | F47: 46202 | G47: Sent | H47: A - Contact First | I47: caspian.in | J47: INP000008358 | K47: Block 4A 4th floor Ventureast Plaza Plot No 40 and 41, Financial District Gachibowli | L47: 9104066297100 | M47: 9104066465884 | N47: HYDERABAD | O47: TELANGANA | P47: 500032 | Q47: Block 4A 4th floor Ventureast Plaza Plot No 40 and 41, Financial District Gachibowli | U47: HYDERABAD | V47: TELANGANA | W47: 500032 | X47: Nov 10, 2023 | Y47: Perpetual | AA47: Portfolio Manager | AB47: No | AC47: Portfolio Manager | AE47: corporate_domain | AF47: company_firm | AG47: 100 | AH47: 100 | AJ47: DOMAIN::caspian.in | AM47: Find/verify website, run accessibility scan, then outreach
A48: LGT Wealth India Private Limited | C48: Prem Choudhary | D48: compliance@lgtindia.in | E48: pragatichothe001 | F48: 46202 | G48: Sent | H48: A - Contact First | I48: lgtindia.in | J48: INP000008376 | K48: 7th Floor, A Block, Shiv Sagar Estate, Worli | L48: 9102250941000 | N48: MUMBAI | O48: MAHARASHTRA | P48: 400018 | Q48: 7th Floor, A Block, Shiv Sagar Estate, Worli | U48: MUMBAI | V48: MAHARASHTRA | W48: 400018 | X48: Nov 23, 2023 | Y48: Perpetual | AA48: Portfolio Manager | AB48: No | AC48: Portfolio Manager | AE48: corporate_domain | AF48: company_firm | AG48: 100 | AH48: 100 | AJ48: DOMAIN::lgtindia.in | AM48: Find/verify website, run accessibility scan, then outreach
A49: InvesQ Investment Managers LLP | C49: Rohitkumar Gajbhiye | D49: pmsadmin@invesq.in | E49: pragatichothe001 | F49: 46202 | G49: Sent | H49: A - Contact First | I49: invesq.in | J49: INP000008507 | K49: S N 135 1 Plot H 2 B 302, Swarnavilas Building Behind Ven Construction Office , Baner Pashan Link Road Pashan | L49: 910209881525064 | N49: PUNE | O49: MAHARASHTRA | P49: 411021 | Q49: 101 Harmony Opp Mauli Petrol Pump, Baner Road Baner | U49: PUNE | V49: MAHARASHTRA | W49: 411045 | X49: Jan 03, 2024 | Y49: Perpetual | AA49: Portfolio Manager | AB49: No | AC49: Portfolio Manager | AE49: corporate_domain | AF49: company_firm | AG49: 100 | AH49: 100 | AJ49: DOMAIN::invesq.in | AM49: Find/verify website, run accessibility scan, then outreach
A50: CX ADVISORS LLP | C50: Vinayak Shenvi | D50: vinayak@cxpartners.in | E50: pragatichothe001 | F50: 46202 | G50: Sent | H50: A - Contact First | I50: cxpartners.in | J50: INP000008525 | K50: Atelier Level 1 Suite No 3 Worldmark 2, Aerocity | L50: 001147640000 | M50: 001147640000 | N50: NEW DELHI | O50: NATIONAL CAPITAL TERRITORY OF DELHI | P50: 110037 | Q50: Atelier Level 1 Suite No 3 Worldmark 2, Aerocity | U50: NEW DELHI | V50: NATIONAL CAPITAL TERRITORY OF DELHI | W50: 110037 | X50: Jan 09, 2024 | Y50: Perpetual | AA50: Portfolio Manager | AB50: No | AC50: Portfolio Manager | AE50: corporate_domain | AF50: company_firm | AG50: 100 | AH50: 100 | AJ50: DOMAIN::cxpartners.in | AM50: Find/verify website, run accessibility scan, then outreach
A51: Almondz Financial Services Limited | C51: Pragati Gholap | D51: pragati.gholap@almondz.com | E51: pragatichothe001 | F51: 46202 | G51: Sent | H51: A - Contact First | I51: almondz.com | J51: INP000008589 | K51: F-33/3, Okhla Industrial Area, Phase II | L51: 9101143500700 | M51: 9101143500700 | N51: NEW DELHI | O51: NATIONAL CAPITAL TERRITORY OF DELHI | P51: 110020 | Q51: F-33/3, Okhla Industrial Area, Phase II | U51: NEW DELHI | V51: NATIONAL CAPITAL TERRITORY OF DELHI | W51: 110020 | X51: Feb 09, 2024 | Y51: Perpetual | AA51: Portfolio Manager | AB51: Yes | AC51: Portfolio Manager | AE51: corporate_domain | AF51: company_firm | AG51: 100 | AH51: 100 | AJ51: DOMAIN::almondz.com | AM51: Find/verify website, run accessibility scan, then outreach
A52: Progressive Share Brokers Private Limited | C52: Neha Oza | D52: pms@progressiveshares.com | E52: pragatichothe001 | F52: 46202 | G52: Sent | H52: A - Contact First | I52: progressiveshares.com | J52: INP000008817 | K52: 122, 123,124, 1st Floor, Laxmi Plaza, Laxmi Industrial Estate, New Link Road, Andheri West | L52: 00002240777500 | N52: MUMBAI | O52: MAHARASHTRA | P52: 400053 | Q52: 122, 123,124, 1st Floor, Laxmi Plaza, Laxmi Industrial Estate, New Link Road, Andheri West | U52: MUMBAI | V52: MAHARASHTRA | W52: 400053 | X52: Jul 15, 2024 | Y52: Perpetual | AA52: Portfolio Manager | AB52: No | AC52: Portfolio Manager | AE52: corporate_domain | AF52: company_firm | AG52: 100 | AH52: 100 | AJ52: DOMAIN::progressiveshares.com | AM52: Find/verify website, run accessibility scan, then outreach
A53: Equentis Wealth Advisory Services Limited | C53: Rakesh Gupta | D53: pmscompliance@equentis.com | E53: pragatichothe001 | F53: 46202 | G53: Sent | H53: A - Contact First | I53: equentis.com | J53: INP000008969 | K53: A603, Marathon Futurex, Mafatlal Mills Compound, N M Joshi Marg, Lower Parel E, Mumbai | L53: 00002261013800 | N53: MUMBAI | O53: MAHARASHTRA | P53: 400013 | Q53: A603, Marathon Futurex, Mafatlal Mills Compound, N M Joshi Marg, Lower Parel E, Mumbai | U53: MUMBAI | V53: MAHARASHTRA | W53: 400013 | X53: Sep 09, 2024 | Y53: Perpetual | AA53: Portfolio Manager | AB53: No | AC53: Portfolio Manager | AE53: corporate_domain | AF53: company_firm | AG53: 100 | AH53: 100 | AJ53: DOMAIN::equentis.com | AM53: Find/verify website, run accessibility scan, then outreach
A54: WAYA FINANCIAL TECHNOLOGIES PRIVATE LIMITED | C54: Rupesh Patil | D54: rupesh.patil@thewaya.com | E54: pragatichothe001 | F54: 46202 | G54: Sent | H54: A - Contact First | I54: thewaya.com | J54: INP000008987 | K54: 3602, A Wing, Rustomjee Elanza,, Off Link Road, Malad West, | L54: 00919029832742 | M54: 00919029832742 | N54: MUMBAI | O54: MAHARASHTRA | P54: 400064 | Q54: 805, DLH Park, S.V Road, Goregaon West | U54: MUMBAI | V54: MAHARASHTRA | W54: 400062 | X54: Sep 10, 2024 | Y54: Perpetual | AA54: Portfolio Manager | AB54: Yes | AC54: Portfolio Manager | AE54: corporate_domain | AF54: company_firm | AG54: 100 | AH54: 100 | AJ54: DOMAIN::thewaya.com | AM54: Find/verify website, run accessibility scan, then outreach
A55: PL Asset Management Private Limited | C55: Akshay Seksaria | D55: pmsdesk@plindia.com | E55: pragatichothe001 | F55: 46202 | G55: Sent | H55: A - Contact First | I55: plindia.com | J55: INP000009001 | K55: 3rd Floor, Sadhana House, 570, PB Marg | L55: 9100226632222 | N55: MUMBAI | O55: MAHARASHTRA | P55: 400018 | Q55: 3rd floor, South Annex, Tower 2, One World Centre, Senapati Bapat Marg, Lower Parel | U55: MUMBAI | V55: MAHARASHTRA | W55: 400013 | X55: Sep 16, 2024 | Y55: Perpetual | AA55: Portfolio Manager | AB55: No | AC55: Portfolio Manager | AE55: corporate_domain | AF55: company_firm | AG55: 100 | AH55: 100 | AJ55: DOMAIN::plindia.com | AM55: Find/verify website, run accessibility scan, then outreach
A56: Phi Capital Solutions LLP | C56: P Sivaram | D56: sp@phicapital.in | E56: pragatichothe001 | F56: 46202 | G56: Sent | H56: A - Contact First | I56: phicapital.in | J56: INP000009047 | K56: LG 1A Siddhartha Chambers Near IIT Gate Kalu Sarai Hauz Khas | L56: 00919910111649 | M56: 00919910111649 | N56: NEW DELHI | O56: NATIONAL CAPITAL TERRITORY OF DELHI | P56: 110016 | Q56: C98 Basement Ground Floor Anand Niketan New Delhi | U56: NEW DELHI | V56: NATIONAL CAPITAL TERRITORY OF DELHI | W56: 110021 | X56: Oct 10, 2024 | Y56: Perpetual | AA56: Portfolio Manager | AB56: No | AC56: Portfolio Manager | AE56: corporate_domain | AF56: company_firm | AG56: 100 | AH56: 100 | AJ56: DOMAIN::phicapital.in | AM56: Find/verify website, run accessibility scan, then outreach
A57: B.N. Rathi Securities Limited | C57: Gadila Sabitha Reddy | D57: COMPLIANCE@BNRSECURITIES.COM | E57: pragatichothe001 | F57: 46202 | G57: Sent | H57: A - Contact First | I57: bnrsecurities.com | J57: INP000009135 | K57: 6 3 652 IV FLOOR KAUTILYA, AMRUTHA ESTATES SOMAJIGUDA | L57: 9104040527777 | M57: 9104040527777 | N57: HYDERABAD | O57: TELANGANA | P57: 500082 | Q57: 6 3 652 IV FLOOR KAUTILYA, AMRUTHA ESTATES SOMAJIGUDA | U57: HYDERABAD | V57: TELANGANA | W57: 500082 | X57: Dec 18, 2024 | Y57: Perpetual | AA57: Portfolio Manager | AB57: No | AC57: Portfolio Manager | AE57: corporate_domain | AF57: company_firm | AG57: 100 | AH57: 100 | AJ57: DOMAIN::bnrsecurities.com | AM57: Find/verify website, run accessibility scan, then outreach
A58: BHARAT BHUSHAN EQUITY TRADERS LIMITED | C58: SHARAD KUMAR | D58: sharad@bharatbhushan.com | E58: pragatichothe001 | F58: 46202 | G58: Sent | H58: A - Contact First | I58: bharatbhushan.com | J58: INP000009162 | K58: 503, ROHIT HOUSE, 3 TOLSTOY MARG | L58: 9101149800900 | N58: DELHI | O58: NATIONAL CAPITAL TERRITORY OF DELHI | P58: 110001 | Q58: 204, ROHIT HOUSE, 3 TOLSTOY MARG | U58: NEW DELHI | V58: NATIONAL CAPITAL TERRITORY OF DELHI | W58: 110001 | X58: Jan 06, 2025 | Y58: Perpetual | AA58: Portfolio Manager | AB58: No | AC58: Portfolio Manager | AE58: corporate_domain | AF58: company_firm | AG58: 100 | AH58: 100 | AJ58: DOMAIN::bharatbhushan.com | AM58: Find/verify website, run accessibility scan, then outreach
A59: Apricus Wealth Investment Managers LLP | C59: Shantanu Kant | D59: operations@apricuswealth.in | E59: pragatichothe001 | F59: 46202 | G59: Sent | H59: A - Contact First | I59: apricuswealth.in | J59: INP000009302 | K59: FLAT NO 1105, 11th Floor, 1106 SKIPPER HOUSE, 22 FIRE BRIGADE LANE, BARAKHAMBA, CONNAUGHT PLACE, CENTRAL DELHI | L59: 00919810312124 | M59: 00919810312124 | N59: NEW DELHI | O59: NATIONAL CAPITAL TERRITORY OF DELHI | P59: 110001 | Q59: FLAT NO 1105, 11th Floor, 1106 SKIPPER HOUSE, 22 FIRE BRIGADE LANE, BARAKHAMBA, CONNAUGHT PLACE, CENTRAL DELHI | U59: NEW DELHI | V59: NATIONAL CAPITAL TERRITORY OF DELHI | W59: 110001 | X59: Mar 05, 2025 | Y59: Perpetual | AA59: Portfolio Manager | AB59: Yes | AC59: Portfolio Manager | AE59: corporate_domain | AF59: company_firm | AG59: 100 | AH59: 100 | AJ59: DOMAIN::apricuswealth.in | AM59: Find/verify website, run accessibility scan, then outreach
A60: ARDEKO ASSET MANAGEMENT PRIVATE LIMITED | C60: Dwaitin Dave | D60: dwaitin.dave@ardeko.in | E60: pragatichothe001 | F60: 46202 | G60: Sent | H60: A - Contact First | I60: ardeko.in | J60: INP000009384 | K60: 705, The Ridge, Opp. Novotel, Iscon Char Rasta, | L60: 00007935721558 | M60: 00007935721558 | N60: AHMEDABAD | O60: GUJARAT | P60: 380060 | Q60: 705, The Ridge, Opp. Novotel, Iscon Char Rasta, | U60: AHMEDABAD | V60: GUJARAT | W60: 380060 | X60: Apr 03, 2025 | Y60: Perpetual | AA60: Portfolio Manager | AB60: No | AC60: Portfolio Manager | AE60: corporate_domain | AF60: company_firm | AG60: 100 | AH60: 100 | AJ60: DOMAIN::ardeko.in | AM60: Find/verify website, run accessibility scan, then outreach
A61: Wealth India Financial Services Private Limited | C61: Sarada Priya | D61: s.saradapriya@fundsindia.com | E61: pragatichothe001 | F61: 46202 | G61: Sent | H61: A - Contact First | I61: fundsindia.com | J61: INP000009393 | K61: 3rd floor, Indiqube Wave,438 1,, TR Sundaram Avenue, Anna Salai,Chennai | L61: 04404443443135 | M61: 04404443443135 | N61: CHENNAI | O61: TAMIL NADU | P61: 600006 | Q61: 3rd floor, Indiqube Wave,438 1, TR Sundaram Avenue, Anna Salai,Chennai | U61: CHENNAI | V61: TAMIL NADU | W61: 600006 | X61: Apr 04, 2025 | Y61: Perpetual | AA61: Portfolio Manager | AB61: No | AC61: Portfolio Manager | AE61: corporate_domain | AF61: company_firm | AG61: 100 | AH61: 100 | AJ61: DOMAIN::fundsindia.com | AM61: Find/verify website, run accessibility scan, then outreach
A62: Vivekam Financial Services Private Limited | C62: YASHWANT VEMURU | D62: info@vivekam.co.in | E62: pragatichothe001 | F62: 46202 | G62: Sent | H62: A - Contact First | I62: vivekam.co.in | J62: INP000009481 | K62: Plot No 57, Road No 71, Jubilee Hills | L62: 9104023549941 | N62: HYDERABAD | O62: TELANGANA | P62: 500096 | Q62: Plot No 57, Road No 71, Jubilee Hills | U62: HYDERABAD | V62: TELANGANA | W62: 500096 | X62: Jun 05, 2025 | Y62: Perpetual | AA62: Portfolio Manager | AB62: No | AC62: Portfolio Manager | AE62: corporate_domain | AF62: company_firm | AG62: 100 | AH62: 100 | AJ62: DOMAIN::vivekam.co.in | AM62: Find/verify website, run accessibility scan, then outreach
A63: Niveshaay Investment Management Private Limited | C63: Vidhya Sanwal | D63: vidhya.sanwal@niveshaay.com | E63: pragatichothe001 | F63: 46202 | G63: Sent | H63: A - Contact First | I63: niveshaay.com | J63: INP000009506 | K63: Office No. 610 6th Floor, SNS Platina Vesu | L63: 9107096078870 | M63: 9107096078870 | N63: SURAT | O63: GUJARAT | P63: 395007 | Q63: Office No. 610 6th Floor, SNS Platina Vesu | U63: SURAT | V63: GUJARAT | W63: 395007 | X63: Jun 23, 2025 | Y63: Perpetual | AA63: Portfolio Manager | AB63: No | AC63: Portfolio Manager | AE63: corporate_domain | AF63: company_firm | AG63: 100 | AH63: 100 | AJ63: DOMAIN::niveshaay.com | AM63: Find/verify website, run accessibility scan, then outreach
A64: Omniscience Capital Advisors Private Limited | C64: Chanchal Manglunia | D64: chanchal.manglunia@omnisciencecapital.com | E64: pragatichothe001 | F64: 46202 | G64: Sent | H64: A - Contact First | I64: omnisciencecapital.com | J64: INP000009597 | K64: Awfis, 1st Floor, B Wing, Parinee Crescenzo,, G Block Bandra Kurla Complex Ground Bandra East Mumbai | L64: 0000000000000 | M64: 0000000000000 | N64: MUMBAI | O64: MAHARASHTRA | P64: 400051 | Q64: Awfis, 1st Floor, B Wing, Parinee Crescenzo, G Block Bandra Kurla Complex Ground Bandra East Mumbai | U64: MUMBAI | V64: MAHARASHTRA | W64: 400051 | X64: Aug 18, 2025 | Y64: Perpetual | AA64: Portfolio Manager | AB64: Yes | AC64: Portfolio Manager | AE64: corporate_domain | AF64: company_firm | AG64: 100 | AH64: 100 | AJ64: DOMAIN::omnisciencecapital.com | AM64: Find/verify website, run accessibility scan, then outreach
A65: CREST CAPITAL MANAGEMENT PRIVATE LIMITED | C65: Zuhaib Khan | D65: zuhaib@crest-group.co | E65: pragatichothe001 | F65: 46202 | G65: Sent | H65: A - Contact First | I65: crest-group.co | J65: INP000009612 | K65: B 601, Lantane Mahindra S, LBS Marg, Bhandup West | L65: 00919871396555 | M65: 00919871396555 | N65: MUMBAI | O65: MAHARASHTRA | P65: 400078 | Q65: B wing 6th floor, Supreme Business Park Wing B, SUPREME BUSINESS PARK, , Cliff Avenue Unit No. B, 501a, Hiranandani Gardens, Powai | U65: MUMBAI | V65: MAHARASHTRA | W65: 400076 | X65: Aug 28, 2025 | Y65: Perpetual | AA65: Portfolio Manager | AB65: No | AC65: Portfolio Manager | AE65: corporate_domain | AF65: company_firm | AG65: 100 | AH65: 100 | AJ65: DOMAIN::crest-group.co | AM65: Find/verify website, run accessibility scan, then outreach
A66: PrimeInvestor Financial Research Private Limited | C66: Balachandran D B | D66: bhavana@primeinvestor.in | E66: pragatichothe001 | F66: 46202 | G66: Sent | H66: A - Contact First | I66: primeinvestor.in | J66: INP000009658 | K66: 659, 1st Floor Flat no 1, Alakananda, 4th Avenue, D Sector, Anna Nagar Western Extn | L66: 9109952030734 | N66: CHENNAI | O66: TAMIL NADU | P66: 600101 | Q66: 659, 1st Floor Flat no 1, Alakananda, 4th Avenue, D Sector, Anna Nagar Western Extn | U66: CHENNAI | V66: TAMIL NADU | W66: 600101 | X66: Oct 10, 2025 | Y66: Perpetual | AA66: Portfolio Manager | AB66: Yes | AC66: Portfolio Manager | AE66: corporate_domain | AF66: company_firm | AG66: 100 | AH66: 100 | AJ66: DOMAIN::primeinvestor.in | AM66: Find/verify website, run accessibility scan, then outreach
A67: Systematix Wealth and Asset Services Private Limited | C67: Pradeep Gotecha | D67: compliance_pms@systematixgroup.in | E67: pragatichothe001 | F67: 46203 | G67: Sent | H67: A - Contact First | I67: systematixgroup.in | J67: INP000009728 | K67: The Capital, A wing, No. 603 - 606, 6th Floor, Plot No. C 70, G Block, , Bandra Kurla Complex, Bandra East, | L67: 09102266198000 | M67: 09102266198029 | N67: MUMBAI | O67: MAHARASHTRA | P67: 400051 | Q67: The Capital, A wing, No. 603 - 606, 6th Floor, Plot No. C 70, G Block, , Bandra Kurla Complex, Bandra East, | U67: MUMBAI | V67: MAHARASHTRA | W67: 400051 | X67: Nov 28, 2025 | Y67: Perpetual | AA67: Portfolio Manager | AB67: No | AC67: Portfolio Manager | AE67: corporate_domain | AF67: company_firm | AG67: 100 | AH67: 100 | AJ67: DOMAIN::systematixgroup.in | AM67: Find/verify website, run accessibility scan, then outreach
A68: Sicomoro Advisors Private Limited | C68: Rashmikant Talati | D68: rashmikant.talati@sicomoro.in | E68: pragatichothe001 | F68: 46203 | G68: Sent | H68: A - Contact First | I68: sicomoro.in | J68: INP000009782 | K68: Unit No 102 1st Floor, Pharma Search House 72 73, , Worli Hill Estate, Dr. B.G. Kher Road, Worli | L68: 9102249636131 | M68: 9102249636131 | N68: MUMBAI | O68: MAHARASHTRA | P68: 400018 | Q68: Unit No 102 1st Floor, Pharma Search House 72 73, , Worli Hill Estate, Dr. B.G. Kher Road, Worli | U68: MUMBAI | V68: MAHARASHTRA | W68: 400018 | X68: Jan 21, 2026 | Y68: Perpetual | AA68: Portfolio Manager | AB68: Yes | AC68: Portfolio Manager | AE68: corporate_domain | AF68: company_firm | AG68: 100 | AH68: 100 | AJ68: DOMAIN::sicomoro.in | AM68: Find/verify website, run accessibility scan, then outreach
A69: Abakkus Investment Managers Private Limited | C69: Lijo Varghese | D69: lijo.varghese@abakkusinvest.com | E69: pragatichothe001 | F69: 46203 | G69: Sent | H69: A - Contact First | I69: abakkusinvest.com | J69: INP000009959 | K69: 6th Floor, Param House, Shanti Nagar, Near Grand Hyatt,, Santacruz East, | L69: 91919819032286 | M69: 91919819032286 | N69: MUMBAI | O69: MAHARASHTRA | P69: 400055 | Q69: Abakkus Corporate Centre, 9th Floor, Param House, Shanti Nagar, Near Grand Hyatt, Off Santacruz Chembur Link Road, Santacruz East, | U69: MUMBAI | V69: MAHARASHTRA | W69: 400055 | X69: Apr 24, 2026 | Y69: Perpetual | AA69: Portfolio Manager | AB69: No | AC69: Portfolio Manager | AE69: corporate_domain | AF69: company_firm | AG69: 100 | AH69: 100 | AJ69: DOMAIN::abakkusinvest.com | AM69: Find/verify website, run accessibility scan, then outreach
A70: NARNOLIA VELOX ADVISORY LIMITED | C70: Ramesh Singh | D70: rdebnath@narnolia.com | E70: pragatichothe001 | F70: 46203 | G70: Sent | H70: A - Contact First | I70: narnolia.com | J70: INP000009995 | K70: 236B AJC BOSE ROAD, MARBLE ARCH 2ND FLOOR | L70: 9103340501500 | N70: KOLKATA | O70: WEST BENGAL | P70: 700020 | Q70: 236B AJC BOSE ROAD, MARBLE ARCH 2ND FLOOR | U70: KOLKATA | V70: WEST BENGAL | W70: 700020 | X70: May 06, 2026 | Y70: Perpetual | AA70: Portfolio Manager | AB70: No | AC70: Portfolio Manager | AE70: corporate_domain | AF70: company_firm | AG70: 100 | AH70: 100 | AJ70: DOMAIN::narnolia.com | AM70: Find/verify website, run accessibility scan, then outreach
A71: Centricity Portfolio Managers Private Limited | C71: Abhishek Sahu | D71: compliance@centricity.co.in | E71: pragatichothe001 | F71: 46203 | G71: Sent | H71: A - Contact First | I71: centricity.co.in | J71: INP000010007 | K71: 405 A Tower B Global Business Park, Dlf Qe | L71: 9101122438810 | M71: 9101122438810 | N71: GURUGRAM | O71: HARYANA | P71: 122002 | X71: May 07, 2026 | Y71: Perpetual | AA71: Portfolio Manager | AB71: No | AC71: Portfolio Manager | AE71: corporate_domain | AF71: company_firm | AG71: 100 | AH71: 100 | AJ71: DOMAIN::centricity.co.in | AM71: Find/verify website, run accessibility scan, then outreach
A72: Greenedge Wealth Services LLP | C72: Jindal Haria | D72: jindal@greenedgewealth.com | E72: pragatichothe001 | F72: 46203 | G72: Sent | H72: A - Contact First | I72: greenedgewealth.com | J72: INP000010043 | K72: Office No. 1123, 11th Floor, Omkar The Summit Business Bay, Off Western Express Highway, Gundavali, , Opp. Movie Max Cinemas, Near, Chakala Midc, Mumbai, Mumbai, Maharashtra, India, 400093 | L72: 0919619526353 | M72: 0919619526353 | N72: MUMBAI | O72: MAHARASHTRA | P72: 400093 | X72: May 12, 2026 | Y72: Perpetual | AA72: Portfolio Manager | AB72: No | AC72: Portfolio Manager | AE72: corporate_domain | AF72: company_firm | AG72: 100 | AH72: 100 | AJ72: DOMAIN::greenedgewealth.com | AM72: Find/verify website, run accessibility scan, then outreach
A73: Finnovate Investment Managers Private Limited | C73: Pravin Mayekar | D73: pravin.mayekar@finnovate.in | E73: pragatichothe001 | F73: 46203 | G73: Sent | H73: A - Contact First | I73: finnovate.in | J73: INP000010104 | K73: 703, The Summit Business Bay, Prakashwadi, Gundavali, Chakala MIDC | L73: 91229619783006 | M73: 91229619783006 | N73: MUMBAI | O73: MAHARASHTRA | P73: 400093 | X73: Jun 15, 2026 | Y73: Perpetual | AA73: Portfolio Manager | AB73: No | AC73: Portfolio Manager | AE73: corporate_domain | AF73: company_firm | AG73: 100 | AH73: 100 | AJ73: DOMAIN::finnovate.in | AM73: Find/verify website, run accessibility scan, then outreach
A74: EASTERN FINANCIERS LIMITED | C74: Reena Khetan | D74: reena.k@easternfin.com | E74: pragatichothe001 | F74: 46203 | G74: Sent | H74: A - Contact First | I74: easternfin.com | J74: INP000010122 | K74: 102 & 104, 'Lords', 7/1, Lord Sinha Road, Kolkata | L74: 9109830355996 | M74: 9109830355996 | N74: KOLKATA | O74: WEST BENGAL | P74: 700071 | X74: Jun 15, 2026 | Y74: Perpetual | AA74: Portfolio Manager | AB74: No | AC74: Portfolio Manager | AE74: corporate_domain | AF74: company_firm | AG74: 100 | AH74: 100 | AJ74: DOMAIN::easternfin.com | AM74: Find/verify website, run accessibility scan, then outreach
A75: QUANTUM INFORMATION SERVICES PRIVATE LIMITED | C75: Sonal Ramachandran | D75: sonal@equitymaster.com | E75: pragatichothe001 | F75: 46203 | G75: Sent | H75: A - Contact First | I75: equitymaster.com | J75: INA000000680 | K75: 103, REGENT CHAMBERS,, NARIMAN POINT, | L75: 0919867009724 | M75: 0919867009724 | N75: MUMBAI | O75: MAHARASHTRA | P75: 400021 | Q75: 101, Raheja Chambers, Fee Press Journal marg, 213, Nariman Point, | U75: MUMBAI | V75: MAHARASHTRA | W75: 400021 | X75: Dec 27, 2013 | Y75: Perpetual | AA75: Investment Adviser | AB75: No | AC75: Investment Adviser | AE75: corporate_domain | AF75: company_firm | AG75: 100 | AH75: 97 | AJ75: DOMAIN::equitymaster.com | AM75: Find/verify website, run accessibility scan, then outreach
A76: DSIJ Wealth Advisory Private Limited | C76: MR. RAJESH PADODE | D76: rajeshp@dsij.in | E76: pragatichothe001 | F76: 46203 | G76: Sent | H76: A - Contact First | I76: dsij.in | J76: INA000001142 | K76: 419-A, 4TH FLOOR, ARUN CHAMBERS,, TARDEO, NEXT TO AC MARKET, | L76: 2040197219 | M76: 2040197219 | N76: MUMBAI | O76: MAHARASHTRA | P76: 400034 | Q76: Office No. ? 303, 3rd Floor, Siddhivinayak Aurum, Behind Eden Garden Society, Near IBIS Hotel, Vimannagar, | U76: PUNE | V76: MAHARASHTRA | W76: 411014 | X76: Feb 24, 2014 | Y76: Perpetual | AA76: Investment Adviser | AB76: Yes | AC76: Investment Adviser | AE76: corporate_domain | AF76: company_firm | AG76: 100 | AH76: 97 | AJ76: DOMAIN::dsij.in | AM76: Find/verify website, run accessibility scan, then outreach
A77: GEPL INVESTMENT ADVISORS PRIVATE LIMITED | C77: ABHISHEK A MISTRY | D77: advisors@geplcapital.com | E77: pragatichothe001 | F77: 46203 | G77: Not delivered | H77: A - Contact First | I77: geplcapital.com | J77: INA000002744 | K77: C-14, DHANRAJ MAHAL,C.S.M MARG,, COLABA, | L77: 2266142751 | M77: 2266142751 | N77: MUMBAI | O77: MAHARASHTRA | P77: 400001 | Q77: C-14, Dhanraj Mahal,C.S.M Marg, Colaba, | U77: MUMBAI | V77: MAHARASHTRA | W77: 400001 | X77: Mar 03, 2015 | Y77: Perpetual | AA77: Investment Adviser | AB77: No | AC77: Investment Adviser | AE77: corporate_domain | AF77: company_firm | AG77: 100 | AH77: 97 | AJ77: DOMAIN::geplcapital.com | AM77: Find/verify website, run accessibility scan, then outreach
A78: MONARCH NETWORTH INVESTMENT ADVISORS PVT. LTD. | C78: MR. VIPUL SHAH | D78: vipul.shah@mnclgroup.com | E78: pragatichothe001 | F78: 46203 | G78: Not delivered | H78: A - Contact First | I78: mnclgroup.com | J78: INA000005721 | K78: MONARCH HOUSE, NR. ISHWAR BHUWAN CROSS ROAD, NR. COMMERCE SIX ROAD, NAVRANGPURA | L78: 02230641600 | M78: 02230641600 | N78: AHMEDABAD | O78: GUJARAT | P78: 380009 | Q78: Monarch House, Nr. Ishwar Bhuwan Cross Road, Nr. Commerce Six Road, Navrangpura | U78: AHMEDABAD | V78: GUJARAT | W78: 380009 | X78: Nov 24, 2016 | Y78: Perpetual | AA78: Investment Adviser | AB78: No | AC78: Investment Adviser | AE78: corporate_domain | AF78: company_firm | AG78: 100 | AH78: 97 | AJ78: DOMAIN::mnclgroup.com | AM78: Find/verify website, run accessibility scan, then outreach
A79: LKP Wealth Advisory Limited | C79: Ritesh Tiwari | D79: ho_compliance@lkpsec.com | E79: pragatichothe001 | F79: 46203 | G79: Sent | H79: A - Contact First | I79: lkpsec.com | J79: INA000009861 | K79: 203, Embassy Centre,, Nariman Point | L79: 919136525875 | M79: 919136525875 | N79: MUMBAI | O79: MAHARASHTRA | P79: 400021 | Q79: 1303-1304, Raheja Centre, Free Press Marg, Nariman point | U79: MUMBAI | V79: MAHARASHTRA | W79: 400001 | X79: Feb 21, 2018 | Y79: Perpetual | AA79: Investment Adviser | AB79: No | AC79: Investment Adviser | AE79: corporate_domain | AF79: company_firm | AG79: 100 | AH79: 97 | AJ79: DOMAIN::lkpsec.com | AM79: Find/verify website, run accessibility scan, then outreach
A80: Banayantree Services Limited | C80: Neeraj Gugnani | D80: compliance@etmoney.com | E80: pragatichothe001 | F80: 46203 | G80: Sent | H80: A - Contact First | I80: etmoney.com | J80: INA100006898 | K80: Express Building, 9-10 Bahadurshah, Zafar Marg, New Delhi | L80: 00919871396095 | M80: 00919871396095 | N80: NEW DELHI | O80: NATIONAL CAPITAL TERRITORY OF DELHI | P80: 110002 | Q80: Plot no. 391, Udyog Vihar-III, Gurgaon, Haryana | U80: GURUGRAM | V80: HARYANA | W80: 122016 | X80: Nov 18, 2025 | Y80: Perpetual | AA80: Investment Adviser | AB80: Yes | AC80: Investment Adviser | AE80: corporate_domain | AF80: company_firm | AG80: 100 | AH80: 97 | AJ80: DOMAIN::etmoney.com | AM80: Find/verify website, run accessibility scan, then outreach
A81: Finwizard Technology Private Limited | C81: Nishank Jain | D81: nishank.jain@fisdom.com | E81: pragatichothe001 | F81: 46203 | G81: Sent | H81: A - Contact First | I81: fisdom.com | J81: INA200005323 | K81: IndiQube Sapphire, 2nd Floor,, No. 73 1, St Mark s Road, | L81: 00918109616263 | M81: 00918109616263 | N81: BANGALORE | O81: KARNATAKA | P81: 560001 | X81: Jun 04, 2026 | Y81: Perpetual | AA81: Investment Adviser | AB81: Yes | AC81: Investment Adviser | AE81: corporate_domain | AF81: company_firm | AG81: 100 | AH81: 97 | AJ81: DOMAIN::fisdom.com | AM81: Find/verify website, run accessibility scan, then outreach
A82: PRUDENT CORPORATE ADVISORY SERVICES LIMITED | C82: Meghna Jain | D82: meghna.jain@prudentcorporate.com | E82: pragatichothe001 | F82: 46203 | G82: Sent | H82: A - Contact First | I82: prudentcorporate.com | J82: INA000004906 | K82: PRUDENT HOUSE, 3 Devang Park Society,, Panjrapole Cross Road, Ambawadi | L82: 091977940209600 | M82: 091977940209600 | N82: AHMEDABAD | O82: GUJARAT | P82: 380015 | Q82: PRUDENT HOUSE, Panjrapole Cross Road, Nr. Polytechnic, Ambawadi | U82: AHMEDABAD | V82: GUJARAT | W82: 380015 | X82: Jun 08, 2016 | Y82: Perpetual | AA82: Investment Adviser | AB82: No | AC82: Investment Adviser | AE82: corporate_domain | AF82: company_firm | AG82: 100 | AH82: 97 | AJ82: DOMAIN::prudentcorporate.com | AM82: Find/verify website, run accessibility scan, then outreach
A83: Incred Capital Wealth Portfolio Managers Private Limited | C83: Preeti Lalwani | D83: compliance@incredcapital.com | E83: pragatichothe001 | F83: 46203 | G83: Sent | H83: A - Contact First | I83: incredcapital.com | J83: INA000014890 | K83: Unit No. 1502-A, 15th Floor, The Capital Building, C-70, G Block, Bandra Kurla Complex, Bandra East | L83: 91009820455802 | M83: 91009820455802 | N83: MUMBAI | O83: MAHARASHTRA | P83: 400051 | Q83: Unit No. 1502-A, 15th Floor, The Capital Building, C-70, G Block, Bandra Kurla Complex, Bandra East | U83: MUMBAI | V83: MAHARASHTRA | W83: 400051 | X83: Jul 31, 2020 | Y83: Perpetual | AA83: Investment Adviser | AB83: Yes | AC83: Investment Adviser | AE83: corporate_domain | AF83: company_firm | AG83: 100 | AH83: 97 | AJ83: DOMAIN::incredcapital.com | AM83: Find/verify website, run accessibility scan, then outreach
A84: Omkara Capital Private Limited | C84: Vineet Sood | D84: compliance@omkaracapital.in | E84: pragatichothe001 | F84: 46203 | G84: Sent | H84: A - Contact First | I84: omkaracapital.in | J84: INA000016825 | K84: UNIT NO. 207 A/B, PENINSULA CENTRE, DR. S. S. RAO ROAD, BEHIND PIRAMAL CHAMBERS,, PAREL EAST | L84: 00917897891192 | M84: 00917897891192 | N84: MUMBAI | O84: MAHARASHTRA | P84: 400012 | X84: Apr 11, 2022 | Y84: Perpetual | AA84: Investment Adviser | AB84: No | AC84: Investment Adviser | AE84: corporate_domain | AF84: company_firm | AG84: 100 | AH84: 97 | AJ84: DOMAIN::omkaracapital.in | AM84: Find/verify website, run accessibility scan, then outreach
A85: Pioneer Wealth Management Services Limited | C85: Riddhi Sidhpura | D85: riddhi.sidhpura@pinc.co.in | E85: pragatichothe001 | F85: 46203 | G85: Sent | H85: A - Contact First | I85: pinc.co.in | J85: INA000017259 | K85: 1218 Maker Chambers V, Nariman Point | L85: 009867654945 | M85: 009867654945 | N85: MUMBAI | O85: MAHARASHTRA | P85: 400021 | Q85: 1218 Maker Chambers V, Nariman Point | R85: amitc@pinc.co.in | U85: MUMBAI | V85: MAHARASHTRA | W85: 400021 | X85: Oct 18, 2022 | Y85: Perpetual | AA85: Investment Adviser | AB85: Yes | AC85: Investment Adviser | AE85: corporate_domain | AF85: company_firm | AG85: 100 | AH85: 97 | AJ85: DOMAIN::pinc.co.in | AM85: Find/verify website, run accessibility scan, then outreach
A86: Neo Wealth Management Private Limited | C86: Nitesh Shah | D86: compliance@neo-wealth.com | E86: pragatichothe001 | F86: 46203 | G86: Sent | H86: A - Contact First | I86: neo-wealth.com | J86: INA000017286 | K86: 903, B wing, Floor 9, Marathon Futurex, N. M. Joshi Marg, Lower Parel | L86: 91229619523663 | M86: 91229619523663 | N86: MUMBAI | O86: MAHARASHTRA | P86: 400013 | Q86: 903, B wing, Floor 9, Marathon Futurex, N. M. Joshi Marg, Lower Parel | U86: MUMBAI | V86: MAHARASHTRA | W86: 400013 | X86: Nov 01, 2022 | Y86: Perpetual | AA86: Investment Adviser | AB86: Yes | AC86: Investment Adviser | AE86: corporate_domain | AF86: company_firm | AG86: 100 | AH86: 97 | AJ86: DOMAIN::neo-wealth.com | AM86: Find/verify website, run accessibility scan, then outreach
A87: Kredent InfoEdge Private Limited | C87: Vivek Bajaj | D87: vivek@stockedge.com | E87: pragatichothe001 | F87: 46203 | G87: Sent | H87: A - Contact First | I87: stockedge.com | J87: INA000017781 | K87: J-1/14, BLOCK - EP and GP, 9TH FLOOR, , SECTOR - V, SALTLAKE CITY KOLKATA | L87: 0919903048099 | M87: 0919903048099 | N87: KOLKATA | O87: WEST BENGAL | P87: 700091 | Q87: J-1/14, BLOCK - EP and GP, 9TH FLOOR, , SECTOR - V, SALTLAKE CITY KOLKATA | U87: KOLKATA | V87: WEST BENGAL | W87: 700091 | X87: Mar 23, 2023 | Y87: Perpetual | AA87: Investment Adviser | AB87: No | AC87: Investment Adviser | AE87: corporate_domain | AF87: company_firm | AG87: 100 | AH87: 97 | AJ87: DOMAIN::stockedge.com | AM87: Find/verify website, run accessibility scan, then outreach
A88: Yadnya Academy Private Limited | C88: Mayur Firodiya | D88: mayur@investyadnya.in | E88: pragatichothe001 | F88: 46203 | G88: Sent | H88: A - Contact First | I88: investyadnya.in | J88: INA000017897 | K88: G703 BALWANTPURAM SAMRAJYA L5 , CTS NO 1148110 1 A KOTHRUD Pune | L88: 0919730601468 | M88: 0919730601468 | N88: PUNE | O88: MAHARASHTRA | P88: 411038 | Q88: A2 SR No.133/ 1, PL NO.16 Purva Apartment Aundh | U88: PUNE | V88: MAHARASHTRA | W88: 411007 | X88: Apr 24, 2023 | Y88: Perpetual | AA88: Investment Adviser | AB88: No | AC88: Investment Adviser | AE88: corporate_domain | AF88: company_firm | AG88: 100 | AH88: 97 | AJ88: DOMAIN::investyadnya.in | AM88: Find/verify website, run accessibility scan, then outreach
A89: AlphaGrep Advisors Private Limited | C89: Punit Sahi | D89: punit.sahi@alphagrepadvisors.com | E89: pragatichothe001 | F89: 46203 | G89: Sent | H89: A - Contact First | I89: alphagrepadvisors.com | J89: INA000018470 | K89: Parinee Crescenzo, Unit No. I406, 14th Floor, G Block, Bandra Kurla Complex, Bandra East, Mumbai | L89: 00917710993310 | M89: 00917710993310 | N89: MUMBAI | O89: MAHARASHTRA | P89: 400051 | Q89: Parinee Crescenzo, Unit No. I406, 14th Floor, G Block, Bandra Kurla Complex, Bandra East, Mumbai | U89: MUMBAI | V89: MAHARASHTRA | W89: 400051 | X89: Jan 08, 2026 | Y89: Perpetual | AA89: Investment Adviser | AB89: Yes | AC89: Investment Adviser | AE89: corporate_domain | AF89: company_firm | AG89: 100 | AH89: 97 | AJ89: DOMAIN::alphagrepadvisors.com | AM89: Find/verify website, run accessibility scan, then outreach
A90: Basant Maheshwari Wealth Advisers LLP | C90: Basant Maheshwari | D90: info@theequitydesk.com | E90: pragatichothe001 | F90: 46203 | G90: Sent | H90: A - Contact First | I90: theequitydesk.com | J90: INA000018498 | K90: Office No. 701, 7th Floor, Plot 211, Dalamal Tower,, Free Press Journal Marg, Nariman Point | L90: 91009830627071 | M90: 91009830627071 | N90: MUMBAI | O90: MAHARASHTRA | P90: 400021 | Q90: Office No. 701, 7th Floor, Plot 211, Dalamal Tower, Free Press Journal Marg, Nariman Point | U90: MUMBAI | V90: MAHARASHTRA | W90: 400021 | X90: Oct 16, 2023 | Y90: Perpetual | AA90: Investment Adviser | AB90: Yes | AC90: Investment Adviser | AE90: corporate_domain | AF90: company_firm | AG90: 100 | AH90: 97 | AJ90: DOMAIN::theequitydesk.com | AM90: Find/verify website, run accessibility scan, then outreach
A91: MOOL CAPITAL PRIVATE LIMITED | C91: SRINIVASA SHARAN | D91: sharan@mool.one | E91: pragatichothe001 | F91: 46203 | G91: Not delivered | H91: A - Contact First | I91: mool.one | J91: INA000018708 | K91: H N 4066, SECT B, PKT 5/6,, VASANT KUNJ, SOUTH DELHI | L91: 00919741248158 | M91: 00919741248158 | N91: DELHI | O91: NATIONAL CAPITAL TERRITORY OF DELHI | P91: 110070 | Q91: H N 4066, SECT B, PKT 5/6, VASANT KUNJ, SOUTH DELHI | U91: DELHI | V91: NATIONAL CAPITAL TERRITORY OF DELHI | W91: 110070 | X91: Dec 18, 2023 | Y91: Perpetual | AA91: Investment Adviser | AB91: Yes | AC91: Investment Adviser | AE91: corporate_domain | AF91: company_firm | AG91: 100 | AH91: 97 | AJ91: DOMAIN::mool.one | AM91: Find/verify website, run accessibility scan, then outreach
A92: Fluid Fincap Private Limited | C92: Aniket Shirke | D92: aniket@liquide.life | E92: pragatichothe001 | F92: 46203 | G92: Sent | H92: A - Contact First | I92: liquide.life | J92: INA000018762 | K92: Obeya Signal, Ground Floor, Embassy Signet, Embassy Tech Square, Kaverappa Layout, Kad.besanahall, | L92: 91007718957000 | M92: 91007718957000 | N92: BANGALORE | O92: KARNATAKA | P92: 560103 | Q92: Obeya Signal, Ground Floor, Embassy Signet, Embassy Tech Square, Kaverappa Layout, Kad.besanahall, | U92: BANGALORE | V92: KARNATAKA | W92: 560103 | X92: Jan 16, 2024 | Y92: Perpetual | AA92: Investment Adviser | AB92: No | AC92: Investment Adviser | AE92: corporate_domain | AF92: company_firm | AG92: 100 | AH92: 97 | AJ92: DOMAIN::liquide.life | AM92: Find/verify website, run accessibility scan, then outreach
A93: ONE CENTURION VENTURES PRIVATE LIMITED | C93: Priya Shah | D93: advisory@onecenturion.in | E93: pragatichothe001 | F93: 46203 | G93: Sent | H93: A - Contact First | I93: onecenturion.in | J93: INA000018896 | K93: 601, Signature Suresh Sawant Road,, Off. Veera Desai Road, Andheri, | L93: 918655742577 | M93: 918655742577 | N93: MUMBAI | O93: MAHARASHTRA | P93: 400053 | Q93: Unit No. 601, 604, 6th floor, Lotus Signature, , Off Veera Desai Road, Andheri (West), | U93: MUMBAI | V93: MAHARASHTRA | W93: 400053 | X93: Feb 29, 2024 | Y93: Perpetual | AA93: Investment Adviser | AB93: Yes | AC93: Investment Adviser | AE93: corporate_domain | AF93: company_firm | AG93: 100 | AH93: 97 | AJ93: DOMAIN::onecenturion.in | AM93: Find/verify website, run accessibility scan, then outreach
A94: Candour Asset Management LLP | C94: Amey Kulkarni | D94: amey.kulkarni@candorinvesting.com | E94: pragatichothe001 | F94: 46203 | G94: Sent | H94: A - Contact First | I94: candorinvesting.com | J94: INA000019479 | K94: CTS NO 155 / 156 SAMRUDHHI HEIGHT, 1 ST FLOOR PARVATI PUNE | L94: 917841852436 | M94: 917841852436 | N94: PUNE | O94: MAHARASHTRA | P94: 411009 | Q94: Office 302, CTS NO. 681, S.No, 15/1A. Dattakrupa Soc, Kothrud Pune City | U94: PUNE | V94: MAHARASHTRA | W94: 411038 | X94: Aug 06, 2024 | Y94: Perpetual | AA94: Investment Adviser | AB94: No | AC94: Investment Adviser | AE94: corporate_domain | AF94: company_firm | AG94: 100 | AH94: 97 | AJ94: DOMAIN::candorinvesting.com | AM94: Find/verify website, run accessibility scan, then outreach
A95: Profitmart Securities Private Limited | C95: Nitin Bora | D95: compliance@profitmart.in | E95: pragatichothe001 | F95: 46203 | G95: Sent | H95: A - Contact First | I95: profitmart.in | J95: INA000020095 | K95: UNIT NO. 213, OPAL SQUARE, Plot no. C1 Thane east Mumbai | L95: 00919850444689 | M95: 00919850444689 | N95: THANE | O95: MAHARASHTRA | P95: 400604 | Q95: Office No.3, 1st floor, B3, Cerebrum IT Park, Above DMART, Kalyani Nagar Pune | U95: PUNE | V95: MAHARASHTRA | W95: 411014 | X95: Apr 09, 2025 | Y95: Perpetual | AA95: Investment Adviser | AB95: No | AC95: Investment Adviser | AE95: corporate_domain | AF95: company_firm | AG95: 100 | AH95: 97 | AJ95: DOMAIN::profitmart.in | AM95: Find/verify website, run accessibility scan, then outreach
A96: Dolat Finserv Private Limited | C96: Viplab Dasgupta | D96: Viplabd@dolatcapital.com | E96: pragatichothe001 | F96: 46203 | G96: Sent | H96: A - Contact First | I96: dolatcapital.com | J96: INA000020101 | K96: 301-308, Bhagwati House, A-19, Veera Desai Road,, Andheri West | L96: 00919870193603 | M96: 00919870193603 | N96: MUMBAI | O96: MAHARASHTRA | P96: 400058 | Q96: Unit No. 1201, B Wing, 12th Floor, Naman Midtown B wing Premises C. S. Ltd., Senapati Bapat Marg, Elphinstone, Prabhadevi | U96: MUMBAI | V96: MAHARASHTRA | W96: 400013 | X96: Apr 19, 2025 | Y96: Perpetual | AA96: Investment Adviser | AB96: No | AC96: Investment Adviser | AE96: corporate_domain | AF96: company_firm | AG96: 100 | AH96: 97 | AJ96: DOMAIN::dolatcapital.com | AM96: Find/verify website, run accessibility scan, then outreach
A97: Indira Securities Private Limited | C97: SUMEET PATEL | D97: dharmeshk@indiratrade.com | E97: pragatichothe002 | F97: 46203 | G97: Sent | H97: A - Contact First | I97: indiratrade.com | J97: INA000021410 | K97: Indira House, 3rd Floor, 5 Topiwala Lane, Lamington Road, Mumbai | L97: 00917314797158 | M97: 00917314797158 | N97: MUMBAI | O97: MAHARASHTRA | P97: 400007 | Q97: 204-205 Amardarshan, 28/2 Old Palasia, Indore | U97: INDORE | V97: MADHYA PRADESH | W97: 452018 | X97: Nov 27, 2025 | Y97: Perpetual | AA97: Investment Adviser | AB97: No | AC97: Investment Adviser | AE97: corporate_domain | AF97: company_firm | AG97: 100 | AH97: 97 | AJ97: DOMAIN::indiratrade.com | AM97: Find/verify website, run accessibility scan, then outreach
... A100: Bristlecone Consultants | C100: Hoshner Patel | D100: hoshner@bristlecone.in | E100: pragatichothe002 | F100: 46203 | G100: Sent | H100: A - Contact First | I100: bristlecone.in | J100: INA000021872 | K100: Unit-18,19,20, Technoplis Knowlegde Park,, Mahakali Caves Road, NR Udyog Bhavan, Chakala, Andheri East, | L100: 00919356261682 | M100: 00919356261682 | N100: MUMBAI | O100: MAHARASHTRA | P100: 400093 | Q100: Unit-18,19,20, Technoplis Knowlegde Park, Mahakali Caves Road, NR Udyog Bhavan, Chakala, Andheri East, | U100: MUMBAI | V100: MAHARASHTRA | W100: 400093 | X100: Feb 16, 2026 | Y100: Perpetual | AA100: Investment Adviser | AB100: Yes | AC100: Investment Adviser | AE100: corporate_domain | AF100: company_firm | AG100: 100 | AH100: 97 | AJ100: DOMAIN::bristlecone.in | AM100: Find/verify website, run accessibility scan, then outreach
A101: WHERE2INVEST LIMITED | C101: VINAY JAIS | D101: advisors@where2invest.com | E101: pragatichothe002 | F101: 46203 | G101: Sent | H101: A - Contact First | I101: where2invest.com | J101: INA000022075 | K101: 7th Floor Flat No. 708, Asian Suncity,, Forest Department, Serilingampally Kondapur, Hyderabad, Medchal Malkajgiri, | L101: 00918977729398 | M101: 00918977729398 | N101: HYDERABAD | O101: TELANGANA | P101: 500084 | X101: Mar 23, 2026 | Y101: Perpetual | AA101: Investment Adviser | AB101: Yes | AC101: Investment Adviser | AE101: corporate_domain | AF101: company_firm | AG101: 100 | AH101: 97 | AJ101: DOMAIN::where2invest.com | AM101: Find/verify website, run accessibility scan, then outreach
A102: WILLIAM O NEIL INDIA PRIVATE LIMITED | C102: anupam shingh | D102: anupam.singhi@williamoneilindia.com | E102: pragatichothe002 | F102: 46203 | G102: Sent | H102: A - Contact First | I102: williamoneilindia.com | J102: INA200005125 | K102: Akshay Tech Park, Unit No 302, 3rd Floor, Plot 72 & 73, EPIP Area,, Hoodi Village, Hobli, Whitefield, Krishnarajapura, EPIP Bangalore | L102: 8067453802 | M102: 8067453802 | N102: BANGALORE | O102: KARNATAKA | P102: 560066 | Q102: TECHNOMARK BUILDING, A-4, NGEF ANCILLARY INDUSTRIAL ESTATE, GRAPHITE INDIA ROAD, MAHADEVAPURA, WHITEFIELD, | U102: BANGALORE | V102: KARNATAKA | W102: 560048 | X102: Jul 12, 2016 | Y102: Perpetual | AA102: Investment Adviser | AB102: No | AC102: Investment Adviser | AE102: corporate_domain | AF102: company_firm | AG102: 85 | AH102: 97 | AJ102: DOMAIN::williamoneilindia.com | AM102: Find/verify website, run accessibility scan, then outreach
...

Sheet Need Manual Review
A1: Name | B1: Registration No. | C1: Contact Person | D1: Registered Office Address | E1: Registered Office Email-Id | F1: Registered Office Telephone | G1: Registered Office Fax | H1: Registered Office City | I1: Registered Office State | J1: Registered Office Pincode | K1: Correspondence Address | L1: Correspondence Email-Id | M1: Correspondence Telephone | N1: Correspondence Fax | O1: Correspondence City | P1: Correspondence State | Q1: Correspondence Pincode | R1: Validity From | S1: Validity To | T1: Country | U1: Lead Type | V1: Multi-Registered | W1: source_category | X1: email_domain | Y1: email_type | Z1: entity_type | AA1: data_completeness_score | AB1: lead_priority_score | AC1: lead_bucket | AD1: duplicate_group_key | AE1: exclusion_reason | AF1: review_reason | AG1: recommended_next_step
A2: Spark PWM Private Limited | B2: INP200007274 | C2: Anupam Mohaney | D2: No. 1, 3rd Floor, First Crescent Park Road, , Gandhi Nagar, Adyar | E2: pwm.compliance@sparkcapital.in | F2: 9104469250000 | G2: 9104469250000 | H2: CHENNAI | I2: TAMIL NADU | J2: 600020 | K2: No. 1, 3rd Floor, First Crescent Park Road, , Gandhi Nagar, Adyar | O2: CHENNAI | P2: TAMIL NADU | Q2: 600020 | R2: Sep 14, 2021 | S2: Perpetual | U2: Portfolio Manager | V2: Yes | W2: Portfolio Manager | X2: sparkcapital.in | Y2: corporate_domain | Z2: company_firm | AA2: 100 | AB2: 100 | AC2: A - Contact First | AD2: DOMAIN::sparkcapital.in | AF2: possible_duplicate_or_multi_category_entity | AG2: Manually verify website and contact details before outreach
A3: Waterfield Fund Managers Private Limited | B3: INP000008288 | C3: Shivani Sharma | D3: 142 Maker Chamber VI 220 , Jamnalal Bajaj Marg Nariman Point | E3: shivani.sharma@waterfieldadvisors.com | F3: 00919987358249 | G3: 00919987358249 | H3: MUMBAI | I3: MAHARASHTRA | J3: 400021 | K3: Unit no 07 7th office level equivalent to the 14th floor Avighna House, 82 Annie Besant Road Worli | O3: MUMBAI | P3: MAHARASHTRA | Q3: 400018 | R3: Sep 07, 2023 | S3: Perpetual | U3: Portfolio Manager | V3: No | W3: Portfolio Manager | X3: waterfieldadvisors.com | Y3: corporate_domain | Z3: company_firm | AA3: 100 | AB3: 100 | AC3: A - Contact First | AD3: DOMAIN::waterfieldadvisors.com | AF3: possible_duplicate_or_multi_category_entity | AG3: Manually verify website and contact details before outreach
A4: 360 ONE Alternates Asset Management Limited | B4: INP000008640 | C4: Chirag Gandhi | D4: 360 ONE Centre, Kamala City, Lower Parel West | E4: pmscompliance@360.one | F4: 9102248765600 | G4: 9102248765600 | H4: MUMBAI | I4: MAHARASHTRA | J4: 400013 | K4: 360 ONE Centre, Kamala City, Lower Parel West | O4: MUMBAI | P4: MAHARASHTRA | Q4: 400013 | R4: Mar 27, 2024 | S4: Perpetual | U4: Portfolio Manager | V4: No | W4: Portfolio Manager | X4: 360.one | Y4: corporate_domain | Z4: company_firm | AA4: 100 | AB4: 100 | AC4: A - Contact First | AD4: DOMAIN::360.one | AF4: possible_duplicate_or_multi_category_entity | AG4: Manually verify website and contact details before outreach
A5: Spark Fund Advisors LLP | B5: INP000008835 | C5: Amrita Pillai | D5: No. 1, 3rd Floor, First Crescent Park Road,, Gandhi Nagar, Adyar, | E5: compliance@sparkcapital.in | F5: 9104469250000 | G5: 9104469250000 | H5: CHENNAI | I5: TAMIL NADU | J5: 600020 | K5: No. 1, 3rd Floor, First Crescent Park Road, Gandhi Nagar, Adyar, | O5: CHENNAI | P5: TAMIL NADU | Q5: 600020 | R5: Jul 22, 2024 | S5: Perpetual | U5: Portfolio Manager | V5: No | W5: Portfolio Manager | X5: sparkcapital.in | Y5: corporate_domain | Z5: company_firm | AA5: 100 | AB5: 100 | AC5: A - Contact First | AD5: DOMAIN::sparkcapital.in | AF5: possible_duplicate_or_multi_category_entity | AG5: Manually verify website and contact details before outreach
A6: ASTEYA INVESTMENT MANAGERS LLP | B6: INA000000276 | C6: MR. ARUN BHAL | D6: 4G/4H, SIDDHIVINAYAK CHAMBERS,, 643, GANDHI NAGAR, OPP. MIG CLUB, BANDRA EAST, MUMBAI | E6: arun.bhal@asteyaglobal.com | F6: 2226514252 | G6: 2226514252 | H6: MUMBAI | I6: MAHARASHTRA | J6: 400051 | K6: 4G/4H, Siddhivinayak Chambers, 643, Gandhi Nagar, Opp. MIG Club, Bandra East, Mumbai | O6: MUMBAI | P6: MAHARASHTRA | Q6: 400051 | R6: Nov 21, 2013 | S6: Perpetual | U6: Investment Adviser | V6: No | W6: Investment Adviser | X6: asteyaglobal.com | Y6: corporate_domain | Z6: company_firm | AA6: 100 | AB6: 97 | AC6: A - Contact First | AD6: DOMAIN::asteyaglobal.com | AF6: possible_duplicate_or_multi_category_entity | AG6: Manually verify website and contact details before outreach
A7: ASK Wealth Advisors Private Limited | B7: INA000000532 | C7: Vijay Shah | D7: Birla Aurora, 16 Level, Office Floor 9 , Dr. Annie Besant Road, Worli | E7: askwa_compliance@askwealthadvisors.com | F7: 0919930235443 | G7: 0919930235443 | H7: MUMBAI | I7: MAHARASHTRA | J7: 400030 | K7: 28th floor, 2803, 2804 and 2805, One Lodha Place, Senapati Bapat Marg, Lower Parel | O7: MUMBAI | P7: MAHARASHTRA | Q7: 400013 | R7: Mar 31, 2023 | S7: Perpetual | U7: Investment Adviser | V7: Yes | W7: Investment Adviser | X7: askwealthadvisors.com | Y7: corporate_domain | Z7: company_firm | AA7: 100 | AB7: 97 | AC7: A - Contact First | AD7: DOMAIN::askwealthadvisors.com | AF7: possible_duplicate_or_multi_category_entity | AG7: Manually verify website and contact details before outreach
A8: Purnartha Investment Advisers Pvt.Ltd. | B8: INA000000672 | C8: Chandani Saruparia | D8: Rachna Bunglow,Near Dr.Shyamrao Kalmadi HighSchool,, Dr.Ketkar Road, Off Karve Road, Erandwane | E8: chandani.s@purnartha.com | F8: 919993969339 | G8: 919993969339 | H8: PUNE | I8: MAHARASHTRA | J8: 411004 | K8: Rachna Bunglow,Near Dr.Shyamrao Kalmadi HighSchool, Dr.Ketkar Road, Off Karve Road, Erandwane | O8: PUNE | P8: MAHARASHTRA | Q8: 411004 | R8: Dec 26, 2013 | S8: Perpetual | U8: Investment Adviser | V8: Yes | W8: Investment Adviser | X8: purnartha.com | Y8: corporate_domain | Z8: company_firm | AA8: 100 | AB8: 97 | AC8: A - Contact First | AD8: DOMAIN::purnartha.com | AF8: possible_duplicate_or_multi_category_entity | AG8: Manually verify website and contact details before outreach
A9: 360 ONE Investment Adviser and Trustee Services Limited | B9: INA000000888 | C9: Jatin Sanghani | D9: IIFL Centre, Kamala Mills, Senapati Bapat Marg, Lower Parel | E9: 360.compliance@360.one | F9: 0919769974254 | G9: 0919769974254 | H9: MUMBAI | I9: MAHARASHTRA | J9: 400013 | K9: 7th Floor,IIFL Centre, Kamala Mills Compound,Senapati Bapat Marg,Lower Parel (West), | O9: MUMBAI | P9: MAHARASHTRA | Q9: 400013 | R9: Jan 22, 2014 | S9: Perpetual | U9: Investment Adviser | V9: No | W9: Investment Adviser | X9: 360.one | Y9: corporate_domain | Z9: company_firm | AA9: 100 | AB9: 97 | AC9: A - Contact First | AD9: DOMAIN::360.one | AF9: possible_duplicate_or_multi_category_entity | AG9: Manually verify website and contact details before outreach
A10: WATERFIELD FINANCIAL AND INVESTMENT ADVISORS PRIVATE LIMITED | B10: INA000001811 | C10: Vivek Rajaraman | D10: 142, 14TH FLOOR, MAKER CHAMBERS, VI, 220, JAMNALAL BAJAJ MARG, NARIMAN POINT | E10: principal.officer@waterfieldadvisors.com | F10: 919987538394 | G10: 919987538394 | I10: MAHARASHTRA | J10: 400021 | K10: 7 Avighna House 82 Dr Annie Besant Road, Worli Naka Siddharth Nagar Worli Mumbai | O10: MUMBAI | P10: MAHARASHTRA | Q10: 400018 | R10: Jun 02, 2014 | S10: Perpetual | U10: Investment Adviser | V10: No | W10: Investment Adviser | X10: waterfieldadvisors.com | Y10: corporate_domain | Z10: company_firm | AA10: 100 | AB10: 97 | AC10: A - Contact First | AD10: DOMAIN::waterfieldadvisors.com | AF10: possible_duplicate_or_multi_category_entity | AG10: Manually verify website and contact details before outreach
A11: Julius Baer Wealth Advisors (India) Private Limited | B11: INA000003130 | C11: Naynesh Sampat | D11: Altimus, 2501, 25th Level, Pandurang Budhkar Marg, Worli | E11: naynesh.sampat@juliusbaer.com | F11: 91009823420785 | G11: 91009823420785 | H11: MUMBAI | I11: MAHARASHTRA | J11: 400018 | K11: Altimus, 2501, 25th Level, Pandurang Budhkar Marg, Worli | O11: MUMBAI | P11: MAHARASHTRA | Q11: 400018 | R11: Jun 30, 2015 | S11: Perpetual | U11: Investment Adviser | V11: No | W11: Investment Adviser | X11: juliusbaer.com | Y11: corporate_domain | Z11: company_firm | AA11: 100 | AB11: 97 | AC11: A - Contact First | AD11: DOMAIN::juliusbaer.com | AF11: possible_duplicate_or_multi_category_entity | AG11: Manually verify website and contact details before outreach
A12: EQUENTIS WEALTH ADVISORY SERVICES LIMITED | B12: INA000003874 | C12: Rakesh Gupta | D12: A-603, Marathon Futurex, Mafatlal Mills Compound,, N. M. Joshi Marg, Lower Parel, | E12: compliance@equentis.com | F12: 919152000163 | G12: 919152000163 | H12: MUMBAI | I12: MAHARASHTRA | J12: 400013 | K12: A-603, Marathon Futurex, Mafatlal Mills Compound, N. M. Joshi Marg, Lower Parel, | O12: MUMBAI | P12: MAHARASHTRA | Q12: 400013 | R12: Dec 08, 2015 | S12: Perpetual | U12: Investment Adviser | V12: No | W12: Investment Adviser | X12: equentis.com | Y12: corporate_domain | Z12: company_firm | AA12: 100 | AB12: 97 | AC12: A - Contact First | AD12: DOMAIN::equentis.com | AF12: possible_duplicate_or_multi_category_entity | AG12: Manually verify website and contact details before outreach
A13: WEALTH FIRST INVESTMENT ADVISERS PVT. LTD. | B13: INA000005812 | C13: MR. NISHIL PANDYA | D13: CAPITOL HOUSE, 10, PARAS BUNGLOW II, NEAR CAMPUS CORNER, PRAHLADNAGAR, ANAND NAGAR | E13: nishil@wealthfirst.biz | F13: 07940240000 | G13: 07940240000 | H13: AHMEDABAD | I13: GUJARAT | J13: 380015 | K13: Capitol House, 10, Paras Bunglow II, Near Campus Corner, Prahladnagar, Anand Nagar | O13: AHMEDABAD | P13: GUJARAT | Q13: 380015 | R13: Jan 07, 2017 | S13: Perpetual | U13: Investment Adviser | V13: No | W13: Investment Adviser | X13: wealthfirst.biz | Y13: corporate_domain | Z13: company_firm | AA13: 100 | AB13: 97 | AC13: A - Contact First | AD13: DOMAIN::wealthfirst.biz | AF13: possible_duplicate_or_multi_category_entity | AG13: Manually verify website and contact details before outreach
A14: White Oak Capital Management Consultants LLP | B14: INA000008659 | C14: Riddhi Gohel | D14: Unit 6 2B, 6th Floor, Cnergy Building, Appasaheb Marathe Marg, Prabhadevi | E14: riddhi.gohel@whiteoakinvestors.com | F14: 91008976840036 | G14: 91008976840036 | H14: MUMBAI | I14: MAHARASHTRA | J14: 400025 | K14: Unit 6 2B, 6th Floor, Cnergy Building, Appasaheb Marathe Marg, Prabhadevi | L14: shweta.subramanian@whiteoakindia.com | M14: 91-00-9819155184 | N14: 91-00-9819155184 | O14: MUMBAI | P14: MAHARASHTRA | Q14: 400025 | R14: Oct 26, 2017 | S14: Perpetual | U14: Investment Adviser | V14: No | W14: Investment Adviser | X14: whiteoakinvestors.com | Y14: corporate_domain | Z14: company_firm | AA14: 100 | AB14: 97 | AC14: A - Contact First | AD14: DOMAIN::whiteoakinvestors.com | AF14: possible_duplicate_or_multi_category_entity | AG14: Manually verify website and contact details before outreach
A15: Sicomoro Advisors Private Limited | B15: INA000009834 | C15: Amit Khandelwal | D15: 102, first floor, Pharma Search House,, B.G. Kher Marg, Worli | E15: amit.khandelwal@sicomoro.in | F15: 912249636131 | G15: 912249636131 | H15: MUMBAI | I15: MAHARASHTRA | J15: 400018 | K15: 102, first floor, Pharma Search House, B.G. Kher Marg, Worli | O15: MUMBAI | P15: MAHARASHTRA | Q15: 400018 | R15: Feb 15, 2018 | S15: Perpetual | U15: Investment Adviser | V15: Yes | W15: Investment Adviser | X15: sicomoro.in | Y15: corporate_domain | Z15: company_firm | AA15: 100 | AB15: 97 | AC15: A - Contact First | AD15: DOMAIN::sicomoro.in | AF15: possible_duplicate_or_multi_category_entity | AG15: Manually verify website and contact details before outreach
A16: SWASTIKA INVESTMART LTD. | B16: INA000009843 | C16: SUNIL NYATI | D16: Office No. 104, 1st Floor, KESHAVA Commercial Building, Plot No.C 5, E Block, Bandra Kurla Complex, Opp GST Bhavan, Bandra East, | E16: COMPLIANCE@SWASTIKA.CO.IN | F16: 917310736644221 | G16: 917310736644221 | H16: MUMBAI | I16: MAHARASHTRA | J16: 400051 | K16: 48, JAORA COMPOUND, MYH ROAD | O16: INDORE | P16: MADHYA PRADESH | Q16: 452001 | R16: Feb 16, 2018 | S16: Perpetual | U16: Investment Adviser | V16: No | W16: Investment Adviser | X16: swastika.co.in | Y16: corporate_domain | Z16: company_firm | AA16: 100 | AB16: 97 | AC16: A - Contact First | AD16: DOMAIN::swastika.co.in | AF16: possible_duplicate_or_multi_category_entity | AG16: Manually verify website and contact details before outreach
A17: Pioneer Client Associates Pvt Ltd | B17: INA100010660 | C17: Rakesh Khanna | D17: 2nd floor block B vatika Towers , Golf course road sector 54 | E17: rakeshkhanna@clientassociates.com | F17: 911244995400 | G17: 911244995400 | H17: GURGAON | I17: HARYANA | J17: 122002 | K17: 2nd floor block B vatika Towers , Golf course road sector 54 | O17: GURGAON | P17: HARYANA | Q17: 122002 | R17: May 23, 2018 | S17: Perpetual | U17: Investment Adviser | V17: No | W17: Investment Adviser | X17: clientassociates.com | Y17: corporate_domain | Z17: company_firm | AA17: 100 | AB17: 97 | AC17: A - Contact First | AD17: DOMAIN::clientassociates.com | AF17: possible_duplicate_or_multi_category_entity | AG17: Manually verify website and contact details before outreach
A18: VIVEKAM FINANCIAL SERVICES PRIVATE LIMITED | B18: INA200000316 | C18: Vemuru VenkataKrishna Prasad | D18: Plot No.57, Road No.71, Jubilee Hills, Hyderabad | E18: vvkprasad@vivekam.co.in | F18: 0919848040548 | G18: 0919848040548 | H18: HYDERABAD | I18: ANDHRA PRADESH | J18: 500082 | K18: H.no.8-2-293/82/A/68, Road No.1, Jubilee Hills | O18: HYDERABAD | P18: ANDHRA PRADESH | Q18: 500033 | R18: Nov 22, 2013 | S18: Perpetual | U18: Investment Adviser | V18: No | W18: Investment Adviser | X18: vivekam.co.in | Y18: corporate_domain | Z18: company_firm | AA18: 100 | AB18: 97 | AC18: A - Contact First | AD18: DOMAIN::vivekam.co.in | AF18: possible_duplicate_or_multi_category_entity | AG18: Manually verify website and contact details before outreach
A19: CASPIAN IMPACT INVESTMENT ADVISER PRIVATE LIMITED | B19: INA200000753 | C19: VISWANATHA PRASAD | D19: 3RD FLOOR, 8-2-595/5/B/1, ROAD NO.10, BANJARA HILLS | E19: prasad@caspian.in | F19: 04066297100 | G19: 04066297100 | H19: HYDERABAD | I19: ANDHRA PRADESH | J19: 500034 | K19: 3rd floor, 8-2-595/5/B/1, Road No.10, Banjara Hills | P19: ANDHRA PRADESH | Q19: 500034 | R19: Dec 31, 2013 | S19: Perpetual | U19: Investment Adviser | V19: No | W19: Investment Adviser | X19: caspian.in | Y19: corporate_domain | Z19: company_firm | AA19: 100 | AB19: 97 | AC19: A - Contact First | AD19: DOMAIN::caspian.in | AF19: possible_duplicate_or_multi_category_entity | AG19: Manually verify website and contact details before outreach
A20: RIGHT HORIZONS INVESTMENT ADVISORY SERVICES PRIVATE LTD | B20: INA200002601 | C20: Apoorva Patil | D20: 6, AREKERE VILLAGE,, OPP, BIRTISH BIOLOGICALS, BANNAERGHATTA ROAD, | E20: complianceofficer@righthorizons.com | F20: 0919545238236 | G20: 0919545238236 | H20: BANGALORE | I20: KARNATAKA | J20: 560076 | K20: 6, AREKERE VILLAGE, OPP, BIRTISH BIOLOGICALS, BANNAERGHATTA ROAD, | O20: BANGALORE | P20: KARNATAKA | Q20: 560076 | R20: Jan 27, 2015 | S20: Perpetual | U20: Investment Adviser | V20: No | W20: Investment Adviser | X20: righthorizons.com | Y20: corporate_domain | Z20: company_firm | AA20: 100 | AB20: 97 | AC20: A - Contact First | AD20: DOMAIN::righthorizons.com | AF20: possible_duplicate_or_multi_category_entity | AG20: Manually verify website and contact details before outreach
A21: ENTRUST FAMILY OFFICE INVESTMENT ADVISORS PVT. LTD. | B21: INA200004201 | C21: Pradeep A N | D21: N0.24, 4th floor,1st Cross, Magrath Road | E21: compliance@entrust.co.in | F21: 910228041479777 | G21: 910228041479777 | H21: BANGALORE | I21: KARNATAKA | J21: 560025 | K21: NO.24, 4TH FLOOR, 1ST CROSS, MAGRATH ROAD, BEHIND GARUDA MALL | O21: BANGALORE | P21: KARNATAKA | Q21: 560025 | R21: Feb 16, 2016 | S21: Perpetual | U21: Investment Adviser | V21: No | W21: Investment Adviser | X21: entrust.co.in | Y21: corporate_domain | Z21: company_firm | AA21: 100 | AB21: 97 | AC21: A - Contact First | AD21: DOMAIN::entrust.co.in | AF21: possible_duplicate_or_multi_category_entity | AG21: Manually verify website and contact details before outreach
A22: PHI CAPITAL SERVICES LLP | B22: INA200004284 | C22: MR. P SIVARAM | D22: LG 1A, Siddhartha Chambers, Near IIT Gate, Kalu Sarai, Hauz Khas | E22: sp@phicapital.in | F22: 04428286556 | G22: 04428286556 | H22: DELHI | I22: NATIONAL CAPITAL TERRITORY OF DELHI | J22: 110016 | K22: 3rd Floor, Jayalakshmi Estates, No. 29, Haddows Road, Nungambakkam | O22: CHENNAI | P22: TAMIL NADU | Q22: 600006 | R22: Mar 04, 2016 | S22: Perpetual | U22: Investment Adviser | V22: No | W22: Investment Adviser | X22: phicapital.in | Y22: corporate_domain | Z22: company_firm | AA22: 100 | AB22: 97 | AC22: A - Contact First | AD22: DOMAIN::phicapital.in | AF22: possible_duplicate_or_multi_category_entity | AG22: Manually verify website and contact details before outreach
A23: NARNOLIA INVESTMENT ADVISORS PRIVATE LIMITED | B23: INA300005439 | C23: Anchal Narnolia | D23: Marble Arch, 236B A.J.C. Bose Road, 2nd Floor, Room No. 201 | E23: compliance@narnolia.com | F23: 0919163750006 | G23: 0919163750006 | H23: KOLKATA | I23: WEST BENGAL | J23: 700020 | K23: Marble Arch, 236B A.J.C. Bose Road, 2nd Floor, Room No. 201 | O23: KOLKATA | P23: WEST BENGAL | Q23: 700020 | R23: Aug 25, 2016 | S23: Perpetual | U23: Investment Adviser | V23: No | W23: Investment Adviser | X23: narnolia.com | Y23: corporate_domain | Z23: company_firm | AA23: 100 | AB23: 97 | AC23: A - Contact First | AD23: DOMAIN::narnolia.com | AF23: possible_duplicate_or_multi_category_entity | AG23: Manually verify website and contact details before outreach
A24: GreenEdge Wealth Services LLP | B24: INA000011574 | C24: RESHA DHAVAL HARIA | D24: The Summit Business Bay Unit No. 1123, 11th Floor, Opp. Movie Max Cinema,, Next to the Western Express Highway Metro Station,Off. Andheri Kurla Road, Gundavali, Andheri East | E24: info@greenedgewealth.com | F24: 0917400241555 | G24: 0917400241555 | H24: MUMBAI | I24: MAHARASHTRA | J24: 400093 | K24: The Summit Business Bay Unit No. 1123, 11th Floor, Opp. Movie Max Cinema, Next to the Western Express Highway Metro Station,Off. Andheri Kurla Road, Gundavali, Andheri East | O24: MUMBAI | P24: MAHARASHTRA | Q24: 400093 | R24: Aug 31, 2018 | S24: Perpetual | U24: Investment Adviser | V24: No | W24: Investment Adviser | X24: greenedgewealth.com | Y24: corporate_domain | Z24: company_firm | AA24: 100 | AB24: 97 | AC24: A - Contact First | AD24: DOMAIN::greenedgewealth.com | AF24: possible_duplicate_or_multi_category_entity | AG24: Manually verify website and contact details before outreach
A25: BUGLEROCK BHUVI INVESTMENT ADVISERS PRIVATE LIMITED | B25: INA200012674 | C25: Neha Sharma | D25: Prestige Takt, 1st Floor, No. 23,, Kasturba Road Cross, | E25: compliance.ria@buglerock.asia | F25: 918069029000 | G25: 918069029000 | H25: BANGALORE | I25: KARNATAKA | J25: 560001 | K25: Prestige Takt, 1st Floor, No. 23, Kasturba Road Cross, | O25: BANGALORE | P25: KARNATAKA | Q25: 560001 | R25: Mar 12, 2019 | S25: Perpetual | U25: Investment Adviser | V25: No | W25: Investment Adviser | X25: buglerock.asia | Y25: corporate_domain | Z25: company_firm | AA25: 100 | AB25: 97 | AC25: A - Contact First | AD25: DOMAIN::buglerock.asia | AF25: possible_duplicate_or_multi_category_entity | AG25: Manually verify website and contact details before outreach
A26: Emkay Wealth Advisory Limited | B26: INA000013961 | C26: Sonal Jadhav | D26: 7th Floor, The Ruby,, Senapati Bapat Marg, Dadar West, | E26: compliance@emkayglobal.com | F26: 9102266299299 | G26: 9102266299299 | H26: MUMBAI | I26: MAHARASHTRA | J26: 400028 | K26: Paragon Center, C-06, Ground Floor, Pandurang Budhkar Marg, Worli, | O26: MUMBAI | P26: MAHARASHTRA | Q26: 400013 | R26: Sep 16, 2019 | S26: Perpetual | U26: Investment Adviser | V26: No | W26: Investment Adviser | X26: emkayglobal.com | Y26: corporate_domain | Z26: company_firm | AA26: 100 | AB26: 97 | AC26: A - Contact First | AD26: DOMAIN::emkayglobal.com | AF26: possible_duplicate_or_multi_category_entity | AG26: Manually verify website and contact details before outreach
A27: Altinvest Capital Advisors Private Limited | B27: INA200014706 | C27: Kunal Moktan | D27: 10th Floor,SKAV Seethalakshmi, 21/22, Kasturba Road, Banglore | E27: kunal.moktan@propsharecapital.com | F27: 9108042283385 | G27: 9108042283385 | H27: BANGALORE | I27: KARNATAKA | J27: 560001 | K27: 10th Floor, SKAV, Seethalakshmi, Kasturba Road 21/22 | O27: BANGALORE | P27: KARNATAKA | Q27: 560001 | R27: May 29, 2020 | S27: Perpetual | U27: Investment Adviser | V27: No | W27: Investment Adviser | X27: propsharecapital.com | Y27: corporate_domain | Z27: company_firm | AA27: 100 | AB27: 97 | AC27: A - Contact First | AD27: DOMAIN::propsharecapital.com | AF27: possible_duplicate_or_multi_category_entity | AG27: Manually verify website and contact details before outreach
A28: Abakkus Asset Manager Private Limited | B28: INA000015729 | C28: Merlin Nadar | D28: 6th Floor,Param House,Shanti Nagar,Santacruz Chembur Link Road, Santacruz East | E28: merlin.nadar@abakkusinvest.com | F28: 0917039820098 | G28: 0917039820098 | H28: MUMBAI | I28: MAHARASHTRA | J28: 400055 | K28: 6th Floor,Param House,Shanti Nagar,Santacruz Chembur Link Road, Santacruz East | O28: MUMBAI | P28: MAHARASHTRA | Q28: 400055 | R28: Feb 03, 2021 | S28: Perpetual | U28: Investment Adviser | V28: Yes | W28: Investment Adviser | X28: abakkusinvest.com | Y28: corporate_domain | Z28: company_firm | AA28: 100 | AB28: 97 | AC28: A - Contact First | AD28: DOMAIN::abakkusinvest.com | AF28: possible_duplicate_or_multi_category_entity | AG28: Manually verify website and contact details before outreach
A29: RENAISSANCE SMART TECH PRIVATE LIMITED | B29: INA000016436 | C29: Nidhi Kamani | D29: Office No. 508, B Wing, 5th Floor,, Mittal Commercia Premises Co-op Ltd., Off. M.V. Road. Near Mittal Estate, Marol, Andheri East | E29: nidhi.kamani@renaissanceinvest.in | F29: 0919920980102 | G29: 0919920980102 | H29: MUMBAI | I29: MAHARASHTRA | J29: 400059 | K29: Office No. 508, B Wing, 5th Floor, Mittal Commercia Premises Co-op Ltd., Off. M.V. Road. Near Mittal Estate, Marol, Andheri East | O29: MUMBAI | P29: MAHARASHTRA | Q29: 400059 | R29: Nov 30, 2021 | S29: Perpetual | U29: Investment Adviser | V29: No | W29: Investment Adviser | X29: renaissanceinvest.in | Y29: corporate_domain | Z29: company_firm | AA29: 100 | AB29: 97 | AC29: A - Contact First | AD29: DOMAIN::renaissanceinvest.in | AF29: possible_duplicate_or_multi_category_entity | AG29: Manually verify website and contact details before outreach
A30: Compound Everyday Capital Management LLP | B30: INA000017198 | C30: Surbhi Sarda | D30: Sakar Bhawan 2nd floor, ATM side,, 21/4 Ratlam Kothi Main Road, Above Federal Bank | E30: surbhi@cedcapital.in | F30: 9107312510070 | G30: 9107312510070 | H30: INDORE | I30: MADHYA PRADESH | J30: 452001 | K30: Sakar Bhawan 2nd floor, ATM side, 21/4 Ratlam Kothi Main Road, Above Federal Bank | O30: INDORE | P30: MADHYA PRADESH | Q30: 452001 | R30: Sep 23, 2022 | S30: Perpetual | U30: Investment Adviser | V30: No | W30: Investment Adviser | X30: cedcapital.in | Y30: corporate_domain | Z30: company_firm | AA30: 100 | AB30: 97 | AC30: A - Contact First | AD30: DOMAIN::cedcapital.in | AF30: possible_duplicate_or_multi_category_entity | AG30: Manually verify website and contact details before outreach
A31: SINCERE SYNDICATION AND CORPORATE SERVICES LLP | B31: INA000017453 | C31: Sivaramakrishnan Raghavan | D31: Adwave Towers, 3rd Floor, Block A, No. 9, South Boag Rd, T Nagar | E31: siva@sinceresyndication.com | F31: 0919884058398 | G31: 0919884058398 | H31: CHENNAI | I31: TAMIL NADU | J31: 600017 | K31: Adwave Towers, 3rd Floor, Block A, No. 9, South Boag Rd, T Nagar | O31: CHENNAI | P31: TAMIL NADU | Q31: 600017 | R31: Dec 13, 2022 | S31: Perpetual | U31: Investment Adviser | V31: Yes | W31: Investment Adviser | X31: sinceresyndication.com | Y31: corporate_domain | Z31: company_firm | AA31: 100 | AB31: 97 | AC31: A - Contact First | AD31: DOMAIN::sinceresyndication.com | AF31: possible_duplicate_or_multi_category_entity | AG31: Manually verify website and contact details before outreach
... A33: Apricus Wealth Investment Managers LLP | B33: INA000017657 | C33: Vikrant Gupta | D33: F3/16 Model Town-2, Delhi - 110009 | E33: vikrant@apricuswealth.in | F33: 022919810302008 | G33: 022919810302008 | H33: DELHI | I33: NATIONAL CAPITAL TERRITORY OF DELHI | J33: 110009 | K33: F3/16 Model Town-2, Delhi - 110009 | O33: DELHI | P33: NATIONAL CAPITAL TERRITORY OF DELHI | Q33: 110009 | R33: Feb 20, 2023 | S33: Perpetual | U33: Investment Adviser | V33: Yes | W33: Investment Adviser | X33: apricuswealth.in | Y33: corporate_domain | Z33: company_firm | AA33: 100 | AB33: 97 | AC33: A - Contact First | AD33: DOMAIN::apricuswealth.in | AF33: possible_duplicate_or_multi_category_entity | AG33: Manually verify website and contact details before outreach
A34: Tamohara Investment Managers Private Limited | B34: INA000017842 | C34: Rajesh Kodnaney | D34: 1402, Peninsula Park, Off Veera Desai Road, Andheri West, | E34: rajesh@tamohara.net | F34: 0000000000 | G34: 0000000000 | H34: MUMBAI | I34: MAHARASHTRA | J34: 400053 | K34: 1402, Peninsula Park, , Off Veera Desai Road, Andheri West, Mumbai | L34: rajesh@tamohara.net | M34: 0-0-00000000 | N34: 0-0-00000000 | O34: MUMBAI | P34: MAHARASHTRA | Q34: 400053 | R34: Apr 20, 2023 | S34: Perpetual | U34: Investment Adviser | V34: Yes | W34: Investment Adviser | X34: tamohara.net | Y34: corporate_domain | Z34: company_firm | AA34: 100 | AB34: 97 | AC34: A - Contact First | AD34: DOMAIN::tamohara.net | AF34: possible_duplicate_or_multi_category_entity | AG34: Manually verify website and contact details before outreach
A35: DRCHOKSEY FINSERV PRIVATE LIMITED | B35: INA000017903 | C35: Maulik Trivedi | D35: C-5/6, 5th Floor, Abhishek Building, Behind Monginis Cake Factory, Off New Link Road,, Andheri West, | E35: compliance@devenchoksey.com | F35: 918104482640 | G35: 918104482640 | H35: MUMBAI | I35: MAHARASHTRA | J35: 400058 | K35: C-5/6, 5th Floor, Abhishek Building, Behind Monginis Cake Factory, Off New Link Road, Andheri West, | O35: MUMBAI | P35: MAHARASHTRA | Q35: 400058 | R35: Apr 24, 2023 | S35: Perpetual | U35: Investment Adviser | V35: Yes | W35: Investment Adviser | X35: devenchoksey.com | Y35: corporate_domain | Z35: company_firm | AA35: 100 | AB35: 97 | AC35: A - Contact First | AD35: DOMAIN::devenchoksey.com | AF35: possible_duplicate_or_multi_category_entity | AG35: Manually verify website and contact details before outreach
A36: Concept Investwell Private Limited | B36: INA000018337 | C36: Hemantkumar Desai | D36: 10/A, Union Heights, Maharana Pratap Road,, Rahul Raj Mall Lane, Dumas Road, Surat, Gujarat | E36: hemant@conceptinvestwell.com | F36: 026102206001 | G36: 026102206001 | H36: SURAT | I36: GUJARAT | J36: 395007 | K36: 10/A, Union Heights, Maharana Pratap Road, Rahul Raj Mall Lane, Dumas Road, Surat, Gujarat | O36: SURAT | P36: GUJARAT | Q36: 395007 | R36: Aug 02, 2023 | S36: Perpetual | U36: Investment Adviser | V36: No | W36: Investment Adviser | X36: conceptinvestwell.com | Y36: corporate_domain | Z36: company_firm | AA36: 100 | AB36: 97 | AC36: A - Contact First | AD36: DOMAIN::conceptinvestwell.com | AF36: possible_duplicate_or_multi_category_entity | AG36: Manually verify website and contact details before outreach
A37: CENTRICITY ADVISORY SERVICES PRIVATE LIMITED | B37: INA000018559 | C37: Arpita Hegde | D37: 203B, 2nd Floor, Tower B, Global Business Park, Mehrauli Gurgaon Road | E37: ah@centricity.co.in | F37: 00919619623465 | G37: 00919619623465 | H37: GURGAON | I37: HARYANA | J37: 122002 | K37: Unit No. 203-B, 2nd Floor, Tower B, Global Business Park, MG Road, Gurugram | O37: GURGAON | P37: HARYANA | Q37: 122002 | R37: Nov 13, 2023 | S37: Perpetual | U37: Investment Adviser | V37: No | W37: Investment Adviser | X37: centricity.co.in | Y37: corporate_domain | Z37: company_firm | AA37: 100 | AB37: 97 | AC37: A - Contact First | AD37: DOMAIN::centricity.co.in | AF37: possible_duplicate_or_multi_category_entity | AG37: Manually verify website and contact details before outreach
A38: JVT Investment Adviser LLP | B38: INA000019132 | C38: Nishant Mangla | D38: Atelier Level 1, Suite No. 3, Worldmark 2,, Aerocity, IGI Airport, South West Delhi, New Delhi, | E38: Nishant@cxpartners.in | F38: 911147640000 | G38: 911147640000 | H38: DELHI | I38: NATIONAL CAPITAL TERRITORY OF DELHI | J38: 110037 | K38: Atelier Level 1, Suite No. 3, Worldmark 2, Aerocity, IGI Airport, South West Delhi, New Delhi, | O38: DELHI | P38: NATIONAL CAPITAL TERRITORY OF DELHI | Q38: 110037 | R38: Jun 11, 2024 | S38: Perpetual | U38: Investment Adviser | V38: No | W38: Investment Adviser | X38: cxpartners.in | Y38: corporate_domain | Z38: company_firm | AA38: 100 | AB38: 97 | AC38: A - Contact First | AD38: DOMAIN::cxpartners.in | AF38: possible_duplicate_or_multi_category_entity | AG38: Manually verify website and contact details before outreach
A39: LGT Securities India Private Limited | B39: INA000019716 | C39: Nimish Shah | D39: 7TH Floor, A Block, Shiv Sagar Estate, Dr Annie Besant Road,, Near Nehru Transit Camp Centre, Worli, | E39: nimish.shah@lgtindia.in | F39: 91009821046488 | G39: 91009821046488 | H39: MUMBAI | I39: MAHARASHTRA | J39: 400018 | K39: 7TH Floor, A Block, Shiv Sagar Estate, Dr Annie Besant Road, Near Nehru Transit Camp Centre, Worli, | O39: MUMBAI | P39: MAHARASHTRA | Q39: 400018 | R39: Dec 06, 2024 | S39: Perpetual | U39: Investment Adviser | V39: No | W39: Investment Adviser | X39: lgtindia.in | Y39: corporate_domain | Z39: company_firm | AA39: 100 | AB39: 97 | AC39: A - Contact First | AD39: DOMAIN::lgtindia.in | AF39: possible_duplicate_or_multi_category_entity | AG39: Manually verify website and contact details before outreach
A40: Ardeko Asset Management Private Limited | B40: INA000019831 | C40: Dwaitin Dave | D40: 705, 7th Floor, The Ridge, Opp. Novotel,, Nr Iscon Cross Road, SG Highway | E40: info@ardeko.in | F40: 00917859980782 | G40: 00917859980782 | H40: AHMEDABAD | I40: GUJARAT | J40: 380060 | K40: 705, 7th Floor, The Ridge, Opp. Novotel, Nr Iscon Cross Road, SG Highway | O40: AHMEDABAD | P40: GUJARAT | Q40: 380060 | R40: Jan 28, 2025 | S40: Perpetual | U40: Investment Adviser | V40: No | W40: Investment Adviser | X40: ardeko.in | Y40: corporate_domain | Z40: company_firm | AA40: 100 | AB40: 97 | AC40: A - Contact First | AD40: DOMAIN::ardeko.in | AF40: possible_duplicate_or_multi_category_entity | AG40: Manually verify website and contact details before outreach
A41: Credent Asset Management Services Private Limited | B41: INA000019859 | C41: Harshal Gosarani | D41: Unit No. 609, 6th Floor, C-Wing, One BKC, G Block, Bandra Kurla, Complex, Bandra East, Mumbai City, Mumbai | E41: harshal@credentglobal.com | F41: 00918657032041 | G41: 00918657032041 | H41: MUMBAI | I41: MAHARASHTRA | J41: 400051 | K41: Unit No. 609, 6th Floor, C-Wing, One BKC, G Block, Bandra Kurla, Complex, Bandra East, Mumbai City, Mumbai | O41: MUMBAI | P41: MAHARASHTRA | Q41: 400051 | R41: Jan 30, 2025 | S41: Perpetual | U41: Investment Adviser | V41: Yes | W41: Investment Adviser | X41: credentglobal.com | Y41: corporate_domain | Z41: company_firm | AA41: 100 | AB41: 97 | AC41: A - Contact First | AD41: DOMAIN::credentglobal.com | AF41: possible_duplicate_or_multi_category_entity | AG41: Manually verify website and contact details before outreach
A42: CKREDENCE WEALTH MANAGEMENT PRIVATE LIMITED | B42: INA000020846 | C42: Prakashkumar Mavani | D42: 901,902 & 903, , International Wealth Center, VIP Road, Vesu, | E42: prakash.mavani@ckredencewealth.com | F42: 912612614084406 | G42: 912612614084406 | H42: SURAT | I42: GUJARAT | J42: 395007 | K42: 901,902 & 903, , International Wealth Center, VIP Road, Vesu, | O42: SURAT | P42: GUJARAT | Q42: 395007 | R42: Aug 07, 2025 | S42: Perpetual | U42: Investment Adviser | V42: Yes | W42: Investment Adviser | X42: ckredencewealth.com | Y42: corporate_domain | Z42: company_firm | AA42: 100 | AB42: 97 | AC42: A - Contact First | AD42: DOMAIN::ckredencewealth.com | AF42: possible_duplicate_or_multi_category_entity | AG42: Manually verify website and contact details before outreach
A43: Crest Capital Management Private Limited | B43: INA000020907 | C43: Zuhaib Khan | D43: B/601, Lantane Mahindra S, LBS Marg, Bhandup West, Mumbai | E43: zuhaib@crest-group.co | F43: 00919871396555 | G43: 00919871396555 | H43: MUMBAI | I43: MAHARASHTRA | J43: 400078 | K43: B Wing, 6th Floor, Supreme Business Park, Cliff Avenue, Unit No. B, 501/A, Hiranandani Gardens, Powai | O43: MUMBAI | P43: MAHARASHTRA | Q43: 400076 | R43: Aug 07, 2025 | S43: Perpetual | U43: Investment Adviser | V43: No | W43: Investment Adviser | X43: crest-group.co | Y43: corporate_domain | Z43: company_firm | AA43: 100 | AB43: 97 | AC43: A - Contact First | AD43: DOMAIN::crest-group.co | AF43: possible_duplicate_or_multi_category_entity | AG43: Manually verify website and contact details before outreach
A44: SPARK PWM PRIVATE LIMITED | B44: INA000021067 | C44: Saurav Lugria | D44: No.1,3rd Floor, First Crescent Park Road, Gandhi Nagar, Adyar, Chennai | E44: saurav.l@sparkcapital.in | F44: 00919819146237 | G44: 00919819146237 | H44: CHENNAI | I44: TAMIL NADU | J44: 600020 | K44: No. 1252, 5th Floor,Building No. 12, Solitaire Corporate Park, Andheri Kurla Road, Chakala, Andheri East, Mumbai | O44: MUMBAI | P44: MAHARASHTRA | Q44: 400093 | R44: Sep 25, 2025 | S44: Perpetual | U44: Investment Adviser | V44: No | W44: Investment Adviser | X44: sparkcapital.in | Y44: corporate_domain | Z44: company_firm | AA44: 100 | AB44: 97 | AC44: A - Contact First | AD44: DOMAIN::sparkcapital.in | AF44: possible_duplicate_or_multi_category_entity | AG44: Manually verify website and contact details before outreach
A45: EUREKA STOCK & SHARE BROKING SERVICES LIMITED | B45: INA000021137 | C45: Debomita Maity | D45: 1101, Merlin Infinite, DN 51, 11th Floor, Salt Lake, Sector 5, Kolkata,West Bengal | E45: debomita@eurekasec.com | F45: 0091983600908 | G45: 0091983600908 | H45: KOLKATA | I45: WEST BENGAL | J45: 700091 | K45: 1101, Merlin Infinite, DN 51, 11th Floor, Salt Lake, Sector 5, Kolkata,West Bengal | O45: KOLKATA | P45: WEST BENGAL | Q45: 700091 | R45: Oct 08, 2025 | S45: Perpetual | U45: Investment Adviser | V45: No | W45: Investment Adviser | X45: eurekasec.com | Y45: corporate_domain | Z45: company_firm | AA45: 100 | AB45: 97 | AC45: A - Contact First | AD45: DOMAIN::eurekasec.com | AF45: possible_duplicate_or_multi_category_entity | AG45: Manually verify website and contact details before outreach
A46: Dezerv Investments Private Limited | B46: INA000022914 | C46: Meetali Gandhi | D46: Unit No. 301, Trade Centre, Kanzul Iman Road, Bandra East | E46: meetali@dezerv.in | F46: 0000000000000000 | G46: 0000000000000000 | H46: MUMBAI | I46: MAHARASHTRA | J46: 400051 | K46: Unit No. 301, Trade Centre, Kanzul Iman Road, Bandra East | O46: MUMBAI | P46: MAHARASHTRA | Q46: 400051 | R46: Jun 25, 2026 | S46: Perpetual | U46: Investment Adviser | V46: Yes | W46: Investment Adviser | X46: dezerv.in | Y46: corporate_domain | Z46: company_firm | AA46: 100 | AB46: 97 | AC46: A - Contact First | AD46: DOMAIN::dezerv.in | AF46: possible_duplicate_or_multi_category_entity | AG46: Manually verify website and contact details before outreach
... A92: InCred Capital Wealth Portfolio Managers Private Limited | B92: INH000023922 | C92: Preeti Lalwani | D92: Unit No 1203, 12th floor, B Wing, The Capital, Plot No C 70, G Block, Bandra Kurla Complex, Bandra East | E92: compliance@incredcapital.com | F92: 002269041596 | G92: 002269041596 | H92: MUMBAI | I92: MAHARASHTRA | J92: 400051 | K92: Laxmi Towers, Office No 3, B Wing, 5th Floor, Plot No C 25, G Block, Bandra Kurla Complex, Bandra East | O92: MUMBAI | P92: MAHARASHTRA | Q92: 400051 | R92: Nov 28, 2025 | S92: Perpetual | U92: Research Analyst | V92: No | W92: Research Analyst | X92: incredcapital.com | Y92: corporate_domain | Z92: company_firm | AA92: 100 | AB92: 90 | AC92: A - Contact First | AD92: DOMAIN::incredcapital.com | AF92: possible_duplicate_or_multi_category_entity | AG92: Manually verify website and contact details before outreach
A93: ONE CENTURION VENTURES PRIVATE LIMITED | B93: INH000023968 | C93: Sagar Dave | D93: 601, Signature Suresh Sawant Road,, Off. Veera Desai Road, Andheri, | E93: sagar@onecenturion.in | F93: 918655742577 | H93: MUMBAI | I93: MAHARASHTRA | J93: 400053 | K93: 601/604, 6th floor, Lotus Signature,off Veer Desai Road, Andheri West | O93: MUMBAI | P93: MAHARASHTRA | Q93: 400053 | R93: Dec 01, 2025 | S93: Perpetual | U93: Research Analyst | V93: Yes | W93: Research Analyst | X93: onecenturion.in | Y93: corporate_domain | Z93: company_firm | AA93: 100 | AB93: 90 | AC93: A - Contact First | AD93: DOMAIN::onecenturion.in | AF93: possible_duplicate_or_multi_category_entity | AG93: Manually verify website and contact details before outreach
A94: Swastika Investmart Limited | B94: INH000024073 | C94: Santosh Meena | D94: Office No 104, 1st Floor, KESHAVA Commercial Building, Plot No.C 5, E Block, Bandra Kurla Complex, Opp GST Bhavan, Bandra East | E94: santosh.meena@swastika.co.in | F94: 007314840117 | G94: 007314840117 | H94: MUMBAI | I94: MAHARASHTRA | J94: 400051 | R94: Dec 11, 2025 | S94: Perpetual | U94: Research Analyst | V94: Yes | W94: Research Analyst | X94: swastika.co.in | Y94: corporate_domain | Z94: company_firm | AA94: 100 | AB94: 90 | AC94: A - Contact First | AD94: DOMAIN::swastika.co.in | AF94: possible_duplicate_or_multi_category_entity | AG94: Manually verify website and contact details before outreach
A95: NBHAVA CAPITAL PRIVATE LIMITED | B95: INH000024426 | C95: KONDURI CHAKRADHARA NAIDU | D95: No. 311, Tower A, Signature Altius, , Kollur Road, Kollur, Medak, Patancheru, | E95: CHAKRADHAR@NBHAVA.COM | F95: 00000000000000 | G95: 00000000000000 | H95: HYDERABAD | I95: TELANGANA | J95: 502300 | K95: No. 311, Tower A, Signature Altius, , Kollur Road, Kollur, Medak, Patancheru, | O95: HYDERABAD | P95: TELANGANA | Q95: 502300 | R95: Dec 23, 2025 | S95: Perpetual | U95: Research Analyst | V95: Yes | W95: Research Analyst | X95: nbhava.com | Y95: corporate_domain | Z95: company_firm | AA95: 100 | AB95: 90 | AC95: A - Contact First | AD95: DOMAIN::nbhava.com | AF95: possible_duplicate_or_multi_category_entity | AG95: Manually verify website and contact details before outreach
A96: FORT CAPITAL INVESTMENT ADVISORY PRIVATE LIMITED | B96: INH000024851 | C96: Swapnil Shah | D96: 304,3rd Floor, Hubtown Solaris, N.S. Phadke Marg, Near Flyover Bridge, Andheri East | E96: compliance@fortcapital.in | F96: 0000000000000 | G96: 0000000000000 | H96: MUMBAI | I96: MAHARASHTRA | J96: 400069 | R96: Feb 03, 2026 | S96: Perpetual | U96: Research Analyst | V96: Yes | W96: Research Analyst | X96: fortcapital.in | Y96: corporate_domain | Z96: company_firm | AA96: 100 | AB96: 90 | AC96: A - Contact First | AD96: DOMAIN::fortcapital.in | AF96: possible_duplicate_or_multi_category_entity | AG96: Manually verify website and contact details before outreach
A97: AlphaGrep Advisors Private Limited | B97: INH000025197 | C97: Shubham Sarjine | D97: Parinee Crescenzo, Unit No. I406, 14th Floor, G Block. Bandra Kurla Complex, Bandra East | E97: RAagadvisors@alphagrepadvisors.com | F97: 917710993310 | H97: MUMBAI | I97: MAHARASHTRA | J97: 400051 | K97: Parinee Crescenzo, Unit No. I406, 14th Floor, G Block. Bandra Kurla Complex, Bandra East | O97: MUMBAI | P97: MAHARASHTRA | Q97: 400051 | R97: Feb 27, 2026 | S97: Perpetual | U97: Research Analyst | V97: Yes | W97: Research Analyst | X97: alphagrepadvisors.com | Y97: corporate_domain | Z97: company_firm | AA97: 100 | AB97: 90 | AC97: A - Contact First | AD97: DOMAIN::alphagrepadvisors.com | AF97: possible_duplicate_or_multi_category_entity | AG97: Manually verify website and contact details before outreach
A98: CHASEALPHA GLOBAL RESEARCH PRIVATE LIMITED | B98: INH000025531 | C98: Vishvesh Harilal | D98: SH 17 P1 LEVEL COMMERCIAL OFFICE SHOPS MAKWANA ROAD VASANT OASIS JB NAGAR MAROL ANDHERI EAST | E98: vishvesh@chasealpha.in | F98: 008779174997 | G98: 008779174997 | H98: MUMBAI | I98: MAHARASHTRA | J98: 400059 | K98: SH 17 P1 LEVEL COMMERCIAL OFFICE SHOPS MAKWANA ROAD VASANT OASIS JB NAGAR MAROL ANDHERI EAST | O98: MUMBAI | P98: MAHARASHTRA | Q98: 400059 | R98: Mar 16, 2026 | S98: Perpetual | U98: Research Analyst | V98: No | W98: Research Analyst | X98: chasealpha.in | Y98: corporate_domain | Z98: company_firm | AA98: 100 | AB98: 90 | AC98: A - Contact First | AD98: DOMAIN::chasealpha.in | AF98: possible_duplicate_or_multi_category_entity | AG98: Manually verify website and contact details before outreach
A99: Neo Wealth Management Private Limited | B99: INH000025674 | C99: Dhirendra Rautela | D99: 903 B Wing, Marathon Futurex, NM Joshi Marg, Lower Parel | E99: compliance@neo-wealth.com | F99: 0000000000000 | G99: 0000000000000 | H99: MUMBAI | I99: MAHARASHTRA | J99: 400013 | K99: 903 B Wing, Marathon Futurex, NM Joshi Marg, Lower Parel | O99: MUMBAI | P99: MAHARASHTRA | Q99: 400013 | R99: Apr 01, 2026 | S99: Perpetual | U99: Research Analyst | V99: Yes | W99: Research Analyst | X99: neo-wealth.com | Y99: corporate_domain | Z99: company_firm | AA99: 100 | AB99: 90 | AC99: A - Contact First | AD99: DOMAIN::neo-wealth.com | AF99: possible_duplicate_or_multi_category_entity | AG99: Manually verify website and contact details before outreach
A100: JBV Share Broker And Fintech Private Limited | B100: INH000026822 | C100: Asit Mistry | D100: 1018, Millenium Business Hub, Sarthana, Varachha Road | E100: asit@growthavenues.co.in | F100: 009825145217 | G100: 009825145217 | H100: SURAT | I100: GUJARAT | J100: 395006 | K100: Office No-2001, The Junomonta Tower, Opp. Pal RTO, Near Rajhans Cinema, Pal - Adajan | O100: SURAT | P100: GUJARAT | Q100: 395009 | R100: May 06, 2026 | S100: Perpetual | U100: Research Analyst | V100: Yes | W100: Research Analyst | X100: growthavenues.co.in | Y100: corporate_domain | Z100: company_firm | AA100: 100 | AB100: 90 | AC100: A - Contact First | AD100: DOMAIN::growthavenues.co.in | AF100: possible_duplicate_or_multi_category_entity | AG100: Manually verify website and contact details before outreach
A101: WHERE2INVEST LIMITED | B101: INH000026965 | C101: Vaishnavi Pande | D101: 7th Floor Flat No. 708, Asian Suncity, Forest Department, Serilingampally Kondapur, | E101: vaishnavi.p@where2invest.com | F101: 0008977729398 | G101: 0008977729398 | H101: HYDERABAD | I101: TELANGANA | J101: 500084 | R101: May 12, 2026 | S101: Perpetual | U101: Research Analyst | V101: Yes | W101: Research Analyst | X101: where2invest.com | Y101: corporate_domain | Z101: company_firm | AA101: 100 | AB101: 90 | AC101: A - Contact First | AD101: DOMAIN::where2invest.com | AF101: possible_duplicate_or_multi_category_entity | AG101: Manually verify website and contact details before outreach
A102: NIVESHAAY INVESTMENT ADVISORS PRIVATE LIMITED | B102: INH000027830 | C102: Vikram Sharma | D102: Office no. 508, 5th Floor, SNS Platina, Vesu | E102: vikram@niveshaay.com | F102: 918690635092 | G102: 918690635092 | H102: SURAT | I102: GUJARAT | J102: 395007 | K102: Office no. 508, 5th Floor, SNS Platina, Vesu | O102: SURAT | P102: GUJARAT | Q102: 395007 | R102: Jun 04, 2026 | S102: Perpetual | U102: Research Analyst | V102: No | W102: Research Analyst | X102: niveshaay.com | Y102: corporate_domain | Z102: company_firm | AA102: 100 | AB102: 90 | AC102: A - Contact First | AD102: DOMAIN::niveshaay.com | AF102: possible_duplicate_or_multi_category_entity | AG102: Manually verify website and contact details before outreach
A103: MOJO MARKETS PRIVATE LIMITED | B103: INA000012528 | C103: MOHIT BATRA | D103: Benefice Business House, Office No. 3B, 3rd Floor,, C.S. 242, Mathuradas Mills Estate, N.M. Joshi Marg, Tulsi Pipe Road, Lower Parel West, | E103: mohit@MARKETSMOJO.COM | H103: MUMBAI | I103: MAHARASHTRA | J103: 400013 | K103: Benefice Business House, Office No. 3B, 3rd Floor, C.S. 242, Mathuradas Mills Estate, N.M. Joshi Marg, Tulsi Pipe Road, Lower Parel West, | O103: MUMBAI | P103: MAHARASHTRA | Q103: 400013 | R103: Feb 25, 2019 | S103: Perpetual | U103: Investment Adviser | V103: No | W103: Investment Adviser | X103: marketsmojo.com | Y103: corporate_domain | Z103: company_firm | AA103: 90 | AB103: 87 | AC103: A - Contact First | AD103: DOMAIN::marketsmojo.com | AF103: possible_duplicate_or_multi_category_entity | AG103: Manually verify website and contact details before outreach
A104: JEENA SCRIPTECH ALPHA ADVISORS PRIVATE LIMITED | B104: INA000013217 | C104: Gaurav Parikh | D104: JEENA HOUSE , PLOT NO 170, OM NAGAR , OFF PIPELINE ROAD , ANDHERI EAST | E104: gaurav@jsalphaa.com | H104: MUMBAI | I104: MAHARASHTRA | J104: 400099 | K104: JEENA HOUSE , PLOT NO 170, OM NAGAR , OFF PIPELINE ROAD , ANDHERI EAST | O104: MUMBAI | P104: MAHARASHTRA | Q104: 400099 | R104: May 07, 2019 | S104: Perpetual | U104: Investment Adviser | V104: Yes | W104: Investment Adviser | X104: jsalphaa.com | Y104: corporate_domain | Z104: company_firm | AA104: 90 | AB104: 87 | AC104: A - Contact First | AD104: DOMAIN::jsalphaa.com | AF104: possible_duplicate_or_multi_category_entity | AG104: Manually verify website and contact details before outreach
A105: FINNOVATE FINANCIAL SERVICES PVT LTD | B105: INA000013518 | C105: NEHAL MOTA | D105: UNIT NO. 703, 7th FLOOR, THE SUMMIT BUSINESS BAY, OFF ANDHERI KURLA ROAD, PVR CINEMAS ANDHERI EAST | E105: nehal.mota@finnovate.in | H105: MUMBAI | I105: MAHARASHTRA | J105: 400093 | K105: UNIT NO. 703, 7th FLOOR, THE SUMMIT BUSINESS BAY, OFF ANDHERI KURLA ROAD, PVR CINEMAS ANDHERI EAST | O105: MUMBAI | P105: MAHARASHTRA | Q105: 400093 | R105: Jun 19, 2019 | S105: Perpetual | U105: Investment Adviser | V105: No | W105: Investment Adviser | X105: finnovate.in | Y105: corporate_domain | Z105: company_firm | AA105: 90 | AB105: 87 | AC105: A - Contact First | AD105: DOMAIN::finnovate.in | AF105: possible_duplicate_or_multi_category_entity | AG105: Manually verify website and contact details before outreach
A106: Lotusdew Wealth and Investment Advisors Private Limited | B106: INA200013770 | C106: Abhishek Banerjee | D106: cabin 3 4th Floor 1A and 1B Jyoti Imperial, Gachibowli Rd Janardana Hills Lumbini Avenue | E106: abhishek.banerjee@lotusdew.in | H106: HYDERABAD | I106: TELANGANA | J106: 500032 | K106: 3 Eurospace, 4th Floor, Jyothi Imperial, Vamsiram Building, Gachibowli | O106: HYDERABAD | P106: TELANGANA | Q106: 500032 | R106: Aug 13, 2019 | S106: Perpetual | U106: Investment Adviser | V106: Yes | W106: Investment Adviser | X106: lotusdew.in | Y106: corporate_domain | Z106: company_firm | AA106: 90 | AB106: 87 | AC106: A - Contact First | AD106: DOMAIN::lotusdew.in | AF106: possible_duplicate_or_multi_category_entity | AG106: Manually verify website and contact details before outreach
A107: Samco Ventures Pvt. Ltd. | B107: INA000013828 | C107: Umesh Mehta | D107: 1004 A 10th Floor, Naman Midtown, Senapati Bapat Marg, Elphinstone Road | E107: umesh@samco.in | H107: MUMBAI | I107: MAHARASHTRA | J107: 400013 | K107: 1004 A 10th Floor, Naman Midtown, Senapati Bapat Marg, Elphinstone Road | O107: MUMBAI | P107: MAHARASHTRA | Q107: 400013 | R107: Aug 19, 2019 | S107: Perpetual | U107: Investment Adviser | V107: No | W107: Investment Adviser | X107: samco.in | Y107: corporate_domain | Z107: company_firm | AA107: 90 | AB107: 87 | AC107: A - Contact First | AD107: DOMAIN::samco.in | AF107: possible_duplicate_or_multi_category_entity | AG107: Manually verify website and contact details before outreach
A108: ARTHYA WEALTH AND INVESTMENTS PRIVATE LIMITED | B108: INA000015279 | C108: GAURAV ARORA | D108: Flat No. 12, Jumbo Co operative Housing Society, TPS IV, Road No. 1, Bandra West | E108: gaurav@arthyawealth.com | H108: MUMBAI | I108: MAHARASHTRA | J108: 400050 | K108: Flat No. 12, Jumbo Co operative Housing Society, TPS IV, Road No. 1, Bandra West | O108: MUMBAI | P108: MAHARASHTRA | Q108: 400050 | R108: Oct 07, 2020 | S108: Perpetual | U108: Investment Adviser | V108: No | W108: Investment Adviser | X108: arthyawealth.com | Y108: corporate_domain | Z108: company_firm | AA108: 90 | AB108: 87 | AC108: A - Contact First | AD108: DOMAIN::arthyawealth.com | AF108: possible_duplicate_or_multi_category_entity | AG108: Manually verify website and contact details before outreach
A109: ALFACCURATE ADVISORS PVT LTD | B109: INA000015701 | C109: BHUSHAN KOLI | D109: 503 B WING NAMAN MIDTOWN, SENAPATI BAPAT MARG ELPHINSTON ROAD | E109: bhushankoli@alfaccurate.com | H109: MUMBAI | I109: MAHARASHTRA | J109: 400013 | K109: 503 B WING NAMAN MIDTOWN, SENAPATI BAPAT MARG ELPHINSTON ROAD | O109: MUMBAI | P109: MAHARASHTRA | Q109: 400013 | R109: Jan 12, 2021 | S109: Perpetual | U109: Investment Adviser | V109: No | W109: Investment Adviser | X109: alfaccurate.com | Y109: corporate_domain | Z109: company_firm | AA109: 90 | AB109: 87 | AC109: A - Contact First | AD109: DOMAIN::alfaccurate.com | AF109: possible_duplicate_or_multi_category_entity | AG109: Manually verify website and contact details before outreach
A110: InvesQ Investment Advisors Private Limited | B110: INA000015808 | C110: Aashish Upganlawar | D110: SR NO 270/1/20, FLAT NO 101, HARMONY, BANER ROAD,, OPP MAULI PETROL PUMP, BANER, PUNE | E110: aashish@invesq.in | H110: PUNE | I110: MAHARASHTRA | J110: 411045 | K110: SR NO 270/1/20, FLAT NO 101, HARMONY, BANER ROAD, OPP MAULI PETROL PUMP, BANER, PUNE | O110: PUNE | P110: MAHARASHTRA | Q110: 411045 | R110: Mar 24, 2021 | S110: Perpetual | U110: Investment Adviser | V110: No | W110: Investment Adviser | X110: invesq.in | Y110: corporate_domain | Z110: company_firm | AA110: 90 | AB110: 87 | AC110: A - Contact First | AD110: DOMAIN::invesq.in | AF110: possible_duplicate_or_multi_category_entity | AG110: Manually verify website and contact details before outreach
A111: Citrus Advisors Private Limited | B111: INA000016348 | C111: Jeni Chaudhary | D111: 2B, 2, Neptune Apartments CHS,, Juhu Tara Road, Santacruz West | E111: jeni.shukla@citrusadvisors.com | H111: MUMBAI | I111: MAHARASHTRA | J111: 400054 | K111: Plot No. 116, Sector 21, Near Iskcon Temple, Opp Bhagwati Gardens, Kharghar, | O111: NAVI MUMBAI | P111: MAHARASHTRA | Q111: 410210 | R111: Oct 28, 2021 | S111: Perpetual | U111: Investment Adviser | V111: Yes | W111: Investment Adviser | X111: citrusadvisors.com | Y111: corporate_domain | Z111: company_firm | AA111: 90 | AB111: 87 | AC111: A - Contact First | AD111: DOMAIN::citrusadvisors.com | AF111: possible_duplicate_or_multi_category_entity | AG111: Manually verify website and contact details before outreach
A112: DAYCO SECURITIES PVT LTD | B112: INA300016701 | C112: Aditi Nundy | D112: 113 Park Street, Poddar Point B Block 7th Floor | E112: aditi@daycoindia.com | H112: KOLKATA | I112: WEST BENGAL | J112: 700016 | K112: 113 Park Street, Poddar Point B Block 7th Floor | O112: KOLKATA | P112: WEST BENGAL | Q112: 700016 | R112: Feb 18, 2022 | S112: Perpetual | U112: Investment Adviser | V112: No | W112: Investment Adviser | X112: daycoindia.com | Y112: corporate_domain | Z112: company_firm | AA112: 90 | AB112: 87 | AC112: A - Contact First | AD112: DOMAIN::daycoindia.com | AF112: possible_duplicate_or_multi_category_entity | AG112: Manually verify website and contact details before outreach
A113: HEM SECURITIES LIMITED | B113: INH100002250 | C113: Rohit sharma | D113: 203, JAIPUR TOWER, M.I. ROAD | E113: compliance@hemsecurities.com | F113: 1414051000 | G113: 1414051000 | H113: JAIPUR | I113: RAJASTHAN | J113: 302001 | K113: 203, JAIPUR TOWER, M.I. ROAD | O113: JAIPUR | P113: RAJASTHAN | Q113: 302001 | R113: Nov 17, 2015 | S113: Perpetual | U113: Research Analyst | V113: No | W113: Research Analyst | X113: hemsecurities.com | Y113: corporate_domain | Z113: company_firm | AA113: 100 | AB113: 85 | AC113: A - Contact First | AD113: DOMAIN::hemsecurities.com | AF113: possible_duplicate_or_multi_category_entity | AG113: Manually verify website and contact details before outreach
A114: SHARE INDIA SECURITIES LIMITED | B114: INH100005011 | C114: Beena Sadhwani | D114: Unit No. 615 and 616, 6th Floor, X-Change Plaza, Dalal Street Commercial Co-operative Society Limite, Road 5 E, Block 53, Zone 5, Gift City, Gandhi Nagar, | E114: beena.sadhwani@shareindia.com | F114: 918058301483 | G114: 918058301483 | H114: GANDHINAGAR | I114: GUJARAT | J114: 382050 | K114: A 15, Sector 64, Noida, Gautam Buddha Nagar | O114: NOIDA | P114: UTTAR PRADESH | Q114: 201301 | R114: Jul 14, 2017 | S114: Perpetual | U114: Research Analyst | V114: No | W114: Research Analyst | X114: shareindia.com | Y114: corporate_domain | Z114: company_firm | AA114: 100 | AB114: 85 | AC114: A - Contact First | AD114: DOMAIN::shareindia.com | AF114: possible_duplicate_or_multi_category_entity | AG114: Manually verify website and contact details before outreach
A115: ZEBU SHARE AND WEALTH MANAGEMENTS PRIVATE LIMITED | B115: INH200006044 | C115: VIJAYAKUMAR VELLAIYAN | D115: 36, KRISHNA COMPLEX, VCTV MAIN ROAD | E115: exchange@zebuetrade.com | F115: 914448557991 | G115: 914448557991 | H115: ERODE | I115: TAMIL NADU | J115: 638003 | K115: No301,4th Main Road, Burma Colony, Perungudi | O115: CHENNAI | P115: TAMIL NADU | Q115: 600096 | R115: Jun 21, 2018 | S115: Perpetual | U115: Research Analyst | V115: No | W115: Research Analyst | X115: zebuetrade.com | Y115: corporate_domain | Z115: company_firm | AA115: 100 | AB115: 85 | AC115: A - Contact First | AD115: DOMAIN::zebuetrade.com | AF115: possible_duplicate_or_multi_category_entity | AG115: Manually verify website and contact details before outreach
A116: FINVASIA SECURITIES PRIVATE LIMITED | B116: INH000011927 | C116: Ramanjeet Kaur | D116: 1108, Sector 21 B | E116: ccofspl@shoonya.com | F116: 9101726670000 | G116: 9101726670000 | H116: CHANDIGARH | I116: CHANDIGARH | J116: 160055 | K116: Finvasia Tower, C-214, 4th Floor, Phase 8 B, Sector 74, Industrial Focal Point, SAS Nagar | O116: MOHALI | P116: PUNJAB | Q116: 160055 | R116: Mar 16, 2023 | S116: Perpetual | U116: Research Analyst | V116: No | W116: Research Analyst | X116: shoonya.com | Y116: corporate_domain | Z116: company_firm | AA116: 100 | AB116: 85 | AC116: A - Contact First | AD116: DOMAIN::shoonya.com | AF116: possible_duplicate_or_multi_category_entity | AG116: Manually verify website and contact details before outreach
A117: FINVASIA SECURITIES PRIVATE LIMITED | B117: INH000011927 | C117: Ramanjeet Kaur | D117: 1108, Sector 21 B | E117: ccofspl@shoonya.com | F117: 9101726670000 | G117: 9101726670000 | H117: CHANDIGARH | I117: CHANDIGARH | J117: 160055 | K117: Finvasia Tower, C-214, 4th Floor, Phase 8 B, Sector 74, Industrial Focal Point, SAS Nagar | O117: MOHALI | P117: PUNJAB | Q117: 160055 | R117: Mar 16, 2023 | S117: Perpetual | U117: Research Analyst | V117: No | W117: Research Analyst | X117: shoonya.com | Y117: corporate_domain | Z117: company_firm | AA117: 100 | AB117: 85 | AC117: A - Contact First | AD117: DOMAIN::shoonya.com | AF117: possible_duplicate_or_multi_category_entity | AG117: Manually verify website and contact details before outreach
A118: dolat capital mkt pvt ltd | B118: INH000014012 | C118: SANDEEP BHOWAD | D118: 1401-1409, Dalal Street Commercial Co-op Soc Ltd,, Block 53 (Bldg. No.53E) Zone-5, Road-5E, Gift City | E118: ops@dolatcapital.com | F118: 912240969717 | G118: 912240969717 | H118: GANDHINAGAR | I118: GUJARAT | J118: 382355 | K118: A WING ,1203 NAMAN MIDTOWN,SENAPATI BAPAT MARG,PRABHADEVI, SENAPATI BAPAT MARG | O118: MUMBAI | P118: MAHARASHTRA | Q118: 400013 | R118: Dec 11, 2023 | S118: Perpetual | U118: Research Analyst | V118: No | W118: Research Analyst | X118: dolatcapital.com | Y118: corporate_domain | Z118: company_firm | AA118: 100 | AB118: 85 | AC118: A - Contact First | AD118: DOMAIN::dolatcapital.com | AF118: possible_duplicate_or_multi_category_entity | AG118: Manually verify website and contact details before outreach
A119: Estee Advisors Private Limited | B119: INH000019503 | C119: Preeti Joshi Mundeja | D119: 5th Flr Tower A PO5 01A PO5 01B, PO5 01C, GiftCity Complex, Block 51, Zone5, Road 5E, Gift City, Gandhinagar, Gandhinagar | E119: preeti.joshi@esteeadvisors.com | F119: 919646294265 | G119: 919646294265 | H119: GANDHINAGAR | I119: GUJARAT | J119: 382355 | K119: 5th Flr Tower A PO5 01A PO5 01B, PO5 01C, GiftCity Complex, Block 51, Zone5, Road 5E, Gift City, Gandhinagar, Gandhinagar | O119: GANDHINAGAR | P119: GUJARAT | Q119: 382355 | R119: Jan 31, 2025 | S119: Perpetual | U119: Research Analyst | V119: Yes | W119: Research Analyst | X119: esteeadvisors.com | Y119: corporate_domain | Z119: company_firm | AA119: 100 | AB119: 85 | AC119: A - Contact First | AD119: DOMAIN::esteeadvisors.com | AF119: possible_duplicate_or_multi_category_entity | AG119: Manually verify website and contact details before outreach
A120: GEOJIT INVESTMENTS LIMITED | B120: INH000019567 | C120: ANAND JAMES | D120: 7th Floor, 34 659 P,Civil Line Road, Padivattom Edapally,Ernakulam | E120: anand_james@geojit.com | F120: 919995800123 | G120: 919995800123 | H120: KOCHI | I120: KERALA | J120: 682024 | K120: 7th Floor, 34 659 P,Civil Line Road, Padivattom Edapally,Ernakulam | O120: KOCHI | P120: KERALA | Q120: 682024 | R120: Feb 05, 2025 | S120: Perpetual | U120: Research Analyst | V120: No | W120: Research Analyst | X120: geojit.com | Y120: corporate_domain | Z120: company_firm | AA120: 100 | AB120: 85 | AC120: A - Contact First | AD120: DOMAIN::geojit.com | AF120: possible_duplicate_or_multi_category_entity | AG120: Manually verify website and contact details before outreach
A121: Findoc Investmart Private Limited | B121: INH000024107 | C121: Yamank Kumar | D121: 1210/1211/1212/1213,1213A, Exchange Plaza, Near Mercury Hotel, opp. WTC Tower, Gift City, | E121: yamank.kumar@myfindoc.com | F121: 917982047064 | G121: 917982047064 | H121: GANDHINAGAR | I121: GUJARAT | J121: 382355 | R121: Dec 11, 2025 | S121: Perpetual | U121: Research Analyst | V121: Yes | W121: Research Analyst | X121: myfindoc.com | Y121: corporate_domain | Z121: company_firm | AA121: 100 | AB121: 85 | AC121: A - Contact First | AD121: DOMAIN::myfindoc.com | AF121: possible_duplicate_or_multi_category_entity | AG121: Manually verify website and contact details before outreach
A122: Finology Ventures Private Limited | B122: INH000024277 | C122: Antra Mahto | D122: 4th Floor, Avinash One, Opposite to Magneto Mall | E122: compliance@finology.in | F122: 009981691620 | G122: 009981691620 | H122: RAIPUR | I122: CHHATTISGARH | J122: 492001 | K122: 4th Floor, Avinash One, Opposite to Magneto Mall | O122: RAIPUR | P122: CHHATTISGARH | Q122: 492001 | R122: Dec 16, 2025 | S122: Perpetual | U122: Research Analyst | V122: Yes | W122: Research Analyst | X122: finology.in | Y122: corporate_domain | Z122: company_firm | AA122: 100 | AB122: 85 | AC122: A - Contact First | AD122: DOMAIN::finology.in | AF122: possible_duplicate_or_multi_category_entity | AG122: Manually verify website and contact details before outreach
A123: QICAP Management LLP | B123: INH000024763 | C123: Sandeep Ahuja | D123: Block-51 (301A-301B),WTCROAD 5E, ZONE-5, GIFTCITY,Dabhoda, Gandhi Nagar, Gandhinagar | E123: sandeep.ahuja@qi-cap.com | F123: 0919880252699 | G123: 0919880252699 | H123: GANDHINAGAR | I123: GUJARAT | J123: 382355 | R123: Jan 27, 2026 | S123: Perpetual | U123: Research Analyst | V123: Yes | W123: Research Analyst | X123: qi-cap.com | Y123: corporate_domain | Z123: company_firm | AA123: 100 | AB123: 85 | AC123: A - Contact First | AD123: DOMAIN::qi-cap.com | AF123: possible_duplicate_or_multi_category_entity | AG123: Manually verify website and contact details before outreach
A124: INVESTCUES CAPITAL INVESTMENT ADVISORS | B124: INH000024897 | C124: Abhishek Misra | D124: SAKET 59, Aishwarya Residency, Telibandha | E124: abhishek.misra@investcues.com | F124: 009867728579 | G124: 009867728579 | H124: RAIPUR | I124: CHHATTISGARH | J124: 492001 | R124: Feb 04, 2026 | S124: Perpetual | U124: Research Analyst | V124: Yes | W124: Research Analyst | X124: investcues.com | Y124: corporate_domain | Z124: company_firm | AA124: 100 | AB124: 85 | AC124: A - Contact First | AD124: DOMAIN::investcues.com | AF124: possible_duplicate_or_multi_category_entity | AG124: Manually verify website and contact details before outreach
A125: EQUITY99 | B125: INA000005358 | D125: A wing, 912 Dalamal Tower, 9th Floor,, Free Press Journal Marg, Nariman Point | E125: profittrack@rediff.com | F125: 07554204534 | G125: 07554204534 | H125: MUMBAI | I125: MAHARASHTRA | J125: 400021 | K125: 301, Sahyog Towers, E-8 Extension, Trilanga | O125: BHOPAL | P125: MADHYA PRADESH | Q125: 462023 | R125: Aug 16, 2016 | S125: Perpetual | U125: Investment Adviser | V125: No | W125: Investment Adviser | X125: rediff.com | Y125: corporate_domain | Z125: unclear | AA125: 85 | AB125: 85 | AC125: A - Contact First | AD125: DOMAIN::rediff.com | AF125: possible_brand_needs_verification | AG125: Manually verify website and contact details before outreach
A126: SMC GLOBAL SECURITIES LTD | B126: INH100001849 | D126: 11/6B, SHANTI CHAMBERS, MAIN PUSA ROAD | E126: ajay@smcindiaonline.com | F126: 1130111000 | G126: 1130111000 | H126: NEW DELHI | J126: 110005 | K126: 11/6B, Shanti Chambers, Main Pusa Road | O126: NEW DELHI | Q126: 110005 | R126: Oct 01, 2015 | S126: Perpetual | U126: Research Analyst | V126: No | W126: Research Analyst | X126: smcindiaonline.com | Y126: corporate_domain | Z126: company_firm | AA126: 70 | AB126: 85 | AC126: A - Contact First | AD126: DOMAIN::smcindiaonline.com | AF126: possible_duplicate_or_multi_category_entity | AG126: Manually verify website and contact details before outreach
A127: Estee Advisors Private Limited | B127: INA000016463 | C127: Keshav Kumar | D127: PO5-01A, PO5-01B, PO5-01C, 5th Floor, Tower A,, WTC, Block 51, Road 5E, Zone 5,Gift City | E127: ebo@esteeadvisors.com | H127: GANDHINAGAR | I127: GUJARAT | J127: 382355 | K127: PO5-01A, PO5-01B, PO5-01C, 5th Floor, Tower A, WTC, Block 51, Road 5E, Zone 5,Gift City | O127: GANDHINAGAR | P127: GUJARAT | Q127: 382355 | R127: Dec 17, 2021 | S127: Perpetual | U127: Investment Adviser | V127: Yes | W127: Investment Adviser | X127: esteeadvisors.com | Y127: corporate_domain | Z127: company_firm | AA127: 90 | AB127: 82 | AC127: A - Contact First | AD127: DOMAIN::esteeadvisors.com | AF127: possible_duplicate_or_multi_category_entity | AG127: Manually verify website and contact details before outreach
A128: VANSH CAPITAL PRIVATE LIMITED | B128: INP000009579 | C128: Shrawani Salunke | D128: 795, Bhandarkar Road, Mini Apartment, Near Metro Police Lab, Deccan Gymkhana | E128: vanshcapitalpmscompliance@gmail.com | F128: 0919075976318 | G128: 0919075976318 | H128: PUNE | I128: MAHARASHTRA | J128: 411004 | K128: 795, Bhandarkar Road, Mini Apartment, Near Metro Police Lab, Deccan Gymkhana | O128: PUNE | P128: MAHARASHTRA | Q128: 411004 | R128: Aug 05, 2025 | S128: Perpetual | U128: Portfolio Manager | V128: Yes | W128: Portfolio Manager | X128: gmail.com | Y128: free_personal_email | Z128: company_firm | AA128: 100 | AB128: 80 | AC128: A - Contact First | AD128: NAME::VANSH CAPITAL PRIVATE LIMITED | AF128: firm_with_free_email_needs_website_search | AG128: Manually verify website and contact details before outreach
A129: FIRST GLOBAL FINANCE PRIVATE LIMITED | B129: INH000004635 | C129: NEERAJ KHANNA | D129: Ratnam Square, First Floor, Plot No. 38 39,, Sector 19A, Vashi, Navi Mumbai | E129: neeraj.khanna@firstglobal.in | H129: NAVI MUMBAI | I129: MAHARASHTRA | J129: 400703 | K129: Ratnam Square, Plot No. 38/39, Sector 19A, Vashi | O129: NAVI MUMBAI | P129: MAHARASHTRA | Q129: 400703 | R129: Mar 10, 2017 | S129: Perpetual | U129: Research Analyst | V129: No | W129: Research Analyst | X129: firstglobal.in | Y129: corporate_domain | Z129: company_firm | AA129: 90 | AB129: 80 | AC129: A - Contact First | AD129: DOMAIN::firstglobal.in | AF129: possible_duplicate_or_multi_category_entity | AG129: Manually verify website and contact details before outreach
A130: Profitmart Securities Pvt Ltd | B130: INH000005582 | C130: Gaurav Kothari | D130: Unit No 213. Opal Square, Plot No C 1, Thane East | E130: gaurav.k@profitmart.in | H130: MUMBAI | I130: MAHARASHTRA | J130: 400604 | K130: Office No.3, 1st floor, B3, Cerebrum IT Park, Above DMART, Kalyani Nagar | O130: PUNE | P130: MAHARASHTRA | Q130: 411014 | R130: Jan 10, 2018 | S130: Perpetual | U130: Research Analyst | V130: No | W130: Research Analyst | X130: profitmart.in | Y130: corporate_domain | Z130: company_firm | AA130: 90 | AB130: 80 | AC130: A - Contact First | AD130: DOMAIN::profitmart.in | AF130: possible_duplicate_or_multi_category_entity | AG130: Manually verify website and contact details before outreach
A131: DSIJ Wealth Advisory Private Limited | B131: INH000006396 | C131: RAJESH PADODE | D131: 419-A ARUN CHAMBERS 4TH FLOOR, NEXT TO AIR CONDITION MARKET TARDEO | E131: rajeshp@dsij.in | H131: MUMBAI | I131: MAHARASHTRA | J131: 400034 | K131: OFFICE NO.-305, 3RD FLOOR, C-WING, TRADE CENTER, NORTH MAIN ROAD, NEAR AXIS BANK, OPPOSITE LANE NO 6, KOREGAON PARK | O131: PUNE | P131: MAHARASHTRA | Q131: 411001 | R131: Oct 05, 2018 | S131: Perpetual | U131: Research Analyst | V131: Yes | W131: Research Analyst | X131: dsij.in | Y131: corporate_domain | Z131: company_firm | AA131: 90 | AB131: 80 | AC131: A - Contact First | AD131: DOMAIN::dsij.in | AF131: possible_duplicate_or_multi_category_entity | AG131: Manually verify website and contact details before outreach
A132: JAINAM BROKING LIMITED | B132: INH000006448 | C132: SAURABH SHAH | D132: PLOT 42, JAINAM HOUSE,, NEW PASSPORT OFFICE ROAD, PIPLOD, | E132: compliance@jainam.in | H132: SURAT | I132: GUJARAT | J132: 395007 | K132: PLOT 42, JAINAM HOUSE, NEW PASSPORT OFFICE ROAD, PIPLOD, | O132: SURAT | P132: GUJARAT | Q132: 395007 | R132: Oct 19, 2018 | S132: Perpetual | U132: Research Analyst | V132: Yes | W132: Research Analyst | X132: jainam.in | Y132: corporate_domain | Z132: company_firm | AA132: 90 | AB132: 80 | AC132: A - Contact First | AD132: DOMAIN::jainam.in | AF132: possible_duplicate_or_multi_category_entity | AG132: Manually verify website and contact details before outreach
A133: GREEN PORTFOLIO PRIVATE LIMITED | B133: INH100008513 | C133: DIVAM SHARMA | D133: 7/7, Ground Floor, Ansari Road, Daryaganj | E133: divam@greenportfolio.co | H133: NEW DELHI | I133: NATIONAL CAPITAL TERRITORY OF DELHI | J133: 110002 | K133: 7/7, Ground Floor, Ansari Road, Daryaganj | O133: NEW DELHI | P133: NATIONAL CAPITAL TERRITORY OF DELHI | Q133: 110002 | R133: Jun 21, 2021 | S133: Perpetual | U133: Research Analyst | V133: Yes | W133: Research Analyst | X133: greenportfolio.co | Y133: corporate_domain | Z133: company_firm | AA133: 90 | AB133: 80 | AC133: A - Contact First | AD133: DOMAIN::greenportfolio.co | AF133: possible_duplicate_or_multi_category_entity | AG133: Manually verify website and contact details before outreach
A134: PrimeInvestor Financial Research Private Limited | B134: INH200008653 | C134: Vidya Bala | D134: 659, 1st Floor, Flat No 1, Alakananda, 4th Avenue,, D Sector, Anna Nagar Western Extn, | E134: vidyabala@primeinvestor.in | H134: CHENNAI | I134: TAMIL NADU | J134: 600101 | K134: 659, 1st Floor, Flat No 1, Alakananda, 4th Avenue, D Sector, Anna Nagar Western Extn, | O134: CHENNAI | P134: TAMIL NADU | Q134: 600101 | R134: Aug 19, 2021 | S134: Perpetual | U134: Research Analyst | V134: Yes | W134: Research Analyst | X134: primeinvestor.in | Y134: corporate_domain | Z134: company_firm | AA134: 90 | AB134: 80 | AC134: A - Contact First | AD134: DOMAIN::primeinvestor.in | AF134: possible_duplicate_or_multi_category_entity | AG134: Manually verify website and contact details before outreach
A135: FINWIZARD TECHNOLOGY PRIVATE LIMITED | B135: INH000010238 | C135: KRISHNA JAKKULA | D135: 2nd Floor 73 1 Indiqube, Sapphire St Marks Road, | E135: broking.compliance@fisdom.com | H135: BANGALORE | I135: KARNATAKA | J135: 560001 | K135: 17th Floor, VIOS Tower, Off Eastern Express Highway, NearAnikNagarBusDepot,SewriChemburRoad | O135: MUMBAI | P135: MAHARASHTRA | Q135: 400037 | R135: Oct 18, 2022 | S135: Perpetual | U135: Research Analyst | V135: No | W135: Research Analyst | X135: fisdom.com | Y135: corporate_domain | Z135: company_firm | AA135: 90 | AB135: 80 | AC135: A - Contact First | AD135: DOMAIN::fisdom.com | AF135: possible_duplicate_or_multi_category_entity | AG135: Manually verify website and contact details before outreach
A136: 360 ONE Distribution Services Limited | B136: INH000011431 | C136: Dinesh Tanwar | D136: 360 ONE Centre, Kamla City, Senapati Bapat Marg Lower Parel | E136: Dinesh.Tanwar@iiflw.com | H136: MUMBAI | I136: MAHARASHTRA | J136: 400013 | K136: 360 ONE Centre, Kamla City, Senapati Bapat Marg Lower Parel | O136: MUMBAI | P136: MAHARASHTRA | Q136: 400013 | R136: Feb 16, 2023 | S136: Perpetual | U136: Research Analyst | V136: No | W136: Research Analyst | X136: iiflw.com | Y136: corporate_domain | Z136: company_firm | AA136: 90 | AB136: 80 | AC136: A - Contact First | AD136: DOMAIN::iiflw.com | AF136: possible_duplicate_or_multi_category_entity | AG136: Manually verify website and contact details before outreach
A137: MOOL CAPITAL PRIVATE LIMITED | B137: INH000012449 | C137: Abhinav Nayar | D137: H N 4066 SECT B PKT 5/6 VASANT KUNJ, NEW DELHI, South Delhi | E137: abhinav@mool.one | H137: DELHI | I137: NATIONAL CAPITAL TERRITORY OF DELHI | J137: 110070 | K137: 5th Floor, 463, Woxa IT Park Tower, Rao Gajraj Singh Marg, Phase V, Udyog Vihar, Sector 19 | O137: GURGAON | P137: HARYANA | Q137: 122016 | R137: Jun 19, 2023 | S137: Perpetual | U137: Research Analyst | V137: Yes | W137: Research Analyst | X137: mool.one | Y137: corporate_domain | Z137: company_firm | AA137: 90 | AB137: 80 | AC137: A - Contact First | AD137: DOMAIN::mool.one | AF137: possible_duplicate_or_multi_category_entity | AG137: Manually verify website and contact details before outreach
A138: B N RATHI SECURITIES LIMITED | B138: INH000014687 | C138: CHETAN RATHI | D138: 6-3-652, IV FLOOR, KAUTILYA, AMRUTHA ESTATES | E138: crathi@bnrsecurities.com | H138: HYDERABAD | I138: TELANGANA | J138: 500082 | K138: 6-3-652, IV FLOOR, KAUTILYA, AMRUTHA ESTATES | O138: HYDERABAD | P138: TELANGANA | Q138: 500082 | R138: Feb 09, 2024 | S138: Perpetual | U138: Research Analyst | V138: No | W138: Research Analyst | X138: bnrsecurities.com | Y138: corporate_domain | Z138: company_firm | AA138: 90 | AB138: 80 | AC138: A - Contact First | AD138: DOMAIN::bnrsecurities.com | AF138: possible_duplicate_or_multi_category_entity | AG138: Manually verify website and contact details before outreach
A139: Dezerv Investments Private Limited | B139: INH000014915 | C139: Kavita Khatri | D139: Unit No. 301, Trade Centre, Bandra East | E139: legal-compliance@dezerv.in | H139: MUMBAI | I139: MAHARASHTRA | J139: 400051 | K139: Unit No. 301, Trade Centre, Bandra East | O139: MUMBAI | P139: MAHARASHTRA | Q139: 400051 | R139: Feb 09, 2024 | S139: Perpetual | U139: Research Analyst | V139: Yes | W139: Research Analyst | X139: dezerv.in | Y139: corporate_domain | Z139: company_firm | AA139: 90 | AB139: 80 | AC139: A - Contact First | AD139: DOMAIN::dezerv.in | AF139: possible_duplicate_or_multi_category_entity | AG139: Manually verify website and contact details before outreach
A140: WEALTH INDIA FINANCIAL SERVICES PVT LTD | B140: INH000015570 | C140: Srinivas Subudhi | D140: NO 38 & 39, UTTAM BUILDING,3RD FLOOR, WHITES ROAD,ROYAPETTAH,CHENNAI | E140: compliance@fundsindia.com | H140: CHENNAI | I140: TAMIL NADU | J140: 600014 | R140: Mar 19, 2024 | S140: Perpetual | U140: Research Analyst | V140: No | W140: Research Analyst | X140: fundsindia.com | Y140: corporate_domain | Z140: company_firm | AA140: 90 | AB140: 80 | AC140: A - Contact First | AD140: DOMAIN::fundsindia.com | AF140: possible_duplicate_or_multi_category_entity | AG140: Manually verify website and contact details before outreach
A141: Niveshaay Investment Advisors | B141: INH000017338 | C141: Vikram Sharma | D141: 508, 5th Floor, SNS Platina, Somesh Enclave, Near Reliance Mart, vesu | E141: vikram@niveshaay.com | H141: SURAT | I141: GUJARAT | J141: 395007 | K141: 508, 5th Floor, SNS Platina, Somesh Enclave, Near Reliance Mart, vesu | O141: SURAT | P141: GUJARAT | Q141: 395007 | R141: Jul 04, 2024 | S141: Perpetual | U141: Research Analyst | V141: No | W141: Research Analyst | X141: niveshaay.com | Y141: corporate_domain | Z141: company_firm | AA141: 90 | AB141: 80 | AC141: A - Contact First | AD141: DOMAIN::niveshaay.com | AF141: possible_duplicate_or_multi_category_entity | AG141: Manually verify website and contact details before outreach
A142: Prudent Corporate Advisory Services Limited | B142: INH000018115 | C142: Archana Kapadiya | D142: Prudent House Panjrapole Cross Road, Nr Polytechnic Ambawadi | E142: cmp@prudentcorporate.com | H142: AHMEDABAD | I142: GUJARAT | J142: 380015 | K142: Prudent House Panjrapole Cross Road, Nr Polytechnic Ambawadi | O142: AHMEDABAD | P142: GUJARAT | Q142: 380015 | R142: Aug 01, 2024 | S142: Perpetual | U142: Research Analyst | V142: No | W142: Research Analyst | X142: prudentcorporate.com | Y142: corporate_domain | Z142: company_firm | AA142: 90 | AB142: 80 | AC142: A - Contact First | AD142: DOMAIN::prudentcorporate.com | AF142: possible_duplicate_or_multi_category_entity | AG142: Manually verify website and contact details before outreach
A143: MANGAL KESHAV FINANCIAL SERVICES LLP | B143: INH000018319 | C143: GYAN PRAKASH | D143: 501, HERITAGE PLAZA, JP ROAD, OPP INDIAN OIL COLONY, ANDHERI WEST | E143: compliance@mangalkeshav.com | H143: MUMBAI | I143: MAHARASHTRA | J143: 400053 | K143: 501, HERITAGE PLAZA, JP ROAD, OPP INDIAN OIL COLONY, ANDHERI WEST | O143: MUMBAI | P143: MAHARASHTRA | Q143: 400053 | R143: Aug 07, 2024 | S143: Perpetual | U143: Research Analyst | V143: No | W143: Research Analyst | X143: mangalkeshav.com | Y143: corporate_domain | Z143: company_firm | AA143: 90 | AB143: 80 | AC143: A - Contact First | AD143: DOMAIN::mangalkeshav.com | AF143: possible_duplicate_or_multi_category_entity | AG143: Manually verify website and contact details before outreach
A144: Ayushi Chauksey Adviser Private Limited | B144: INA000019707 | C144: AYUSHI CHAUKSEY | D144: 801 SAHKARWADI SAHAKAR SOC BHD VIRWANI INDL ESTATE MULUND GOREGAON LK RD, GOREGAON EAST | E144: ayushichaukseyadviser2024@gmail.com | F144: 91007777024549 | G144: 91007777024549 | H144: MUMBAI | I144: MAHARASHTRA | J144: 400063 | K144: 801 SAHKARWADI SAHAKAR SOC BHD VIRWANI INDL ESTATE MULUND GOREGAON LK RD, GOREGAON EAST | O144: MUMBAI | P144: MAHARASHTRA | Q144: 400063 | R144: Dec 06, 2024 | S144: Perpetual | U144: Investment Adviser | V144: No | W144: Investment Adviser | X144: gmail.com | Y144: free_personal_email | Z144: company_firm | AA144: 100 | AB144: 77 | AC144: B - Good Lead | AD144: NAME::AYUSHI CHAUKSEY ADVISER PRIVATE LIMITED | AF144: firm_with_free_email_needs_website_search | AG144: Manually verify website and contact details before outreach
A145: INVESTGOAL CAPITAL ADVISORS PRIVATE LIMITED | B145: INA000021623 | C145: Kekin Nandu | D145: D-317, Dheeraj Valley Bldg. No. 2, Gokhale Road, Near, Saibaba Complex, Goregaon East, Mumbai | E145: kekinnandu25@gmail.com | F145: 00919820464524 | G145: 00919820464524 | H145: MUMBAI | I145: MAHARASHTRA | J145: 400063 | K145: D-317, Dheeraj Valley Bldg. No. 2, Gokhale Road, Near, Saibaba Complex, Goregaon East, Mumbai | O145: MUMBAI | P145: MAHARASHTRA | Q145: 400063 | R145: Dec 23, 2025 | S145: Perpetual | U145: Investment Adviser | V145: Yes | W145: Investment Adviser | X145: gmail.com | Y145: free_personal_email | Z145: company_firm | AA145: 100 | AB145: 77 | AC145: B - Good Lead | AD145: NAME::INVESTGOAL CAPITAL ADVISORS PRIVATE LIMITED | AF145: firm_with_free_email_needs_website_search | AG145: Manually verify website and contact details before outreach
A146: HENSEX SECURITIES PRIVATE LIMITED | B146: INH000012209 | C146: TAHIR HUSSAIN | D146: 7 BHAGAT KI KOTHI EXTENSION NH-65,, PALI ROAD, | E146: securities@hensex.com | H146: JODHPUR | I146: RAJASTHAN | J146: 342005 | K146: 7 BHAGAT KI KOTHI EXTENSION NH-65, PALI ROAD, | O146: JODHPUR | P146: RAJASTHAN | Q146: 342005 | R146: Apr 10, 2023 | S146: Perpetual | U146: Research Analyst | V146: Yes | W146: Research Analyst | X146: hensex.com | Y146: corporate_domain | Z146: company_firm | AA146: 90 | AB146: 75 | AC146: B - Good Lead | AD146: DOMAIN::hensex.com | AF146: possible_duplicate_or_multi_category_entity | AG146: Manually verify website and contact details before outreach
...

Sheet Excluded Leads
A1: Name | B1: Registration No. | C1: Contact Person | D1: Registered Office Address | E1: Registered Office Email-Id | F1: Registered Office Telephone | G1: Registered Office Fax | H1: Registered Office City | I1: Registered Office State | J1: Registered Office Pincode | K1: Correspondence Address | L1: Correspondence Email-Id | M1: Correspondence Telephone | N1: Correspondence Fax | O1: Correspondence City | P1: Correspondence State | Q1: Correspondence Pincode | R1: Validity From | S1: Validity To | T1: Country | U1: Lead Type | V1: Multi-Registered | W1: source_category | X1: email_domain | Y1: email_type | Z1: entity_type | AA1: data_completeness_score | AB1: lead_priority_score | AC1: lead_bucket | AD1: duplicate_group_key | AE1: exclusion_reason | AF1: review_reason | AG1: recommended_next_step
A2: Finwizard Technology Private Limited | B2: INP000008950 | C2: Krishna Jakkula | D2: IndiQube Sapphire,2nd Floor,No73,1,StMarks Road,Bangalore | E2: krishna@fisdom.com | F2: 910229820178911 | H2: BANGALORE | I2: KARNATAKA | J2: 560052 | K2: 17th Floor VIOS Tower Off Eastern Express Highway, Near Anik Nagar Bus Depot Sewri Chembur Road | O2: MUMBAI | P2: MAHARASHTRA | Q2: 400037 | R2: Sep 09, 2024 | S2: May 26, 2026 | U2: Portfolio Manager | V2: Yes | W2: Portfolio Manager | X2: fisdom.com | Y2: corporate_domain | Z2: company_firm | AA2: 100 | AB2: 100 | AC2: A - Contact First | AD2: DOMAIN::fisdom.com | AE2: inactive_or_expired_registration | AG2: Do not target in first campaign
A3: NARNOLIA FINANCIAL SERVICES LTD | B3: INP000006420 | R3: Mar 06, 2019 | S3: May 05, 2026 | U3: Portfolio Manager | V3: No | W3: Portfolio Manager | Y3: missing_email | Z3: company_firm | AA3: 25 | AB3: 5 | AC3: D - Ignore | AD3: NAME::NARNOLIA FINANCIAL SERVICES LTD | AE3: inactive_or_expired_registration; no_contact_channel | AG3: Do not target in first campaign
A4: AAKANKSHA GUPTA | B4: INH000013457 | C4: AAKANKSHA GUPTA | D4: D 116, Crystal Plaza, New Link Road, opposite Infiniti Mall, Andheri West | E4: aakanshauptti@gmail.com | H4: MUMBAI | I4: MAHARASHTRA | J4: 400058 | K4: D 116, Crystal Plaza, New Link Road, opposite Infiniti Mall, Andheri West | O4: MUMBAI | P4: MAHARASHTRA | Q4: 400058 | R4: Oct 16, 2023 | S4: Perpetual | U4: Research Analyst | V4: No | W4: Research Analyst | X4: gmail.com | Y4: free_personal_email | Z4: individual_practitioner | AA4: 90 | AB4: 0 | AC4: D - Ignore | AD4: NAME::AAKANKSHA GUPTA | AE4: individual_free_email_low_priority | AG4: Do not target in first campaign
A5: ABHIJIT DHAR | B5: INH000028228 | C5: ABHIJIT DHAR | D5: PLOT-DF-157,PRE-15-0352 AA-ID,NEW, TOWN,KOLKATA, NORTH 24 PARGANAS | E5: ca.abhijitdhar1@gmail.com | F5: 919748176461 | G5: 919748176461 | H5: KOLKATA | I5: WEST BENGAL | J5: 700156 | K5: PLOT-DF-157,PRE-15-0352 AA-ID,NEW, TOWN,KOLKATA, NORTH 24 PARGANAS | O5: KOLKATA | P5: WEST BENGAL | Q5: 700156 | R5: Jun 16, 2026 | S5: Perpetual | U5: Research Analyst | V5: No | W5: Research Analyst | X5: gmail.com | Y5: free_personal_email | Z5: individual_practitioner | AA5: 100 | AB5: 10 | AC5: D - Ignore | AD5: NAME::ABHIJIT DHAR | AE5: individual_free_email_low_priority | AG5: Do not target in first campaign
A6: ABHIJIT PANDURANG PATIL | B6: INH000021304 | C6: ABHIJIT PATIL | D6: Office No B4 5 Omkar Plaza, Rajaram Road Bagal Chowk Kolhapur | E6: abhipatilca@hotmail.com | F6: 919970101402 | H6: KOLHAPUR | I6: MAHARASHTRA | J6: 416001 | K6: Office No B4 5 Omkar Plaza, Rajaram Road Bagal Chowk Kolhapur | O6: KOLHAPUR | P6: MAHARASHTRA | Q6: 416001 | R6: Jun 24, 2025 | S6: Perpetual | U6: Research Analyst | V6: No | W6: Research Analyst | X6: hotmail.com | Y6: free_personal_email | Z6: individual_practitioner | AA6: 100 | AB6: 5 | AC6: D - Ignore | AD6: NAME::ABHIJIT PANDURANG PATIL | AE6: individual_free_email_low_priority | AG6: Do not target in first campaign
A7: ABHISHEK NANDAN | B7: INH000009463 | C7: Abhishek Nandan | D7: 132 Gayatri Nagar -A, Maharani Farm, Durgapura | E7: analystabhishek7@gmail.com | F7: 919503018865 | H7: JAIPUR | I7: RAJASTHAN | J7: 302018 | K7: 132 Gayatri Nagar -A, Maharani Farm, Durgapura | O7: JAIPUR | P7: RAJASTHAN | Q7: 302018 | R7: May 09, 2022 | S7: Perpetual | U7: Research Analyst | V7: No | W7: Research Analyst | X7: gmail.com | Y7: free_personal_email | Z7: individual_practitioner | AA7: 100 | AB7: 5 | AC7: D - Ignore | AD7: NAME::ABHISHEK NANDAN | AE7: individual_free_email_low_priority | AG7: Do not target in first campaign
A8: ADARSH NIMBORKAR | B8: INA000019789 | C8: ADARSH NIMBORKAR | D8: 49, PRASAD NAGAR, JAITALA ROAD, NAGPUR CITY, MAHARASHTRA | E8: ADARSHMNIMBORKAR99@GMAIL.COM | F8: 919130997271 | H8: NAGPUR | I8: MAHARASHTRA | J8: 440022 | K8: 49, PRASAD NAGAR, JAITALA ROAD, NAGPUR CITY, MAHARASHTRA | O8: NAGPUR | P8: MAHARASHTRA | Q8: 440022 | R8: Jan 06, 2025 | S8: Perpetual | U8: Investment Adviser | V8: No | W8: Investment Adviser | X8: gmail.com | Y8: free_personal_email | Z8: individual_practitioner | AA8: 100 | AB8: 12 | AC8: D - Ignore | AD8: NAME::ADARSH NIMBORKAR | AE8: individual_free_email_low_priority | AG8: Do not target in first campaign
A9: ADITYA BATTU | B9: INH000027946 | C9: ADITYA BATTU | D9: H No- 67, Pleasant Ville, Krcr Harithavanam Colony,, Bachupally, Hyderabad, Medchal Malkajgiri | E9: adityabattu24@gmail.com | F9: 00008861161132 | G9: 00008861161132 | H9: HYDERABAD | I9: TELANGANA | J9: 500090 | K9: H No- 67, Pleasant Ville, Krcr Harithavanam Colony, Bachupally, Hyderabad, Medchal Malkajgiri | O9: HYDERABAD | P9: TELANGANA | Q9: 500090 | R9: Jun 08, 2026 | S9: Perpetual | U9: Research Analyst | V9: No | W9: Research Analyst | X9: gmail.com | Y9: free_personal_email | Z9: individual_practitioner | AA9: 100 | AB9: 10 | AC9: D - Ignore | AD9: NAME::ADITYA BATTU | AE9: individual_free_email_low_priority | AG9: Do not target in first campaign
A10: ADITYA PRADIP NAGORI | B10: INH000027131 | C10: ADITYA NAGORI | D10: Plot No. 350, Ward 5A, Near Vinayak Hospital, Adipur | E10: championtradersindia@gmail.com | F10: 00000000000000 | G10: 00000000000000 | H10: GANDHIDHAM | I10: GUJARAT | J10: 370205 | R10: May 15, 2026 | S10: Perpetual | U10: Research Analyst | V10: No | W10: Research Analyst | X10: gmail.com | Y10: free_personal_email | Z10: individual_practitioner | AA10: 100 | AB10: 5 | AC10: D - Ignore | AD10: NAME::ADITYA PRADIP NAGORI | AE10: individual_free_email_low_priority | AG10: Do not target in first campaign
A11: ADITYA SAKHARAM JADHAV | B11: INA000022729 | C11: ADITYA JADHAV | D11: 43 Golden Bamboo CHS,, Orchids Complex, Majiwade | E11: ADITYAJADHAV@GMAIL.COM | F11: 000919967013381 | G11: 000919967013381 | H11: THANE | I11: MAHARASHTRA | J11: 400601 | R11: Jun 04, 2026 | S11: Perpetual | U11: Investment Adviser | V11: No | W11: Investment Adviser | X11: gmail.com | Y11: free_personal_email | Z11: individual_practitioner | AA11: 100 | AB11: 17 | AC11: D - Ignore | AD11: NAME::ADITYA SAKHARAM JADHAV | AE11: individual_free_email_low_priority | AG11: Do not target in first campaign
A12: ADITYA SHIVHARE | B12: INH000013873 | C12: ADITYA SHIVHARE | D12: H No. 175, Berasiya Road, , Goya Colony Karond, Huzur | E12: ADITYASHIVHARE73@GMAIL.COM | H12: BHOPAL | I12: MADHYA PRADESH | J12: 462038 | K12: H No. 175, Berasiya Road, , Goya Colony Karond, Huzur | O12: BHOPAL | P12: MADHYA PRADESH | Q12: 462038 | R12: Dec 01, 2023 | S12: Perpetual | U12: Research Analyst | V12: No | W12: Research Analyst | X12: gmail.com | Y12: free_personal_email | Z12: individual_practitioner | AA12: 90 | AB12: 0 | AC12: D - Ignore | AD12: NAME::ADITYA SHIVHARE | AE12: individual_free_email_low_priority | AG12: Do not target in first campaign
A13: ADITYA SINGH | B13: INH000025364 | C13: ADITYA SINGH | D13: HOUSE NO. 914 AWAS VIKAS COLONY, MAHADEV JHARKHANDI, KHORABAR URF SOOBABAZAR, KUNRAGHAT | E13: ADITYASINGH2000007@GMAIL.COM | F13: 00000000000000 | G13: 00000000000000 | H13: GORAKHPUR | I13: UTTAR PRADESH | J13: 273008 | K13: HOUSE NO. 914 AWAS VIKAS COLONY, MAHADEV JHARKHANDI, KHORABAR URF SOOBABAZAR, KUNRAGHAT | O13: GORAKHPUR | P13: UTTAR PRADESH | Q13: 273008 | R13: Mar 11, 2026 | S13: Perpetual | U13: Research Analyst | V13: No | W13: Research Analyst | X13: gmail.com | Y13: free_personal_email | Z13: individual_practitioner | AA13: 100 | AB13: 5 | AC13: D - Ignore | AD13: NAME::ADITYA SINGH | AE13: individual_free_email_low_priority | AG13: Do not target in first campaign
A14: AH FLOURISH TECHS | B14: INH000024356 | C14: HAREESH Mariyappa | D14: NO 968, K NO. 101/269/91, JANATHA, COLONY, BOMMASANDRA, JIGANI HOBLI, | E14: ahflourishtechs@gmail.com | F14: 00000000000000 | G14: 00000000000000 | H14: BANGALORE | I14: KARNATAKA | J14: 560099 | K14: NO 968, K NO. 101/269/91, JANATHA, COLONY, BOMMASANDRA, JIGANI HOBLI, | O14: BANGALORE | P14: KARNATAKA | Q14: 560099 | R14: Dec 19, 2025 | S14: Perpetual | U14: Research Analyst | V14: No | W14: Research Analyst | X14: gmail.com | Y14: free_personal_email | Z14: individual_practitioner | AA14: 100 | AB14: 10 | AC14: D - Ignore | AD14: NAME::AH FLOURISH TECHS | AE14: individual_free_email_low_priority | AG14: Do not target in first campaign
A15: AJAY KURIAN VARGHESE | B15: INH000027292 | C15: AJAY VARGHESE | D15: TC13/1561, Ranjini,, Kumarapuram, MC PO | E15: ajayvarghese1177@gmail.com | F15: 0007012983639 | G15: 0007012983639 | H15: THIRUVANANTHAPURAM | I15: KERALA | J15: 695011 | R15: May 19, 2026 | S15: Perpetual | U15: Research Analyst | V15: No | W15: Research Analyst | X15: gmail.com | Y15: free_personal_email | Z15: individual_practitioner | AA15: 100 | AB15: 5 | AC15: D - Ignore | AD15: NAME::AJAY KURIAN VARGHESE | AE15: individual_free_email_low_priority | AG15: Do not target in first campaign
A16: AJAY SINGH | B16: INH000023454 | C16: AJAY SINGH | D16: RZ-97/A, Gali No 12, B-Block, Kailash Puri, Palam Village | E16: ajaysingh.stock@gmail.com | F16: 917551199974 | H16: DELHI | I16: NATIONAL CAPITAL TERRITORY OF DELHI | J16: 110045 | R16: Sep 25, 2025 | S16: Perpetual | U16: Research Analyst | V16: No | W16: Research Analyst | X16: gmail.com | Y16: free_personal_email | Z16: individual_practitioner | AA16: 100 | AB16: 10 | AC16: D - Ignore | AD16: NAME::AJAY SINGH | AE16: individual_free_email_low_priority | AG16: Do not target in first campaign
A17: AJIT ROONGTA | B17: INA000002611 | C17: AJIT ROONGTA | D17: 31, GOPAL BHAVAN, 2ND FLOOR,, 199 PRINCESS STREET, | E17: ajitroongta@yahoo.com | F17: 2222035039 | G17: 2222035039 | H17: MUMBAI | I17: MAHARASHTRA | J17: 400002 | K17: 31, Gopal Bhavan, 2nd Floor, 199 Princess Street, | O17: MUMBAI | P17: MAHARASHTRA | Q17: 400002 | R17: Jan 29, 2015 | S17: Perpetual | U17: Investment Adviser | V17: No | W17: Investment Adviser | X17: yahoo.com | Y17: free_personal_email | Z17: individual_practitioner | AA17: 100 | AB17: 17 | AC17: D - Ignore | AD17: NAME::AJIT ROONGTA | AE17: individual_free_email_low_priority | AG17: Do not target in first campaign
A18: AKASH AGARWAL | B18: INH000012935 | C18: AKASH AGARWAL | D18: H - 87 Sector 63, Gautam Buddha Nagar | E18: akashca355@gmail.com | F18: 919717763937 | H18: NOIDA | I18: UTTAR PRADESH | J18: 201301 | K18: F-21/16, Krishna Nagar, East Delhi | O18: DELHI | P18: NATIONAL CAPITAL TERRITORY OF DELHI | Q18: 110051 | R18: Sep 05, 2023 | S18: Perpetual | U18: Research Analyst | V18: No | W18: Research Analyst | X18: gmail.com | Y18: free_personal_email | Z18: individual_practitioner | AA18: 100 | AB18: 10 | AC18: D - Ignore | AD18: NAME::AKASH AGARWAL | AE18: individual_free_email_low_priority | AG18: Do not target in first campaign
A19: AKASH GARG | B19: INH000027450 | C19: AKASH GARG | D19: G-401, Casa Greenville, Lodha Upper Thane Mankoli | E19: garg.akash.ga@gmail.com | F19: 0009217021552 | G19: 0009217021552 | H19: THANE | I19: MAHARASHTRA | J19: 421311 | R19: May 21, 2026 | S19: Perpetual | U19: Research Analyst | V19: No | W19: Research Analyst | X19: gmail.com | Y19: free_personal_email | Z19: individual_practitioner | AA19: 100 | AB19: 10 | AC19: D - Ignore | AD19: NAME::AKASH GARG | AE19: individual_free_email_low_priority | AG19: Do not target in first campaign
A20: AKHILESH GUPTA | B20: INH000013314 | C20: AKHILESH GUPTA | D20: OFFICE NO 303, SHREENATHJI AVENUE, 158, KIBE COMPOUND | E20: Akhileshguptaresearch@gmail.com | H20: INDORE | I20: MADHYA PRADESH | J20: 452001 | K20: OFFICE NO 303, SHREENATHJI AVENUE, 158, KIBE COMPOUND | O20: INDORE | P20: MADHYA PRADESH | Q20: 452001 | R20: Oct 10, 2023 | S20: Perpetual | U20: Research Analyst | V20: No | W20: Research Analyst | X20: gmail.com | Y20: free_personal_email | Z20: individual_practitioner | AA20: 90 | AB20: 0 | AC20: D - Ignore | AD20: NAME::AKHILESH GUPTA | AE20: individual_free_email_low_priority | AG20: Do not target in first campaign
A21: AKHILESH V GOKARAJU | B21: INA000020299 | C21: AKHILESH V GOKARAJU | D21: House No.7-1-644/48 Plot No. 48,, Sundarnagar, Erragadda, | E21: akhileshvarma@yahoo.com | F21: 919866677897 | H21: HYDERABAD | I21: TELANGANA | J21: 500038 | K21: House No.7-1-644/48 Plot No. 48, Sundarnagar, Erragadda, | O21: HYDERABAD | P21: TELANGANA | Q21: 500038 | R21: Jun 04, 2025 | S21: Perpetual | U21: Investment Adviser | V21: No | W21: Investment Adviser | X21: yahoo.com | Y21: free_personal_email | Z21: individual_practitioner | AA21: 100 | AB21: 17 | AC21: D - Ignore | AD21: NAME::AKHILESH V GOKARAJU | AE21: individual_free_email_low_priority | AG21: Do not target in first campaign
A22: AMAM ARUN | B22: INH000028422 | C22: AMAM ARUN | D22: 1401 Alpine Viva, A Block, Danube, Seegehahalli, Bangalore | E22: amam.arun1@gmail.com | F22: 00007045343709 | G22: 00007045343709 | H22: BANGALORE | I22: KARNATAKA | J22: 560067 | K22: 1401 Alpine Viva, A Block, Danube, Seegehahalli, Bangalore | O22: BANGALORE | P22: KARNATAKA | Q22: 560067 | R22: Jun 22, 2026 | S22: Perpetual | U22: Research Analyst | V22: No | W22: Research Analyst | X22: gmail.com | Y22: free_personal_email | Z22: individual_practitioner | AA22: 100 | AB22: 10 | AC22: D - Ignore | AD22: NAME::AMAM ARUN | AE22: individual_free_email_low_priority | AG22: Do not target in first campaign
A23: AMAR KUMAR THAKUR | B23: INH000026707 | C23: AMAR THAKUR | D23: Rania Udyan Pally, 30FT Auto Stand, Sonarpur, Bansdroni, Boral S.O, South 24 Parganas | E23: amarfinqor@gmail.com | F23: 00000000000000 | G23: 00000000000000 | H23: KOLKATA | I23: WEST BENGAL | J23: 700154 | R23: May 05, 2026 | S23: Perpetual | U23: Research Analyst | V23: No | W23: Research Analyst | X23: gmail.com | Y23: free_personal_email | Z23: individual_practitioner | AA23: 100 | AB23: 10 | AC23: D - Ignore | AD23: NAME::AMAR KUMAR THAKUR | AE23: individual_free_email_low_priority | AG23: Do not target in first campaign
A24: AMARTYA MANI | B24: INH000027900 | C24: Amartya Mani | D24: CHOUDHARY BHAWAN STREET NO 10, GOURAKSHANI SASARAM | E24: amartyadesire@gmail.com | F24: 06184358447 | G24: 06184358447 | H24: GAYA | I24: BIHAR | J24: 821115 | K24: CHOUDHARY BHAWAN STREET NO 10, GOURAKSHANI SASARAM | O24: GAYA | P24: BIHAR | Q24: 821115 | R24: Jun 08, 2026 | S24: Perpetual | U24: Research Analyst | V24: No | W24: Research Analyst | X24: gmail.com | Y24: free_personal_email | Z24: individual_practitioner | AA24: 100 | AB24: 5 | AC24: D - Ignore | AD24: NAME::AMARTYA MANI | AE24: individual_free_email_low_priority | AG24: Do not target in first campaign
A25: AMBAREESH BALIGA | B25: INH000001139 | C25: AMBAREESH BALIGA | D25: 901 ANANT, PLOT 88(2),, SECTOR 29, VASHI, | E25: ambareeshbaliga@yahoo.com | F25: 2265116161 | G25: 2265116161 | H25: NAVI MUMBAI | I25: MAHARASHTRA | J25: 400703 | K25: 901 Anant, Plot 88(2), Sector 29, Vashi, | O25: NAVI MUMBAI | P25: MAHARASHTRA | Q25: 400703 | R25: Jul 22, 2015 | S25: Perpetual | U25: Research Analyst | V25: No | W25: Research Analyst | X25: yahoo.com | Y25: free_personal_email | Z25: individual_practitioner | AA25: 100 | AB25: 10 | AC25: D - Ignore | AD25: NAME::AMBAREESH BALIGA | AE25: individual_free_email_low_priority | AG25: Do not target in first campaign
A26: AMIT BHATTACHARJEE | B26: INH000019886 | C26: AMIT BHATTACHARJEE | D26: 3rd Floor, FL 11, 64, 57 Khudiram Bose Sarani, PS Ultadanga | E26: algobreaths@gmail.com | F26: 919051195088 | H26: KOLKATA | I26: WEST BENGAL | J26: 700037 | K26: 3rd Floor, FL 11, 64, 57 Khudiram Bose Sarani, PS Ultadanga | O26: KOLKATA | P26: WEST BENGAL | Q26: 700037 | R26: Feb 20, 2025 | S26: Perpetual | U26: Research Analyst | V26: No | W26: Research Analyst | X26: gmail.com | Y26: free_personal_email | Z26: individual_practitioner | AA26: 100 | AB26: 10 | AC26: D - Ignore | AD26: NAME::AMIT BHATTACHARJEE | AE26: individual_free_email_low_priority | AG26: Do not target in first campaign
A27: AMIT GORISHANKAR DHANUKA | B27: INA000021298 | C27: AMIT DHANUKA | D27: G 601 CASA VYOMA , BEHIND AHMEDABAD ONE MALL VASTRAPUR | E27: ca.dhanukaamit@gmail.com | F27: 00919924675580 | G27: 00919924675580 | H27: AHMEDABAD | I27: GUJARAT | J27: 380015 | K27: G 601 CASA VYOMA , BEHIND AHMEDABAD ONE MALL VASTRAPUR | O27: AHMEDABAD | P27: GUJARAT | Q27: 380015 | R27: Nov 04, 2025 | S27: Perpetual | U27: Investment Adviser | V27: No | W27: Investment Adviser | X27: gmail.com | Y27: free_personal_email | Z27: individual_practitioner | AA27: 100 | AB27: 17 | AC27: D - Ignore | AD27: NAME::AMIT GORISHANKAR DHANUKA | AE27: individual_free_email_low_priority | AG27: Do not target in first campaign
A28: AMIT GOVIND GOENKA | B28: INH000017930 | C28: AMIT GOENKA | D28: Plot No. 19 Ghat Road Behind Hotel Century, Chandak Lay Out Mahatma Fule Bazar Nagpur | E28: amit.fore@gmail.com | H28: NAGPUR | I28: MAHARASHTRA | J28: 440018 | K28: Plot No. 19 Ghat Road Behind Hotel Century, Chandak Lay Out Mahatma Fule Bazar Nagpur | O28: NAGPUR | P28: MAHARASHTRA | Q28: 440018 | R28: Jul 25, 2024 | S28: Perpetual | U28: Research Analyst | V28: No | W28: Research Analyst | X28: gmail.com | Y28: free_personal_email | Z28: individual_practitioner | AA28: 90 | AB28: 0 | AC28: D - Ignore | AD28: NAME::AMIT GOVIND GOENKA | AE28: individual_free_email_low_priority | AG28: Do not target in first campaign
A29: AMIT GURUH SACHDEVA | B29: INH100005190 | C29: AMIT SACHDEVA | D29: 567/10, ANAND NAGAR, JAIL ROAD | E29: amitguruhsachdeva@yahoo.com | H29: LUCKNOW | I29: UTTAR PRADESH | J29: 226005 | K29: 567/10, ANAND NAGAR, JAIL ROAD | O29: LUCKNOW | P29: UTTAR PRADESH | Q29: 226005 | R29: Sep 07, 2017 | S29: Perpetual | U29: Research Analyst | V29: No | W29: Research Analyst | X29: yahoo.com | Y29: free_personal_email | Z29: individual_practitioner | AA29: 90 | AB29: 0 | AC29: D - Ignore | AD29: NAME::AMIT GURUH SACHDEVA | AE29: individual_free_email_low_priority | AG29: Do not target in first campaign
A30: AMIT KUKREJA | B30: INA100000051 | C30: AMIT KUKREJA | D30: DW-260, Nirvana Country, Sector-50 | E30: akukreja@gmail.com | F30: 91009810353040 | G30: 91009810353040 | H30: GURGAON | I30: HARYANA | J30: 122018 | K30: 405, Tower-C, Nirvana Courtyard, Sector-50, | O30: GURGAON | P30: HARYANA | Q30: 122018 | R30: Aug 02, 2013 | S30: Perpetual | U30: Investment Adviser | V30: No | W30: Investment Adviser | X30: gmail.com | Y30: free_personal_email | Z30: individual_practitioner | AA30: 100 | AB30: 17 | AC30: D - Ignore | AD30: NAME::AMIT KUKREJA | AE30: individual_free_email_low_priority | AG30: Do not target in first campaign
A31: AMIT NITIN SHAH | B31: INH000011413 | C31: AMIT SHAH | D31: B-801 , Safal Seventy , Iscon Cross Road, Ambli Road , Nr ISRO Colony | E31: amitshah2808@gmail.com | H31: AHMEDABAD | I31: GUJARAT | J31: 380054 | K31: B-801 , Safal Seventy , Iscon Cross Road, Ambli Road , Nr ISRO Colony | O31: AHMEDABAD | P31: GUJARAT | Q31: 380054 | R31: Feb 16, 2023 | S31: Perpetual | U31: Research Analyst | V31: No | W31: Research Analyst | X31: gmail.com | Y31: free_personal_email | Z31: individual_practitioner | AA31: 90 | AB31: 0 | AC31: D - Ignore | AD31: NAME::AMIT NITIN SHAH | AE31: individual_free_email_low_priority | AG31: Do not target in first campaign
A32: AMIT PASTAGIA | B32: INH000013253 | C32: AMIT PASTAGIA | D32: 39 Ankur society, Adajan Road | E32: AMT.PST@GMAIL.COM | H32: SURAT | I32: GUJARAT | J32: 395009 | K32: 39 Ankur society, Adajan Road | O32: SURAT | P32: GUJARAT | Q32: 395009 | R32: Oct 09, 2023 | S32: Perpetual | U32: Research Analyst | V32: No | W32: Research Analyst | X32: gmail.com | Y32: free_personal_email | Z32: individual_practitioner | AA32: 90 | AB32: 0 | AC32: D - Ignore | AD32: NAME::AMIT PASTAGIA | AE32: individual_free_email_low_priority | AG32: Do not target in first campaign
A33: AMIT ROY | B33: INH000026211 | C33: AMIT ROY | D33: SILPUKHURI, MITONG NAKATANI | E33: amitroy6618@gmail.com | F33: 00000000000000 | G33: 00000000000000 | H33: DIBRUGARH | I33: ASSAM | J33: 785664 | R33: Apr 16, 2026 | S33: Perpetual | U33: Research Analyst | V33: No | W33: Research Analyst | X33: gmail.com | Y33: free_personal_email | Z33: individual_practitioner | AA33: 100 | AB33: 5 | AC33: D - Ignore | AD33: NAME::AMIT ROY | AE33: individual_free_email_low_priority | AG33: Do not target in first campaign
A34: AMIT SETH | B34: INH300009172 | C34: AMIT SETH | D34: 116/1/1 MAHATMA GANDHI ROAD, FIRST FLOOR | E34: amitseth.research@gmail.com | F34: 918777436040 | G34: 918777436040 | H34: KOLKATA | I34: WEST BENGAL | J34: 700007 | R34: Mar 08, 2022 | S34: Perpetual | U34: Research Analyst | V34: No | W34: Research Analyst | X34: gmail.com | Y34: free_personal_email | Z34: individual_practitioner | AA34: 100 | AB34: 10 | AC34: D - Ignore | AD34: NAME::AMIT SETH | AE34: individual_free_email_low_priority | AG34: Do not target in first campaign
A35: ANAND DINESHBHAI NANAVATI | B35: INH000021289 | C35: ANAND NANAVATI | D35: 321, Vishwamohini Complex, Subhanpura, Vadodara | E35: to_anand@yahoo.com | F35: 919825160807 | H35: VADODARA | I35: GUJARAT | J35: 390023 | K35: 321, Vishwamohini Complex, Subhanpura, Vadodara | O35: VADODARA | P35: GUJARAT | Q35: 390023 | R35: Jun 24, 2025 | S35: Perpetual | U35: Research Analyst | V35: No | W35: Research Analyst | X35: yahoo.com | Y35: free_personal_email | Z35: individual_practitioner | AA35: 100 | AB35: 5 | AC35: D - Ignore | AD35: NAME::ANAND DINESHBHAI NANAVATI | AE35: individual_free_email_low_priority | AG35: Do not target in first campaign
A36: ANAND KUMAR TANTIA | B36: INH100003381 | D36: TANTIA HOUSE, NEAR SUBHASH CHOWK, KAYAMKHANI MOHALLA | E36: at.tantia@gmail.com | F36: 9549901515 | G36: 9549901515 | I36: RAJASTHAN | J36: 335513 | R36: Aug 30, 2016 | S36: Perpetual | U36: Research Analyst | V36: No | W36: Research Analyst | X36: gmail.com | Y36: free_personal_email | Z36: individual_practitioner | AA36: 70 | AB36: 0 | AC36: D - Ignore | AD36: NAME::ANAND KUMAR TANTIA | AE36: individual_free_email_low_priority | AG36: Do not target in first campaign
A37: ANAND SINGH ADHIKARI | B37: INH000022048 | C37: ANAND ADHIKARI | D37: 1003 B1 Parkwoods Ghodbunder road, Thane | E37: anandadhikari@gmail.com | F37: 009833080134 | G37: 009833080134 | H37: THANE | I37: MAHARASHTRA | J37: 400615 | K37: 1003 B1 Parkwoods Ghodbunder road, Thane | O37: THANE | P37: MAHARASHTRA | Q37: 400615 | R37: Jul 24, 2025 | S37: Perpetual | U37: Research Analyst | V37: No | W37: Research Analyst | X37: gmail.com | Y37: free_personal_email | Z37: individual_practitioner | AA37: 100 | AB37: 10 | AC37: D - Ignore | AD37: NAME::ANAND SINGH ADHIKARI | AE37: individual_free_email_low_priority | AG37: Do not target in first campaign
A38: ANCY JACOB | B38: INH000020235 | C38: ANCY JACOB | D38: MUTTATHU, KURISHUMMOOD, , THENGANA | E38: ancy.p.jacob@gmail.com | F38: 918714821606 | H38: Kottayam | I38: KERALA | J38: 686104 | K38: MUTTATHU, KURISHUMMOOD, , THENGANA | O38: Kottayam | P38: KERALA | Q38: 686104 | R38: Apr 09, 2025 | S38: Perpetual | U38: Research Analyst | V38: No | W38: Research Analyst | X38: gmail.com | Y38: free_personal_email | Z38: individual_practitioner | AA38: 100 | AB38: 5 | AC38: D - Ignore | AD38: NAME::ANCY JACOB | AE38: individual_free_email_low_priority | AG38: Do not target in first campaign
A39: ANIL KUMAR RAI | B39: INH000017596 | C39: Anil Rai | D39: 245 C, Bakshi Kala, Nagvasuki, Prayagraj | E39: anilrai.fca@gmail.com | F39: 919667611275 | H39: ALLAHABAD | I39: UTTAR PRADESH | J39: 211006 | K39: 245 C, Bakshi Kala, Nagvasuki, Prayagraj | O39: ALLAHABAD | P39: UTTAR PRADESH | Q39: 211006 | R39: Jul 15, 2024 | S39: Perpetual | U39: Research Analyst | V39: No | W39: Research Analyst | X39: gmail.com | Y39: free_personal_email | Z39: individual_practitioner | AA39: 100 | AB39: 5 | AC39: D - Ignore | AD39: NAME::ANIL KUMAR RAI | AE39: individual_free_email_low_priority | AG39: Do not target in first campaign
A40: ANKIT AGARWAL | B40: INH300008872 | C40: ANKIT AGARWAL | D40: 24/25 Bhairab Dutta Lane, Salkia, Howrah MCorp | E40: aankit_agarwal98@yahoo.com | H40: HOWRAH | I40: WEST BENGAL | J40: 711106 | K40: 24/25 Bhairab Dutta Lane, Salkia, Howrah MCorp | O40: HOWRAH | P40: WEST BENGAL | Q40: 711106 | R40: Nov 23, 2021 | S40: Perpetual | U40: Research Analyst | V40: No | W40: Research Analyst | X40: yahoo.com | Y40: free_personal_email | Z40: individual_practitioner | AA40: 90 | AB40: 0 | AC40: D - Ignore | AD40: NAME::ANKIT AGARWAL | AE40: individual_free_email_low_priority | AG40: Do not target in first campaign
A41: ANKIT RAJ | B41: INH000012810 | C41: ANKIT RAJ | D41: Room No. 305, Capitol Tower, Block B , Fraser Road | E41: caankitraj09@gmail.com | H41: PATNA | I41: BIHAR | J41: 800001 | K41: Room No. 305, Capitol Tower, Block B , Fraser Road | O41: PATNA | P41: BIHAR | Q41: 800001 | R41: Aug 31, 2023 | S41: Perpetual | U41: Research Analyst | V41: No | W41: Research Analyst | X41: gmail.com | Y41: free_personal_email | Z41: individual_practitioner | AA41: 90 | AB41: 0 | AC41: D - Ignore | AD41: NAME::ANKIT RAJ | AE41: individual_free_email_low_priority | AG41: Do not target in first campaign
A42: ANKITA MUKHERJEE | B42: INH000020721 | C42: ANKITA MUKHERJEE | D42: 4 82, SETH BAGAN ROAD, DUMDUM, Ghugudanga | E42: ankitamukherjeesebi.ra@gmail.com | F42: 917980561156 | H42: KOLKATA | I42: WEST BENGAL | J42: 700030 | K42: 4 82, SETH BAGAN ROAD, DUMDUM, Ghugudanga | O42: KOLKATA | P42: WEST BENGAL | Q42: 700030 | R42: Jun 06, 2025 | S42: Perpetual | U42: Research Analyst | V42: No | W42: Research Analyst | X42: gmail.com | Y42: free_personal_email | Z42: individual_practitioner | AA42: 100 | AB42: 10 | AC42: D - Ignore | AD42: NAME::ANKITA MUKHERJEE | AE42: individual_free_email_low_priority | AG42: Do not target in first campaign
A43: ANKUR CHOUDHARY | B43: INA300004853 | D43: 2-B ANKUR APARTMENT, BANSIKUNJ,, DR R P ROAD | E43: ankurc07@gmail.com | F43: 8069000068 | G43: 8069000068 | H43: BHAGALPUR | I43: BIHAR | J43: 812002 | R43: May 31, 2016 | S43: Perpetual | U43: Investment Adviser | V43: No | W43: Investment Adviser | X43: gmail.com | Y43: free_personal_email | Z43: individual_practitioner | AA43: 85 | AB43: 12 | AC43: D - Ignore | AD43: NAME::ANKUR CHOUDHARY | AE43: individual_free_email_low_priority | AG43: Do not target in first campaign
A44: ANKUSH PATEL | B44: INH000027706 | C44: ANKUSH PATEL | D44: Gram Agdal post amiliya | E44: ankushpatelra@gmail.com | F44: 009074590674 | G44: 009074590674 | H44: REWA | I44: MADHYA PRADESH | J44: 486115 | K44: Gram Agdal post amiliya | O44: REWA | P44: MADHYA PRADESH | Q44: 486115 | R44: Jun 02, 2026 | S44: Perpetual | U44: Research Analyst | V44: No | W44: Research Analyst | X44: gmail.com | Y44: free_personal_email | Z44: individual_practitioner | AA44: 100 | AB44: 5 | AC44: D - Ignore | AD44: NAME::ANKUSH PATEL | AE44: individual_free_email_low_priority | AG44: Do not target in first campaign
A45: ANSHUL PAHWA | B45: INH000025771 | C45: ANSHUL PAHWA | D45: HOUSE NO -28-29 KRISHNA NAGAR REWARI REWARI | E45: askniveshguru@gmail.com | F45: 0000000000000 | G45: 0000000000000 | H45: GURUGRAM | I45: HARYANA | J45: 123401 | K45: HOUSE NO -28-29 KRISHNA NAGAR REWARI REWARI | O45: GURUGRAM | P45: HARYANA | Q45: 123401 | R45: Apr 09, 2026 | S45: Perpetual | U45: Research Analyst | V45: No | W45: Research Analyst | X45: gmail.com | Y45: free_personal_email | Z45: individual_practitioner | AA45: 100 | AB45: 10 | AC45: D - Ignore | AD45: NAME::ANSHUL PAHWA | AE45: individual_free_email_low_priority | AG45: Do not target in first campaign
A46: ANSUL KUMAR AGRAWAL | B46: INH000016092 | C46: ANSUL AGRAWAL | D46: Vastraganga, Chowk,, Ballia City | E46: ansul147@gmail.com | F46: 917860648645 | H46: BALLIA | I46: UTTAR PRADESH | J46: 277001 | K46: Vastraganga, Chowk, Ballia City | O46: BALLIA | P46: UTTAR PRADESH | Q46: 277001 | R46: May 07, 2024 | S46: Perpetual | U46: Research Analyst | V46: No | W46: Research Analyst | X46: gmail.com | Y46: free_personal_email | Z46: individual_practitioner | AA46: 100 | AB46: 5 | AC46: D - Ignore | AD46: NAME::ANSUL KUMAR AGRAWAL | AE46: individual_free_email_low_priority | AG46: Do not target in first campaign
A47: ANUBRATA DAS | B47: INH000020998 | C47: ANUBRATA DAS | D47: 21 Rajani Kanta Sen Sarani Road Hakimpara, Siliguri MCorp | E47: ra.anubrata@gmail.com | F47: 918609608080 | H47: SILIGURI | I47: WEST BENGAL | J47: 734001 | K47: 21 Rajani Kanta Sen Sarani Road Hakimpara, Siliguri MCorp | O47: SILIGURI | P47: WEST BENGAL | Q47: 734001 | R47: Jun 17, 2025 | S47: Perpetual | U47: Research Analyst | V47: No | W47: Research Analyst | X47: gmail.com | Y47: free_personal_email | Z47: individual_practitioner | AA47: 100 | AB47: 5 | AC47: D - Ignore | AD47: NAME::ANUBRATA DAS | AE47: individual_free_email_low_priority | AG47: Do not target in first campaign
A48: ANUGYA SINGH | B48: INA000009959 | C48: ANUGYA SINGH | D48: Office No. 1309, Skye Corporate Park,, Scheme No. 78, Vijay Nagar, | E48: ANUGYASINGH05@GMAIL.COM | H48: INDORE | I48: MADHYA PRADESH | J48: 452010 | K48: 101 First Floor, 79 Radhika Palace, Tulsi Nagar | O48: INDORE | P48: MADHYA PRADESH | Q48: 452010 | R48: Mar 01, 2018 | S48: Perpetual | U48: Investment Adviser | V48: No | W48: Investment Adviser | X48: gmail.com | Y48: free_personal_email | Z48: individual_practitioner | AA48: 90 | AB48: 7 | AC48: D - Ignore | AD48: NAME::ANUGYA SINGH | AE48: individual_free_email_low_priority | AG48: Do not target in first campaign
A49: ANUJ GUPTA | B49: INH000025656 | C49: ANUJ GUPTA | D49: B-2/206, YAMUNA VIHAR | E49: ANUJLLB206@GMAIL.COM | H49: DELHI | I49: NATIONAL CAPITAL TERRITORY OF DELHI | J49: 110053 | R49: Apr 01, 2026 | S49: Perpetual | U49: Research Analyst | V49: No | W49: Research Analyst | X49: gmail.com | Y49: free_personal_email | Z49: individual_practitioner | AA49: 90 | AB49: 0 | AC49: D - Ignore | AD49: NAME::ANUJ GUPTA | AE49: individual_free_email_low_priority | AG49: Do not target in first campaign
A50: ANUJ SHARMA | B50: INH000023311 | C50: ANUJ SHARMA | D50: HOUSE NO 2343 SECTOR 28, FARIDABAD | E50: anuj_2343@hotmail.com | F50: 918800295778 | G50: 918800295778 | H50: FARIDABAD | I50: HARYANA | J50: 121008 | R50: Sep 15, 2025 | S50: Perpetual | U50: Research Analyst | V50: No | W50: Research Analyst | X50: hotmail.com | Y50: free_personal_email | Z50: individual_practitioner | AA50: 100 | AB50: 5 | AC50: D - Ignore | AD50: NAME::ANUJ SHARMA | AE50: individual_free_email_low_priority | AG50: Do not target in first campaign
A51: ANUJAY CHOUHAN | B51: INH000027779 | C51: ANUJAY CHOUHAN | D51: C 20/1 MAHANANDA NAGAR , UJJAIN | E51: chouhananujay@gmail.com | F51: 00008602027324 | G51: 00008602027324 | H51: UJJAIN | I51: MADHYA PRADESH | J51: 456010 | K51: C 20/1 MAHANANDA NAGAR , UJJAIN | O51: UJJAIN | P51: MADHYA PRADESH | Q51: 456010 | R51: Jun 03, 2026 | S51: Perpetual | U51: Research Analyst | V51: No | W51: Research Analyst | X51: gmail.com | Y51: free_personal_email | Z51: individual_practitioner | AA51: 100 | AB51: 5 | AC51: D - Ignore | AD51: NAME::ANUJAY CHOUHAN | AE51: individual_free_email_low_priority | AG51: Do not target in first campaign
A52: ANURAG CHAUDHARY | B52: INH000026220 | C52: ANURAG CHAUDHARY | D52: D - 506, Block D, Near Bank of Baroda, Rajaji Puram | E52: anurag4u10@gmail.com | F52: 00000000000000 | G52: 00000000000000 | H52: LUCKNOW | I52: UTTAR PRADESH | J52: 226017 | R52: Apr 16, 2026 | S52: Perpetual | U52: Research Analyst | V52: No | W52: Research Analyst | X52: gmail.com | Y52: free_personal_email | Z52: individual_practitioner | AA52: 100 | AB52: 5 | AC52: D - Ignore | AD52: NAME::ANURAG CHAUDHARY | AE52: individual_free_email_low_priority | AG52: Do not target in first campaign
A53: ANURAG SINGHAL | B53: INA000021775 | C53: ANURAG SINGHAL | D53: FLAT No. D/A/202, SHRI RADHA VALLEY, MATHURA BANGAR, PO, KRISHNA NAGAR | E53: rccmathura@gmail.com | H53: MATHURA | I53: UTTAR PRADESH | J53: 281004 | K53: FLAT No. D/A/202, SHRI RADHA VALLEY, MATHURA BANGAR, PO, KRISHNA NAGAR | O53: MATHURA | P53: UTTAR PRADESH | Q53: 281004 | R53: Feb 03, 2026 | S53: Perpetual | U53: Investment Adviser | V53: No | W53: Investment Adviser | X53: gmail.com | Y53: free_personal_email | Z53: individual_practitioner | AA53: 90 | AB53: 2 | AC53: D - Ignore | AD53: NAME::ANURAG SINGHAL | AE53: individual_free_email_low_priority | AG53: Do not target in first campaign
A54: APNARESEARCHPLUS | B54: INH000012670 | C54: OM PANDEY | D54: H. No. B-27/92-6-A, HANUMANPURA, BHADAINI, WARD BHELUPUR | E54: OMPRAKASH12APNAPLUS@GMAIL.COM | H54: VARANASI | I54: UTTAR PRADESH | J54: 221010 | K54: H. No. B-27/92-6-A, HANUMANPURA, BHADAINI, WARD BHELUPUR | O54: VARANASI | P54: UTTAR PRADESH | Q54: 221010 | R54: Aug 23, 2023 | S54: Perpetual | U54: Research Analyst | V54: No | W54: Research Analyst | X54: gmail.com | Y54: free_personal_email | Z54: individual_practitioner | AA54: 90 | AB54: 0 | AC54: D - Ignore | AD54: NAME::APNARESEARCHPLUS | AE54: individual_free_email_low_priority | AG54: Do not target in first campaign
A55: APURVA HARSH VIRA | B55: INH000024064 | C55: APURVA ANNAVI | D55: C 207, SHANTI SHOPING CENTRE, MIRA ROAD East | E55: WORKWITHAPURVA247@GMAIL.COM | F55: 918789603462 | H55: THANE | I55: MAHARASHTRA | J55: 401107 | K55: C 207, SHANTI SHOPING CENTRE, MIRA ROAD East | O55: THANE | P55: MAHARASHTRA | Q55: 401107 | R55: Dec 11, 2025 | S55: Perpetual | U55: Research Analyst | V55: No | W55: Research Analyst | X55: gmail.com | Y55: free_personal_email | Z55: individual_practitioner | AA55: 100 | AB55: 10 | AC55: D - Ignore | AD55: NAME::APURVA HARSH VIRA | AE55: individual_free_email_low_priority | AG55: Do not target in first campaign
A56: ARIDAMAN SHARMA | B56: INH000027317 | C56: ARIDAMAN SHARMA | D56: FLAT 702 J BLOCK VIKRAM VIHAR, AWHO SECTOR 27 PANCHKULA | E56: adsharma007@gmail.com | F56: 00001724640650 | G56: 00001724640650 | H56: Panchkula | I56: HARYANA | J56: 134116 | R56: May 19, 2026 | S56: Perpetual | U56: Research Analyst | V56: No | W56: Research Analyst | X56: gmail.com | Y56: free_personal_email | Z56: individual_practitioner | AA56: 100 | AB56: 5 | AC56: D - Ignore | AD56: NAME::ARIDAMAN SHARMA | AE56: individual_free_email_low_priority | AG56: Do not target in first campaign
A57: ARIJIT BANERJEE | B57: INH300006582 | C57: ARIJIT BANERJEE | D57: Ichapur Goalapara Gurudwara | E57: goodluckcapital@gmail.com | F57: 919477838855 | G57: 919477838855 | H57: KOLKATA | I57: WEST BENGAL | J57: 743144 | K57: Ichapur Goalapara Gurudwara | O57: KOLKATA | P57: WEST BENGAL | Q57: 743144 | R57: Nov 12, 2018 | S57: Perpetual | U57: Research Analyst | V57: No | W57: Research Analyst | X57: gmail.com | Y57: free_personal_email | Z57: individual_practitioner | AA57: 100 | AB57: 10 | AC57: D - Ignore | AD57: NAME::ARIJIT BANERJEE | AE57: individual_free_email_low_priority | AG57: Do not target in first campaign
A58: ARIJIT MAZUMDAR | B58: INA300011609 | C58: ARIJIT MAZUMDAR | D58: HARIDRADANGA,GOALAPARA, PO&PS-CHANDANNAGORE | E58: arijit.maz@gmail.com | F58: 919748805020 | H58: KOLKATA | I58: WEST BENGAL | J58: 712136 | K58: HARIDRADANGA,GOALAPARA, PO&PS-CHANDANNAGORE | O58: KOLKATA | P58: WEST BENGAL | Q58: 712136 | R58: Sep 04, 2018 | S58: Perpetual | U58: Investment Adviser | V58: No | W58: Investment Adviser | X58: gmail.com | Y58: free_personal_email | Z58: individual_practitioner | AA58: 100 | AB58: 17 | AC58: D - Ignore | AD58: NAME::ARIJIT MAZUMDAR | AE58: individual_free_email_low_priority | AG58: Do not target in first campaign
A59: ARJIT RAJEEV GARG | B59: INH000021951 | C59: ARJIT GARG | D59: Flat no 2701, Tower A4, ,Polaris, Runwl Mycity, Diva Mapada Road,Betavade, Dombivali E | E59: arjit.r.garg@gmail.com | F59: 919819890359 | H59: THANE | I59: MAHARASHTRA | J59: 400612 | K59: Flat no 2701, Tower A4, ,Polaris, Runwl Mycity, Diva Mapada Road,Betavade, Dombivali E | O59: THANE | P59: MAHARASHTRA | Q59: 400612 | R59: Jul 18, 2025 | S59: Perpetual | U59: Research Analyst | V59: No | W59: Research Analyst | X59: gmail.com | Y59: free_personal_email | Z59: individual_practitioner | AA59: 100 | AB59: 10 | AC59: D - Ignore | AD59: NAME::ARJIT RAJEEV GARG | AE59: individual_free_email_low_priority | AG59: Do not target in first campaign
A60: ARNAB CHABIRI | B60: INH000027955 | C60: ARNAB CHABIRI | D60: Flat No. A 207, Khushi Harmony, Near Sapsasti Vihar Palasuni | E60: achabiri@outlook.com | F60: 0006371592224 | G60: 0006371592224 | H60: BHUBANESWAR | I60: ODISHA | J60: 751017 | K60: Flat No. A 207, Khushi Harmony, Near Sapsasti Vihar Palasuni | O60: BHUBANESWAR | P60: ODISHA | Q60: 751017 | R60: Jun 08, 2026 | S60: Perpetual | U60: Research Analyst | V60: No | W60: Research Analyst | X60: outlook.com | Y60: free_personal_email | Z60: individual_practitioner | AA60: 100 | AB60: 5 | AC60: D - Ignore | AD60: NAME::ARNAB CHABIRI | AE60: individual_free_email_low_priority | AG60: Do not target in first campaign
A61: ARPAN KUKREJA | B61: INH000015358 | C61: ARPAN KUKREJA | D61: 2F 34, Ward 11, NH 2, Near Lakhani Dharamshala | E61: arpan.923kukreja2@gmail.com | H61: FARIDABAD | I61: HARYANA | J61: 121001 | K61: 2F 34, Ward 11, NH 2, Near Lakhani Dharamshala | O61: FARIDABAD | P61: HARYANA | Q61: 121001 | R61: Mar 04, 2024 | S61: Perpetual | U61: Research Analyst | V61: No | W61: Research Analyst | X61: gmail.com | Y61: free_personal_email | Z61: individual_practitioner | AA61: 90 | AB61: 0 | AC61: D - Ignore | AD61: NAME::ARPAN KUKREJA | AE61: individual_free_email_low_priority | AG61: Do not target in first campaign
A62: ARPIT AGARWAL | B62: INA000021641 | C62: ARPIT AGARWAL | D62: B 1206, PRATEEK FEDORA, SECTOR 61, NOIDA | E62: arpit2491@gmail.com | F62: 00919953278236 | G62: 00919953278236 | H62: NOIDA | I62: UTTAR PRADESH | J62: 201301 | K62: B 1206, PRATEEK FEDORA, SECTOR 61, NOIDA | O62: NOIDA | P62: UTTAR PRADESH | Q62: 201301 | R62: Dec 30, 2025 | S62: Perpetual | U62: Investment Adviser | V62: No | W62: Investment Adviser | X62: gmail.com | Y62: free_personal_email | Z62: individual_practitioner | AA62: 100 | AB62: 17 | AC62: D - Ignore | AD62: NAME::ARPIT AGARWAL | AE62: individual_free_email_low_priority | AG62: Do not target in first campaign
A63: ARPIT KUSHWAHA | B63: INH000023241 | C63: ARPIT KUSHWAHA | D63: O1,Bhola ka pura,sulem sarai | E63: Singharpit2498@gmail.com | F63: 918920522564 | H63: PRAYAGRAJ | I63: UTTAR PRADESH | J63: 211011 | R63: Sep 15, 2025 | S63: Perpetual | U63: Research Analyst | V63: No | W63: Research Analyst | X63: gmail.com | Y63: free_personal_email | Z63: individual_practitioner | AA63: 100 | AB63: 5 | AC63: D - Ignore | AD63: NAME::ARPIT KUSHWAHA | AE63: individual_free_email_low_priority | AG63: Do not target in first campaign
A64: ARPITA VIJAYVARGIYA | B64: INH000026983 | C64: ARPITA VIJAYVARGIYA | D64: B 6 263, Sudarshana Nagar,, Near Rajiv Gandhi Nursing School | E64: raarpita.vijay@gmail.com | F64: 0009587265921 | G64: 0009587265921 | H64: BIKANER | I64: RAJASTHAN | J64: 334003 | R64: May 12, 2026 | S64: Perpetual | U64: Research Analyst | V64: No | W64: Research Analyst | X64: gmail.com | Y64: free_personal_email | Z64: individual_practitioner | AA64: 100 | AB64: 5 | AC64: D - Ignore | AD64: NAME::ARPITA VIJAYVARGIYA | AE64: individual_free_email_low_priority | AG64: Do not target in first campaign
A65: ARTH SADHANA | B65: INH000020341 | C65: CHANDAN KUMAR | D65: 261 A, MANDIR MARG, NEW A.G. CO OPRATIVE COLONY, Blind School, Kadru, Ranchi | E65: arthsadhana.rnc@gmail.com | F65: 919031656500 | G65: 919031656500 | H65: RANCHI | I65: JHARKHAND | J65: 834002 | K65: 261 A, MANDIR MARG, NEW A.G. CO OPRATIVE COLONY, Blind School, Kadru, Ranchi | O65: RANCHI | P65: JHARKHAND | Q65: 834002 | R65: Apr 21, 2025 | S65: Perpetual | U65: Research Analyst | V65: No | W65: Research Analyst | X65: gmail.com | Y65: free_personal_email | Z65: individual_practitioner | AA65: 100 | AB65: 5 | AC65: D - Ignore | AD65: NAME::ARTH SADHANA | AE65: individual_free_email_low_priority | AG65: Do not target in first campaign
A66: ARUL MOZHI CHELVAN MURUGAN | B66: INH000016287 | C66: ARUL MOZHI CHELVAN MURUGAN | D66: Flat No. G3 Raaj Paradise, Poonga Street ,Opposite to Tirunagar Police Station,Tirunagar | E66: arulmozhichelvan.m@gmail.com | H66: MADURAI | I66: TAMIL NADU | J66: 625006 | K66: Flat No. G3 Raaj Paradise, Poonga Street ,Opposite to Tirunagar Police Station,Tirunagar | O66: MADURAI | P66: TAMIL NADU | Q66: 625006 | R66: Jun 13, 2024 | S66: Perpetual | U66: Research Analyst | V66: No | W66: Research Analyst | X66: gmail.com | Y66: free_personal_email | Z66: individual_practitioner | AA66: 90 | AB66: 0 | AC66: D - Ignore | AD66: NAME::ARUL MOZHI CHELVAN MURUGAN | AE66: individual_free_email_low_priority | AG66: Do not target in first campaign
A67: ARUL SONI | B67: INH000025267 | C67: ARUL SONI | D67: 1 Near SBBJ ATM Station Road, Baran | E67: caarulsoni@gmail.com | F67: 919829977677 | H67: CHHABRA | I67: RAJASTHAN | J67: 325220 | K67: 1 Near SBBJ ATM Station Road, Baran | O67: CHHABRA | P67: RAJASTHAN | Q67: 325220 | R67: Mar 09, 2026 | S67: Perpetual | U67: Research Analyst | V67: No | W67: Research Analyst | X67: gmail.com | Y67: free_personal_email | Z67: individual_practitioner | AA67: 100 | AB67: 5 | AC67: D - Ignore | AD67: NAME::ARUL SONI | AE67: individual_free_email_low_priority | AG67: Do not target in first campaign
A68: ARUN | B68: INH200007353 | C68: ARUN NACHIMUTHU | D68: 160 2 , VAYALUR , PUSHPATHUR POST , PALANI TALUK | E68: arungcteee06@gmail.com | H68: MADURAI | I68: TAMIL NADU | J68: 624618 | K68: 160 2 , VAYALUR , PUSHPATHUR POST , PALANI TALUK | O68: MADURAI | P68: TAMIL NADU | Q68: 624618 | R68: Aug 28, 2019 | S68: Perpetual | U68: Research Analyst | V68: No | W68: Research Analyst | X68: gmail.com | Y68: free_personal_email | Z68: individual_practitioner | AA68: 90 | AB68: 0 | AC68: D - Ignore | AD68: NAME::ARUN | AE68: individual_free_email_low_priority | AG68: Do not target in first campaign
A69: ARUN KUMAR MANTRI | B69: INA200016555 | C69: ARUN MANTRI | D69: H NO 16-2-147/16/5 ANAND NAGAR, MALAKPET | E69: ca.arunmantri@gmail.com | H69: HYDERABAD | I69: TELANGANA | J69: 500036 | K69: H NO 16-2-147/16/5 ANAND NAGAR, MALAKPET | O69: HYDERABAD | P69: TELANGANA | Q69: 500036 | R69: Jan 24, 2022 | S69: Perpetual | U69: Investment Adviser | V69: No | W69: Investment Adviser | X69: gmail.com | Y69: free_personal_email | Z69: individual_practitioner | AA69: 90 | AB69: 7 | AC69: D - Ignore | AD69: NAME::ARUN KUMAR MANTRI | AE69: individual_free_email_low_priority | AG69: Do not target in first campaign
A70: ARUNKUMAR DALPATBHAI RANGPARIYA | B70: INH000005519 | C70: Arunkumar Rangpariya | D70: 2 sanskar tenament, Nikol Naroda Road, Nr, sukan Char Rasta, Opp. Radhika Bunglow, Ghanshyam villa soci., gate | E70: arunrangpariya@yahoo.co.in | H70: AHMEDABAD | I70: GUJARAT | J70: 382350 | K70: 2 sanskar tenament, Nikol Naroda Road, Nr, sukan Char Rasta, Opp. Radhika Bunglow, Ghanshyam villa soci., gate | O70: AHMEDABAD | P70: GUJARAT | Q70: 382350 | R70: Dec 12, 2017 | S70: Perpetual | U70: Research Analyst | V70: No | W70: Research Analyst | X70: yahoo.co.in | Y70: free_personal_email | Z70: individual_practitioner | AA70: 90 | AB70: 0 | AC70: D - Ignore | AD70: NAME::ARUNKUMAR DALPATBHAI RANGPARIYA | AE70: individual_free_email_low_priority | AG70: Do not target in first campaign
A71: ARVIND MANGAL | B71: INH000010450 | C71: ARVIND MANGAL | D71: FIRST FLOOR B.L. JANGID COMPLEX, NEAR BUS STAND PAOTA | E71: CAARVINDKNARAYAN@YAHOO.COM | H71: JAIPUR | I71: RAJASTHAN | J71: 303106 | K71: FIRST FLOOR B.L. JANGID COMPLEX, NEAR BUS STAND PAOTA | O71: JAIPUR | P71: RAJASTHAN | Q71: 303106 | R71: Oct 28, 2022 | S71: Perpetual | U71: Research Analyst | V71: No | W71: Research Analyst | X71: yahoo.com | Y71: free_personal_email | Z71: individual_practitioner | AA71: 90 | AB71: 0 | AC71: D - Ignore | AD71: NAME::ARVIND MANGAL | AE71: individual_free_email_low_priority | AG71: Do not target in first campaign
A72: ASHISH BEDI | B72: INH000021599 | C72: ASHISH BEDI | D72: D 001, Jaipuria Sunrise Green, VIP Road, Zirakpur, SAS Nagar, Mohali | E72: ashishbediresearchanalyst@yahoo.com | F72: 917988121534 | H72: MOHALI | I72: PUNJAB | J72: 140603 | K72: D 001, Jaipuria Sunrise Green, VIP Road, Zirakpur, SAS Nagar, Mohali | O72: MOHALI | P72: PUNJAB | Q72: 140603 | R72: Jul 07, 2025 | S72: Perpetual | U72: Research Analyst | V72: No | W72: Research Analyst | X72: yahoo.com | Y72: free_personal_email | Z72: individual_practitioner | AA72: 100 | AB72: 5 | AC72: D - Ignore | AD72: NAME::ASHISH BEDI | AE72: individual_free_email_low_priority | AG72: Do not target in first campaign
A73: ASHISH CHAUDHARY | B73: INA000020943 | C73: ASHISH CHAUDHARY | D73: A-268 , Vikas Puri New Delhi | E73: ashish12.chaudhary@gmail.com | F73: 00918287647430 | G73: 00918287647430 | H73: NEW DELHI | I73: NATIONAL CAPITAL TERRITORY OF DELHI | J73: 110018 | K73: A-268 , Vikas Puri New Delhi | O73: NEW DELHI | P73: NATIONAL CAPITAL TERRITORY OF DELHI | Q73: 110018 | R73: Aug 20, 2025 | S73: Perpetual | U73: Investment Adviser | V73: No | W73: Investment Adviser | X73: gmail.com | Y73: free_personal_email | Z73: individual_practitioner | AA73: 100 | AB73: 17 | AC73: D - Ignore | AD73: NAME::ASHISH CHAUDHARY | AE73: individual_free_email_low_priority | AG73: Do not target in first campaign
